Workbook

Sheet 00_封面与口径
A1: 宇树科技股份有限公司（688836.SH）经营与财务表现分析底稿
A2: 本底稿为可编辑分析工作簿：所有『核心计算』表中的比率、增速、倍数均由 Excel 公式实时引用『原始数据』表得出，修改任一原始数据后计算结果与图表会自动重算。
A4: 一、基本信息
A5: 发行人全称 | B5: 宇树科技股份有限公司（Yushu Technology Co., Ltd.） | D5: S1/S2
A6: 注册地址 | B6: 浙江省杭州市滨江区西兴街道东流路88号1幢 | D6: S1/S2
A7: 证券代码 / 简称 | B7: 688836 / 宇树科技-W（“W”标识存在特别表决权安排） | D7: S1/S2
A8: 上市板块 | B8: 上海证券交易所 科创板 | D8: S1/S2
A9: 上市日期 | B9: 2026年8月19日 | D9: S1/S2
A10: 主营业务 | B10: 高性能通用人形机器人、四足机器人、机器人组件及具身智能模型的研发、生产和销售 | D10: S1/S2
A11: 所属行业（证监会GB/T4754-2017） | B11: C34 通用设备制造业 | D11: S1/S2
A12: 保荐人（主承销商） | B12: 中信证券股份有限公司 | D12: S1/S2
A13: 会计师事务所 | B13: 容诚会计师事务所（特殊普通合伙） | D13: S1/S2
A14: 发行人律师 | B14: 北京德恒律师事务所 | D14: S1/S2
A15: 实际控制人 | B15: 王兴兴 | D15: S1/S2
A17: 二、资料截止日与报告期口径（重要）
A18: 资料截止日 | B18: 2026年8月30日 | D18: S1/S2
A19: 审计截止日 | B19: 2025年12月31日（三年一期中的“三年”） | D19: S1/S2
A20: 经审计报告期 | B20: 2023年度、2024年度、2025年度（容诚审字[2026]230Z1692号，标准无保留意见） | D20: S1/S2
A21: 经审阅期间 | B21: 2026年1-3月（容诚阅字[2026]230Z0038号） | D21: S1/S2
A22: 未经审计期间 | B22: 2026年1-6月（载于上市公告书；公司明示上市后不再单独披露2026年半年度报告） | D22: S1/S2
A23: 行情数据截止 | B23: 2026年8月28日收盘（截止日前最后一个交易日；8月31日数据超出截止日，本底稿不纳入） | D23: S1/S2
A25: 三、统一单位与格式约定
A26: 金额单位 | B26: 除特别注明外，全部金额单位为【人民币万元】，与招股说明书披露口径一致
A27: 亿元换算 | B27: 如需亿元，请在公式中除以10,000；本底稿不混用单位
A28: 比率存储方式 | B28: 百分比类指标以小数存储（如0.6013），通过单元格格式显示为60.13%
A29: 每股指标单位 | B29: 元/股
A30: 股本单位 | B30: 股（发行前后总股本表另以万股列示，已标注）
A31: 颜色约定 | B31: 蓝色=原始披露数据；绿色=公式计算结果；黄色=口径/提示说明；橙色=需人工核验
A33: 四、数据性质分级（严格区分事实与预测）
A34: 性质代码 | B34: 含义 | C34: 对应期间 | D34: 使用限制
A35: A 经审计 | B35: 容诚会计师事务所审计，标准无保留意见 | C35: 2023/2024/2025年度 | D35: 可作为既成事实引用
A36: B 经审阅 | B36: 容诚会计师事务所审阅（非审计） | C36: 2026年1-3月 | D36: 可引用，需注明“经审阅、未经审计”
A37: C 未经审计 | B37: 公司董事会审议通过并披露，未经审计或审阅 | C37: 2026年1-6月 | D37: 可引用，必须注明“未经审计”
A38: D 管理层预计 | B38: 招股说明书中管理层对2026年1-6月的合理估计，公司明示不构成盈利预测或业绩承诺 | C38: 2026年1-6月（预计区间） | D38: 严禁表述为已发生事实；本底稿单列于表3-4并全程标注
A39: E 分析师测算 | B39: 本底稿基于披露数据自行推算（如年化、倍数），非公司指引 | C39: 视指标而定 | D39: 必须标注“测算”，不得归因于公司
A41: 特别提示：招股说明书披露的“2026年1-6月财务数据预计”属于性质D，原文载明“为管理层对经营状况的合理估计，不代表公司最终实现的营业收入及净利润，相关数据未经会计师审计或审阅，不构成公司的盈利预测或业绩承诺”。该预计区间（营业收入105,200万至112,800万元）与上市公告书披露的实际数（115,224.56万元）不同，本底稿在表7-8中将两者并列对比，不得互相替代。
A43: 五、免责声明
A44: 本底稿仅为基于公开披露文件的信息整理与财务分析工作底稿，不构成任何证券投资建议、评级或估值结论。所有数据以上海证券交易所披露的正式文件为准；使用前请完成表『10_待人工核验』中列示的核对事项。

Sheet 01_资料来源
A1: 资料来源清单（按权威等级排序）
A2: 编号 S1–S8 为上海证券交易所法定信息披露文件（一手来源，权威等级最高）；S9 为行情数据（第三方，仅用于市场表现）；S10 为公司官方渠道（本次分析未直接引用，列入待补）。全表“本底稿引用位置”列指明该来源支撑的数据表。
A3: 来源编号 | B3: 文件名称 | C3: 披露/发布主体 | D3: 披露日期 | E3: 权威等级 | F3: 文件标识（art_code / 文号） | G3: 获取路径 | H3: 本底稿引用位置
A4: S1 | B4: 宇树科技股份有限公司首次公开发行股票并在科创板上市招股说明书 | C4: 宇树科技（上交所披露） | D4: 2026-08-14 | E4: 一手·法定披露 | F4: AN202608131827947910（382页PDF） | G4: 东方财富披露镜像 pdf.dfcfw.com/pdf/H2_AN202608131827947910_1.pdf；原件应核 www.sse.com.cn | H4: 表3-1、3-2、3-4；表4-1~4-7；表5-1~5-3；表6-1、6-3
A5: S2 | B5: 宇树科技首次公开发行股票科创板上市公告书 | C5: 宇树科技（上交所披露） | D5: 2026-08-18 | E5: 一手·法定披露 | F5: AN202608171828062024（90页PDF） | G5: 东方财富披露镜像 pdf.dfcfw.com/pdf/H2_AN202608171828062024_1.pdf；原件应核 www.sse.com.cn | H5: 表2-1；表3-3；表6-2、6-4
A6: S3 | B6: 宇树科技首次公开发行股票科创板上市公告书提示性公告 | C6: 宇树科技（上交所披露） | D6: 2026-08-18 | E6: 一手·法定披露 | F6: AN202608171828062022 | G6: 东方财富披露镜像 | H6: 发行市盈率四口径、市销率、市净率交叉验证
A7: S4 | B7: 宇树科技首次公开发行股票并在科创板上市发行结果公告 | C7: 宇树科技（上交所披露） | D7: 2026-08-14 | E7: 一手·法定披露 | F7: AN202608131827947823 | G7: 东方财富披露镜像 | H7: 募集资金总额/净额、发行费用交叉验证
A8: S5 | B8: 宇树科技首次公开发行股票并在科创板上市发行公告 | C8: 宇树科技（上交所披露） | D8: 2026-08-07 | E8: 一手·法定披露 | F8: AN202608061827718855 | G8: 东方财富披露镜像 | H8: 发行价格确定、行业市盈率、可比公司市销率
A9: S6 | B9: 宇树科技首次公开发行股票并在科创板上市招股意向书 | C9: 宇树科技（上交所披露） | D9: 2026-07-31 | E9: 一手·法定披露 | F9: AN202607301827499558 | G9: 东方财富披露镜像 | H9: 审计报告/审阅报告全文附录（未逐页引用）
A10: S7 | B10: 关于同意宇树科技股份有限公司首次公开发行股票注册的批复 | C10: 中国证监会 | D10: 2026-07-02 | E10: 一手·监管文件 | F10: AN202607061826748666 | G10: 东方财富披露镜像 | H10: 注册生效时点
A11: S8 | B11: 上海证券交易所上市审核委员会2026年第31次审议会议结果公告 | C11: 上海证券交易所 | D11: 2026-06-01 | E11: 一手·监管文件 | F11: AN202606011823128106 | G11: 东方财富披露镜像 | H11: 过会时点
A12: S9 | B12: 688836 日K线行情（2026-08-19至2026-08-28） | C12: 东方财富行情接口 push2his.eastmoney.com | D12: 2026-08-28 | E12: 第三方·行情 | F12: secid=1.688836, klt=101, fqt=0 | G12: 接口直接取数 | H12: 表2-2；图8
A13: S10 | B13: 宇树科技官方网站 / 官方公众号 | C13: 宇树科技 | D13: — | E13: 公司官方·待补 | F13: 未取用 | G13: 本次分析未直接引用 | H13: 列入待核验：产品定价、出货量口径、官网披露与招股书差异
A15: 取数说明：S1、S2 为本底稿的绝对主来源，全部财务与业务数据均逐字提取自该两份 PDF 原文表格，未采用任何媒体转述数值。分析过程中曾出现媒体转述数据与原文冲突的情况（详见表10），均已以 S1/S2 原文为准修正。

Sheet 02_发行上市原始数据
A1: 表2-1 本次发行与上市基本情况（原始披露数据）
A2: 项目 | B2: 数值 | C2: 数据性质 | D2: 来源
A3: 【发行方案】
A4: 每股面值（元） | B4: 1 | C4: A | D4: S2
A5: 发行价格（元/股） | B5: 150.8 | C5: A | D5: S2
A6: 发行股票数量（股） | B6: 40446434 | C6: A | D6: S2
A7: 发行股票数量（万股） | B7: 4044.6434 | C7: A | D7: S2
A8: 新股发行占发行后总股本比例 | B8: 0.1 | C8: A | D8: S2
A9: 发行前总股本（万股） | B9: 36401.791 | C9: A | D9: S1
A10: 发行后总股本（股） | B10: 404464340 | C10: A | D10: S2
A11: 发行后总股本（万股） | B11: 40446.434 | C11: A | D11: S2
A12: 是否涉及老股转让 | B12: 否 | C12: A | D12: S2
A13: 是否行使超额配售选择权 | B13: 否 | C13: A | D13: S2
A14: 【发行方式与结果】
A15: 最终战略配售数量（股） | B15: 8089286 | C15: A | D15: S2
A16: 战略配售占本次发行数量比例 | B16: 0.2 | C16: A | D16: S2
A17: 网下最终发行数量（股） | B17: 22650148 | C17: A | D17: S2
A18: 网下投资者缴款认购（股） | B18: 22650148 | C18: A | D18: S2
A19: 网下放弃认购（股） | B19: 0 | C19: A | D19: S2
A20: 网上最终发行数量（股） | B20: 9707000 | C20: A | D20: S2
A21: 网上投资者缴款认购（股） | B21: 9698266 | C21: A | D21: S2
A22: 网上放弃认购（股） | B22: 8734 | C22: A | D22: S2
A23: 保荐人（主承销商）包销数量（股） | B23: 8734 | C23: A | D23: S2
A24: 发行后股东户数（户） | B24: 27666 | C24: A | D24: S2
A25: 【募集资金】
A26: 募集资金总额（万元） | B26: 609932.22 | C26: A | D26: S2
A27: 发行费用合计（不含增值税，万元） | B27: 18217.31 | C27: A | D27: S2
A28: 承销及保荐费（万元） | B28: 14499.32 | C28: A | D28: S2
A29: 审计及验资费（万元） | B29: 1828.3 | C29: A | D29: S2
A30: 律师费（万元） | B30: 1100 | C30: A | D30: S2
A31: 用于本次发行的信息披露费（万元） | B31: 603.77 | C31: A | D31: S2
A32: 发行手续费及其他费用（万元） | B32: 185.91 | C32: A | D32: S2
A33: 募集资金净额（万元） | B33: 591714.92 | C33: A | D33: S2
A34: 验资报告 | B34: 容诚验字[2026]230Z0118号（2026年8月14日出具） | C34: A | D34: S2
A35: 【发行估值倍数（按发行价150.80元/股）】
A36: 发行市盈率①：2025年扣非后归母净利 ÷ 发行前总股本 | B36: 92.92 | C36: A | D36: S2/S3
A37: 发行市盈率②：2025年扣非前归母净利 ÷ 发行前总股本 | B37: 197.31 | C37: A | D37: S2/S3
A38: 发行市盈率③：2025年扣非后归母净利 ÷ 发行后总股本 | B38: 103.25 | C38: A | D38: S2/S3
A39: 发行市盈率④：2025年扣非前归母净利 ÷ 发行后总股本（公告口径“本次发行市盈率”，按孰低） | B39: 219.23 | C39: A | D39: S2/S3
A40: 发行市销率①：2025年营业收入 ÷ 发行前总股本 | B40: 32.3 | C40: A | D40: S2
A41: 发行市销率②：2025年营业收入 ÷ 发行后总股本（摊薄后静态） | B41: 35.89 | C41: A | D41: S2
A42: 发行市净率（发行价 ÷ 发行后每股净资产） | B42: 7.16 | C42: A | D42: S2
A43: 发行后每股收益（元/股，按2025年扣非前后孰低归母净利） | B43: 0.69 | C43: A | D43: S2
A44: 发行后每股净资产（元/股） | B44: 21.07 | C44: A | D44: S2
A45: 按发行价计算的发行后市值（亿元） | B45: 609.93 | C45: A | D45: S2
A46: 【行业与可比公司估值参照】
A47: 所属行业最近一个月平均静态市盈率（倍，截至2026-08-05 T-3日，中证指数） | B47: 38.56 | C47: A | D47: S2
A48: 可比公司2025年静态市销率算术平均值（倍，Wind，截至2026-08-05） | B48: 19.74 | C48: A | D48: S2
A49: 可比公司选取说明 | B49: 优必选、越疆（港股，按2026-08-05中间价1港元=0.86562人民币折算）；云深处、乐聚智能尚未上市故未纳入 | C49: A | D49: S2
A50: 估值指标选择原因 | B50: 可比上市公司均未盈利，故选择市销率作为估值对比指标 | C50: A | D50: S2
A51: 【上市标准与历史估值】
A52: 适用上市标准 | B52: 《上海证券交易所科创板股票上市规则》第2.1.4条第（一）款：预计市值不低于人民币100亿元（因存在特别表决权安排） | C52: A | D52: S1
A53: 2025年6月最近一次市场化股权融资投前估值（亿元） | B53: 120 | C53: A | D53: S1
A54: 2025年6月最近一次市场化股权融资投后估值（亿元） | B54: 127 | C54: A | D54: S1
A55: 【中介机构】
A56: 保荐人（主承销商） | B56: 中信证券股份有限公司（法定代表人 张佑君） | C56: A | D56: S2
A57: 保荐代表人 | B57: 高若阳（S1010717030001）、陈熙颖（S1010716040002） | C57: A | D57: S2
A58: 审计机构 | B58: 容诚会计师事务所（特殊普通合伙） | C58: A | D58: S2
A59: 审计报告文号 | B59: 容诚审字[2026]230Z1692号（标准无保留意见） | C59: A | D59: S1/S2
A60: 审阅报告文号 | B60: 容诚阅字[2026]230Z0038号（2026年1-3月） | C60: A | D60: S1
A61: 发行人律师 | B61: 北京德恒律师事务所 | C61: A | D61: S1
A62: 战略配售专项核查律师 | B62: 北京市君泽君律师事务所 | C62: A | D62: S1
A64: 表2-2 上市后二级市场表现（2026-08-19 至 2026-08-28，资料截止日前全部交易日）
A65: 交易日 | B65: 开盘价(元) | C65: 收盘价(元) | D65: 最高价(元) | E65: 最低价(元) | F65: 成交量(手) | G65: 成交额(元) | H65: 振幅(%) | I65: 涨跌幅(%) | J65: 涨跌额(元) | K65: 换手率(%)
A66: 2026-08-19 | B66: 1100 | C66: 845 | D66: 1100 | E66: 800.08 | F66: 256579 | G66: 23159535334 | H66: 1.9889 | I66: 4.6034 | J66: 694.2 | K66: 0.8528
A67: 2026-08-20 | B67: 790 | C67: 687 | D67: 790 | E67: 685.01 | F67: 126295 | G67: 9071869080 | H67: 0.1242 | I67: -0.187 | J67: -158 | K67: 0.4198
A68: 2026-08-21 | B68: 659 | C68: 672.41 | D68: 706.98 | E68: 636 | F68: 76057 | G68: 5138831982 | H68: 0.1033 | I68: -0.0212 | J68: -14.59 | K68: 0.2528
A69: 2026-08-24 | B69: 640.26 | C69: 603.08 | D69: 642 | E69: 602.05 | F69: 81289 | G69: 5015549853 | H69: 0.0594 | I69: -0.1031 | J69: -69.33 | K69: 0.2702
A70: 2026-08-25 | B70: 588 | C70: 602.8 | D70: 625.89 | E70: 588 | F70: 53215 | G70: 3244776858 | H70: 0.0628 | I70: -0.0005 | J70: -0.28 | K70: 0.1769
A71: 2026-08-26 | B71: 598 | C71: 591.53 | D71: 614.44 | E71: 571 | F71: 55830 | G71: 3324850833 | H71: 0.0721 | I71: -0.0187 | J71: -11.27 | K71: 0.1856
A72: 2026-08-27 | B72: 588 | C72: 615.03 | D72: 615.05 | E72: 582 | F72: 63398 | G72: 3795447912 | H72: 0.0559 | I72: 0.0397 | J72: 23.5 | K72: 0.2107
A73: 2026-08-28 | B73: 605 | C73: 585 | D73: 605 | E73: 584.88 | F73: 56748 | G73: 3362608198 | H73: 0.0327 | I73: -0.0488 | J73: -30.03 | K73: 0.1886
A74: 口径说明：①上市首日（8月19日）振幅与涨跌幅以前收盘价=发行价150.80元为基准计算，故振幅达198.89%；②8月29日、30日为周末非交易日；③8月31日数据虽已产生，但超出本底稿资料截止日（2026-08-30），故不予纳入；④行情数据来自第三方接口（来源S9），非公司披露，引用时请注明。

Sheet 03_财务原始数据
A1: 表3-1 报告期年度主要财务数据（性质A：经容诚会计师事务所审计）
A2: 单位：人民币万元（每股指标为元/股，比率为小数存储）。列顺序为 2023 / 2024 / 2025 年度，与招股说明书披露顺序一致。
A3: 项目 | B3: 单位 | C3: 2023年度 | D3: 2024年度 | E3: 2025年度 | F3: 数据性质 | G3: 来源
A4: 【一、营业收入与成本】
A5: 营业收入 | B5: 万元 | C5: 15913.44 | D5: 78554.14 | E5: 169926.93 | F5: A | G5: S1
A6: 主营业务收入 | B6: 万元 | C6: 15753.65 | D6: 38767.28 | E6: 167611.09 | F6: A | G6: S1
A7: 其他业务收入 | B7: 万元 | C7: 159.79 | D7: 509.78 | E7: 2315.84 | F7: A | G7: S1
A8: 营业成本合计 | B8: 万元 | C8: 8791.85 | D8: 16804.41 | E8: 67226.1 | F8: A | G8: S1
A9: 主营业务成本 | B9: 万元 | C9: 8787.9 | D9: 16770.67 | E9: 66826.03 | F9: A | G9: S1
A10: 其他业务成本 | B10: 万元 | C10: 3.95 | D10: 33.74 | E10: 400.08 | F10: A | G10: S1
A11: 主营业务毛利 | B11: 万元 | C11: 6965.75 | D11: 21996.62 | E11: 100785.07 | F11: A | G11: S1
A12: 【二、期间费用】
A13: 销售费用 | B13: 万元 | C13: 3771.83 | D13: 5915.85 | E13: 14120.32 | F13: A | G13: S1
A14: 管理费用 | B14: 万元 | C14: 1332.8 | D14: 2500.52 | E14: 39959.61 | F14: A | G14: S1
A15: 研发费用 | B15: 万元 | C15: 4995.18 | D15: 7001.7 | E15: 14496.56 | F15: A | G15: S1
A16: 财务费用 | B16: 万元 | C16: -732.47 | D16: -1718.64 | E16: 98.61 | F16: A | G16: S1
A17: 期间费用合计 | B17: 万元 | C17: 9367.33 | D17: 13699.43 | E17: 68675.11 | F17: A | G17: S1
A18: 【三、其他损益项目】
A19: 投资收益 | B19: 万元 | C19: 154.4 | D19: 927.46 | E19: 2301.09 | F19: A | G19: S1
A20: 其中：理财产品投资收益 | B20: 万元 | C20: 34.92 | D20: 457.3 | E20: 948.57 | F20: A | G20: S1
A21: 其中：债权投资持有期间利息收入 | B21: 万元 | C21: 119.48 | D21: 470.16 | E21: 1368.93 | F21: A | G21: S1
A22: 公允价值变动收益 | B22: 万元 | C22: -5.66 | D22: 95.42 | E22: 91.29 | F22: A | G22: S1
A23: 信用减值损失 | B23: 万元 | C23: -61.82 | D23: -115.59 | E23: -256.52 | F23: A | G23: S1
A24: 资产减值损失 | B24: 万元 | C24: -840.56 | D24: -1037.85 | E24: -1598.06 | F24: A | G24: S1
A25: 营业外收入 | B25: 万元 | C25: 6.08 | D25: 7.02 | E25: 130.92 | F25: A | G25: S1
A26: 营业外支出 | B26: 万元 | C26: 10.26 | D26: 15.49 | E26: 56.36 | F26: A | G26: S1
A27: 【四、利润】
A28: 营业利润 | B28: 万元 | C28: -2136.69 | D28: 10070.25 | E28: 36771.35 | F28: A | G28: S1
A29: 利润总额 | B29: 万元 | C29: -2140.87 | D29: 10061.78 | E29: 36845.9 | F29: A | G29: S1
A30: 净利润 | B30: 万元 | C30: -1114.51 | D30: 9547.47 | E30: 27821.05 | F30: A | G30: S1
A31: 归属于母公司所有者的净利润 | B31: 万元 | C31: -1114.51 | D31: 9547.47 | E31: 27821.05 | F31: A | G31: S1
A32: 扣除非经常性损益后归属于母公司所有者的净利润 | B32: 万元 | C32: -1801.91 | D32: 7847.65 | E32: 59075.28 | F32: A | G32: S1
A33: 【五、非经常性损益关键项】
A34: 股份支付费用（上海宇翼增资，计入管理费用，属非经常性损益） | B34: 万元 | E34: 34906.55 | F34: A | G34: S1
A35: （参考）2022年上海宇翼增资确认股份支付费用 | B35: 万元 | E35: 1872.26 | F35: A | G35: S1
A36: 【六、现金流】
A37: 经营活动产生的现金流量净额 | B37: 万元 | C37: 494.25 | D37: 19239.13 | E37: 66998.18 | F37: A | G37: S1
A38: 【七、资产与权益（期末数）】
A39: 资产总额 | B39: 万元 | C39: 39127.15 | D39: 152786.94 | E39: 320853.83 | F39: A | G39: S1
A40: 流动资产 | B40: 万元 | C40: 32630.22 | D40: 127089.87 | E40: 221966.64 | F40: A | G40: S1
A41: 非流动资产 | B41: 万元 | C41: 6496.93 | D41: 25697.07 | E41: 98887.2 | F41: A | G41: S1
A42: 归属于母公司所有者权益 | B42: 万元 | C42: 29904.49 | D42: 128054.9 | E42: 260465.85 | F42: A | G42: S1
A43: 预付款项 | B43: 万元 | C43: 358.35 | D43: 830.78 | E43: 3015.5 | F43: A | G43: S1
A44: 存货（账面价值） | B44: 万元 | E44: 36775.34 | F44: A | G44: S1
A45: 存货跌价准备 | B45: 万元 | E45: 2457.37 | F45: A | G45: S1
A46: 现金分红 | B46: 万元 | F46: A | G46: S1
A47: 【八、比率指标（招股说明书直接披露）】
A48: 资产负债率（合并） | B48: % | C48: 0.2357 | D48: 0.1619 | E48: 0.1882 | F48: A | G48: S1
A49: 资产负债率（母公司） | B49: % | C49: 0.2357 | D49: 0.1619 | E49: 0.1856 | F49: A | G49: S1
A50: 主营业务毛利率 | B50: % | C50: 0.4422 | D50: 0.5674 | E50: 0.6013 | F50: A | G50: S1
A51: 综合毛利率 | B51: % | C51: 0.4475 | D51: 0.5722 | E51: 0.6044 | F51: A | G51: S1
A52: 加权平均净资产收益率 | B52: % | C52: -0.0366 | D52: 0.1046 | E52: 0.1352 | F52: A | G52: S1
A53: 扣非后加权平均净资产收益率 | B53: % | C53: -0.0592 | D53: 0.086 | E53: 0.287 | F53: A | G53: S1
A54: 研发投入占营业收入比例 | B54: % | C54: 0.3139 | D54: 0.1783 | E54: 0.0853 | F54: A | G54: S1
A55: 基本每股收益 | B55: 元/股 | E55: 0.76 | F55: A | G55: S1
A56: 稀释每股收益 | B56: 元/股 | E56: 0.76 | F56: A | G56: S1
A57: 应收账款坏账计提比例（公司） | B57: % | C57: 0.0613 | D57: 0.0655 | E57: 0.0513 | F57: A | G57: S1
A58: 应收账款坏账计提比例（同行业平均） | B58: % | C58: 0.1219 | D58: 0.1381 | E58: 0.1407 | F58: A | G58: S1
A59: 【九、人员与知识产权（期末数）】
A60: 研发人员（人） | B60: 人 | E60: 184 | F60: A | G60: S1
A61: 员工总数（人） | B61: 人 | E61: 516 | F61: A | G61: S1
A62: 研发人员占员工总数比例 | B62: % | E62: 0.3566 | F62: A | G62: S1
A63: 境内外注册专利（项，截至2026-01-31） | B63: 项 | E63: 262 | F63: A | G63: S1
A64: 其中：境内发明专利（项） | B64: 项 | E64: 20 | F64: A | G64: S1
A66: 表3-2 财务报告审计截止日后主要财务信息：2026年1-3月（性质B：经容诚会计师审阅，未经审计）
A67: 项目 | B67: 单位 | C67: 2026年1-3月 | D67: 2025年1-3月 | E67: 同比变动 | F67: 数据性质 | G67: 来源
A68: 营业收入 | B68: 万元 | C68: 42284.05 | D68: 25095.87 | E68: 0.6849 | F68: B | G68: S1
A69: 营业利润 | B69: 万元 | C69: 4913.6 | D69: 10820.57 | E69: -0.5459 | F69: B | G69: S1
A70: 利润总额 | B70: 万元 | C70: 4897.44 | D70: 10826.23 | E70: -0.5476 | F70: B | G70: S1
A71: 净利润 | B71: 万元 | C71: 5001.38 | D71: 9560.25 | E71: -0.4769 | F71: B | G71: S1
A72: 归属于母公司所有者的净利润 | B72: 万元 | C72: 5001.38 | D72: 9560.25 | E72: -0.4769 | F72: B | G72: S1
A73: 扣非后归属于母公司所有者的净利润 | B73: 万元 | C73: 4025.36 | D73: 8483.65 | E73: -0.5255 | F73: B | G73: S1
A74: 经营活动产生的现金流量净额 | B74: 万元 | C74: 3439.96 | D74: 23972.68 | E74: -0.8565 | F74: B | G74: S1
A75: 投资活动产生的现金流量净额 | B75: 万元 | C75: -4062.77 | D75: 10058.92 | E75: -1.4039 | F75: B | G75: S1
A76: 筹资活动产生的现金流量净额 | B76: 万元 | C76: -1511.59 | D76: 9545.51 | E76: -1.1584 | F76: B | G76: S1
A77: 资产总额（期末） | B77: 万元 | C77: 345907.18 | D77: 320853.83 | E77: 0.0781 | F77: B | G77: S1
A78: 负债总额（期末） | B78: 万元 | C78: 80373.63 | D78: 60387.99 | E78: 0.331 | F78: B | G78: S1
A79: 归属于母公司所有者权益（期末） | B79: 万元 | C79: 265533.55 | D79: 260465.85 | E79: 0.0195 | F79: B | G79: S1
A80: 归属于母公司股东的非经常性损益净额 | B80: 万元 | C80: 976.02 | D80: 1076.6 | F80: B | G80: S1
A81: 其中：计入当期损益的政府补助 | B81: 万元 | C81: 560.2 | D81: 861.93 | F81: B | G81: S1
A82: 其中：金融资产公允价值变动及处置损益 | B82: 万元 | C82: 573.17 | D82: 375.92 | F82: B | G82: S1
A83: 研发费用同比增加额（招股说明书文字披露） | B83: 万元 | C83: 3832.8 | F83: B | G83: S1
A84: 注：资产总额、负债总额、归母权益三行的“2025年1-3月”列实为2025年12月31日期末数，变动比例为较上年末的增减幅（招股说明书原口径）。
A86: 表3-3 2026年1-6月主要财务数据（性质C：载于上市公告书，未经审计；公司明示上市后不再单独披露2026年半年报）
A87: 项目 | B87: 单位 | C87: 2026年1-6月 | D87: 2025年1-6月 | E87: 变动 | F87: 数据性质 | G87: 来源
A88: 营业总收入 | B88: 万元 | C88: 115224.56 | D88: 77571.92 | E88: 0.4854 | F88: C | G88: S2
A89: 营业利润 | B89: 万元 | C89: 30223.84 | D89: 1500.1 | E89: 19.1479 | F89: C | G89: S2
A90: 利润总额 | B90: 万元 | C90: 30111.34 | D90: 1507.59 | E90: 18.9731 | F90: C | G90: S2
A91: 归属于母公司股东的净利润 | B91: 万元 | C91: 27399.99 | D91: -3202.45 | F91: C | G91: S2
A92: 归属于母公司股东的扣除非经常性损益后的净利润 | B92: 万元 | C92: 24393.03 | D92: 30243.35 | E92: -0.1934 | F92: C | G92: S2
A93: 基本每股收益 | B93: 元/股 | C93: 0.75 | D93: -0.09 | F93: C | G93: S2
A94: 扣除非经常性损益后的基本每股收益 | B94: 元/股 | C94: 0.67 | D94: 0.83 | E94: -0.1928 | F94: C | G94: S2
A95: 加权平均净资产收益率 | B95: % | C95: 0.0999 | D95: -0.0223 | E95: 0.1222 | F95: C | G95: S2
A96: 扣除非经常性损益后的加权净资产收益率 | B96: % | C96: 0.089 | D96: 0.2102 | E96: -0.1212 | F96: C | G96: S2
A97: 经营活动产生的现金流量净额 | B97: 万元 | C97: 23154.53 | D97: 34319.36 | E97: -0.3253 | F97: C | G97: S2
A98: 每股经营活动产生的现金流量净额 | B98: 元/股 | C98: 0.64 | D98: 0.94 | E98: -0.3253 | F98: C | G98: S2
A99: 流动资产（期末） | B99: 万元 | C99: 288848.41 | D99: 221966.64 | E99: 0.3013 | F99: C | G99: S2
A100: 流动负债（期末） | B100: 万元 | C100: 86454.44 | D100: 55573.4 | E100: 0.5557 | F100: C | G100: S2
A101: 总资产（期末） | B101: 万元 | C101: 384546.94 | D101: 320853.83 | E101: 0.1985 | F101: C | G101: S2
A102: 负债总额（期末）增速 | B102: % | E102: 0.5988 | F102: C | G102: S2
...

Sheet 04_业务结构原始数据
A1: 表4-1 主营业务收入按产品类别构成（性质A：经审计；单位：万元）
A2: 产品分类 | B2: 2023收入 | C2: 2023占比 | D2: 2024收入 | E2: 2024占比 | F2: 2025收入 | G2: 2025占比 | H2: 来源
A3: 四足机器人 | B3: 11938.09 | C3: 0.7578 | D3: 23054.37 | E3: 0.5947 | F3: 69762.56 | G3: 0.4162 | H3: S1
A4: 人形机器人 | B4: 296.71 | C4: 0.0188 | D4: 10729.76 | E4: 0.2768 | F4: 86783.19 | G4: 0.5178 | H4: S1
A5: 机器人组件 | B5: 2692.34 | C5: 0.1709 | D5: 4453.82 | E5: 0.1149 | F5: 10373.67 | G5: 0.0619 | H5: S1
A6: 其他 | B6: 826.51 | C6: 0.0525 | D6: 529.33 | E6: 0.0137 | F6: 691.67 | G6: 0.0041 | H6: S1
A7: 主营业务收入合计 | B7: 15753.65 | C7: 1 | D7: 38767.28 | E7: 1 | F7: 167611.09 | G7: 1 | H7: S1
A9: 表4-2 主营业务成本按产品类别构成（性质A；单位：万元）
A10: 产品分类 | B10: 2023成本 | C10: 2023占比 | D10: 2024成本 | E10: 2024占比 | F10: 2025成本 | G10: 2025占比 | H10: 来源
A11: 四足机器人 | B11: 6719.87 | C11: 0.7647 | D11: 11147.49 | E11: 0.6647 | F11: 30193.4 | G11: 0.4518 | H11: S1
A12: 人形机器人 | B12: 36.59 | C12: 0.0042 | D12: 3298.78 | E12: 0.1967 | F12: 31956.59 | G12: 0.4782 | H12: S1
A13: 机器人组件 | B13: 1379.44 | C13: 0.157 | D13: 1918.03 | E13: 0.1144 | F13: 4216.26 | G13: 0.0631 | H13: S1
A14: 其他 | B14: 652 | C14: 0.0742 | D14: 406.37 | E14: 0.0242 | F14: 459.78 | G14: 0.0069 | H14: S1
A15: 主营业务成本合计 | B15: 8787.9 | C15: 1 | D15: 16770.67 | E15: 1 | F15: 66826.03 | G15: 1 | H15: S1
A17: 表4-3 主要产品销售量与平均单价（性质A）
A18: 产品 / 指标 | B18: 单位 | C18: 2023 | D18: 2024 | E18: 2024变动 | F18: 2025 | G18: 2025变动 | H18: 来源
A19: 四足机器人 销量 | B19: 台 | C19: 3121 | D19: 7136 | E19: 1.2864 | F19: 23037 | G19: 2.2283 | H19: S1
A20: 四足机器人 平均单价 | B20: 万元/台 | C20: 3.83 | D20: 3.23 | E20: -0.1554 | F20: 3.03 | G20: -0.0627 | H20: S1
A21: 四足机器人 销售收入 | B21: 万元 | C21: 11938.09 | D21: 23054.37 | E21: 0.9312 | F21: 69762.56 | G21: 2.026 | H21: S1
A22: 人形机器人 销量 | B22: 台 | C22: 5 | D22: 412 | E22: 81.4 | F22: 5215 | G22: 11.6578 | H22: S1
A23: 人形机器人 平均单价 | B23: 万元/台 | C23: 59.34 | D23: 26.04 | E23: -0.5611 | F23: 16.64 | G23: -0.361 | H23: S1
A24: 人形机器人 销售收入 | B24: 万元 | C24: 296.71 | D24: 10729.76 | E24: 35.1624 | F24: 86783.19 | G24: 7.0881 | H24: S1
A25: 口径差异提示（重要）：招股说明书“第二节 概览”称2025年度公司人形机器人“出货量已超5,500台（纯人形，不含轮式双臂机器人），出货量全球第一”；而“第六节 财务会计信息”主营业务收入口径下2025年人形机器人“销量”为5,215台。两者相差约300台，系“出货量”与“确认收入销量”的口径差异（可能含发出商品、样机、期后确认等）。引用“全球第一”表述时必须使用出货量口径并注明，进行收入测算时必须使用5,215台销量口径。详见表10待核验事项。
A27: 表4-4 主营业务收入按市场区域构成（性质A；单位：万元）
A28: 区域 | B28: 2023收入 | C28: 2023占比 | D28: 2024收入 | E28: 2024占比 | F28: 2025收入 | G28: 2025占比 | H28: 来源
A29: 境内销售 | B29: 6989.41 | C29: 0.4437 | D29: 17156.55 | E29: 0.4426 | F29: 94445.56 | G29: 0.5635 | H29: S1
A30: 境外销售 | B30: 8764.24 | C30: 0.5563 | D30: 21610.74 | E30: 0.5574 | F30: 73165.53 | G30: 0.4365 | H30: S1
A31: 合计 | B31: 15753.65 | C31: 1 | D31: 38767.28 | E31: 1 | F31: 167611.09 | G31: 1 | H31: S1
A32: 招股说明书解释：2023—2024年境外收入占比略高于境内，显示产品在海外市场认可度较高；2025年境内占比大幅提升至56.35%，主要系2025年年初春晚演出提升全国品牌知名度，以及国内人工智能与机器人产业快速发展与政策支持带动科研教育、商业消费、行业应用客户采购需求。
A34: 表4-5 主营业务收入按季度构成（性质A；单位：万元）
A35: 季度 | B35: 2023收入 | C35: 2023占比 | D35: 2024收入 | E35: 2024占比 | F35: 2025收入 | G35: 2025占比 | H35: 来源
A36: 第一季度 | B36: 3093.17 | C36: 0.1963 | D36: 6510.98 | E36: 0.168 | F36: 24815.92 | G36: 0.1481 | H36: S1
A37: 第二季度 | B37: 4143.92 | C37: 0.263 | D37: 6707.3 | E37: 0.173 | F37: 52095.34 | G37: 0.3108 | H37: S1
A38: 第三季度 | B38: 3222.43 | C38: 0.2046 | D38: 9765.44 | E38: 0.2519 | F38: 38543.68 | G38: 0.23 | H38: S1
A39: 第四季度 | B39: 5294.13 | C39: 0.3361 | D39: 15783.55 | E39: 0.4071 | F39: 52156.15 | G39: 0.3112 | H39: S1
A40: 季节性：新产品多在下半年陆续形成收入并于第四季度形成规模收入；部分客户实行集中采购、预算管理，采购或验收多发生在第四季度，故各年四季度收入占比相对较高。
A42: 表4-6 主营业务收入按销售模式构成（性质A；单位：万元）
A43: 销售模式 | B43: 2023收入 | C43: 2023占比 | D43: 2024收入 | E43: 2024占比 | F43: 2025收入 | G43: 2025占比 | H43: 来源
A44: 线上销售 | B44: 2069.52 | C44: 0.1314 | D44: 4026.34 | E44: 0.1039 | F44: 17970.42 | G44: 0.1072 | H44: S1
A45: 其中：直接销售 | B45: 2069.52 | C45: 0.1314 | D45: 4026.34 | E45: 0.1039 | F45: 13085.26 | G45: 0.0781 | H45: S1
A46: 其中：电商入仓 | F46: 4885.16 | G46: 0.0291 | H46: S1
A47: 线下销售 | B47: 13684.13 | C47: 0.8686 | D47: 34740.94 | E47: 0.8961 | F47: 149640.68 | G47: 0.8928 | H47: S1
A48: 其中：直销 | B48: 8077.3 | C48: 0.5127 | D48: 20873.1 | E48: 0.5384 | F48: 85644.21 | G48: 0.511 | H48: S1
A49: 其中：经销 | B49: 5606.83 | C49: 0.3559 | D49: 13867.84 | E49: 0.3577 | F49: 63996.47 | G49: 0.3818 | H49: S1
A51: 表4-7 主营业务成本按生产要素构成（性质A；单位：万元）
A52: 生产要素 | B52: 2023成本 | C52: 2023占比 | D52: 2024成本 | E52: 2024占比 | F52: 2025成本 | G52: 2025占比 | H52: 来源
A53: 直接材料 | B53: 6403.99 | C53: 0.7287 | D53: 12230.44 | E53: 0.7293 | F53: 54615.94 | G53: 0.8173 | H53: S1
A54: 直接人工 | B54: 1227.74 | C54: 0.1397 | D54: 2084.91 | E54: 0.1243 | F54: 5396.4 | G54: 0.0808 | H54: S1
A55: 制造费用 | B55: 1156.18 | C55: 0.1316 | D55: 2455.31 | E55: 0.1464 | F55: 6813.69 | G55: 0.102 | H55: S1
A56: 招股说明书解释：2025年直接材料占比大幅上升、直接人工及制造费用占比下降，原因包括（1）规模优势凸显、生产工序标准化与人员熟练度提升带来生产效率提高；（2）材料成本占比较高的人形机器人收入占比由27.68%升至51.78%，拉高了直接材料整体占比。
A58: 表4-8 分产品毛利率（招股说明书披露口径）
A59: 产品分类 | B59: 2023毛利率 | C59: 2024毛利率 | D59: 2025毛利率 | E59: 披露方式 | F59: 来源
A60: 机器人组件 | B60: 0.4876 | C60: 0.5694 | D60: 0.5936 | E60: 招股说明书直接披露 | F60: S1
A61: 四足机器人、人形机器人的分产品毛利率招股说明书未以百分比直接列示，本底稿在表7-3中依据表4-1收入与表4-2成本用公式计算得出（计算结果标记为性质E·测算）。

Sheet 05_客户与同业原始数据
A1: 表5-1 报告期前五大客户（性质A；单位：万元）
A2: 年度 | B2: 序号 | C2: 客户名称 | D2: 销售金额 | E2: 占营业收入比例 | F2: 来源
A3: 2025 | B3: 1 | C3: 境外客户N（欧洲） | D3: 5288.74 | E3: 0.0311 | F3: S1
A4: 2025 | B4: 2 | C4: 京东集团股份有限公司 | D4: 4887.32 | E4: 0.0288 | F4: S1
A5: 2025 | B5: 3 | C5: 境外客户A（亚洲） | D5: 4282.66 | E5: 0.0252 | F5: S1
A6: 2025 | B6: 4 | C6: 北京朝元时代科技有限公司 | D6: 3070.69 | E6: 0.0181 | F6: S1
A7: 2025 | B7: 5 | C7: 境外客户B（亚洲） | D7: 3002.16 | E7: 0.0177 | F7: S1
A8: 2025 | B8: 合计 | C8: 前五大客户合计 | D8: 20531.58 | E8: 0.1208 | F8: S1
A9: 2024 | B9: 1 | C9: 境外客户A（亚洲） | D9: 1443.27 | E9: 0.0367 | F9: S1
A10: 2024 | B10: 2 | C10: 境外客户B（亚洲） | D10: 1066.81 | E10: 0.0272 | F10: S1
A11: 2024 | B11: 3 | C11: 境外客户Q（北美洲） | D11: 884.94 | E11: 0.0225 | F11: S1
A12: 2024 | B12: 4 | C12: 境外客户C（欧洲） | D12: 780.02 | E12: 0.0199 | F12: S1
A13: 2024 | B13: 5 | C13: 境内客户A1 | D13: 715.27 | E13: 0.0182 | F13: S1
A14: 2024 | B14: 合计 | C14: 前五大客户合计 | D14: 4890.31 | E14: 0.1245 | F14: S1
A15: 2023 | B15: 1 | C15: 境外客户D（北美洲） | D15: 509.5 | E15: 0.032 | F15: S1
A16: 2023 | B16: 2 | C16: 境外客户A（亚洲） | D16: 410 | E16: 0.0258 | F16: S1
A17: 2023 | B17: 3 | C17: 境外客户C（欧洲） | D17: 408.16 | E17: 0.0256 | F17: S1
A18: 2023 | B18: 4 | C18: 境外客户B（亚洲） | D18: 360.69 | E18: 0.0227 | F18: S1
A19: 2023 | B19: 5 | C19: 境内客户A1 | D19: 331.18 | E19: 0.0208 | F19: S1
A20: 2023 | B20: 合计 | C20: 前五大客户合计 | D20: 2019.53 | E20: 0.1269 | F20: S1
A21: 招股说明书结论：①销售金额对受同一实际控制人控制的客户合并计算；②不存在向单个客户销售比例超过营业收入50%的情形；③公司与报告期内前五大客户均不存在关联关系。客户集中度三年稳定在12%—13%区间，无单一大客户依赖。
A23: 表5-2 同行业可比公司营业收入与综合毛利率对比（性质A；单位：万元）
A24: 公司名称 | B24: 2023营业收入 | C24: 2023毛利率 | D24: 2024营业收入 | E24: 2024毛利率 | F24: 2025营业收入 | G24: 2025毛利率 | H24: 来源
A25: 优必选 | B25: 105569.8 | C25: 0.3153 | D25: 130536.1 | E25: 0.2865 | F25: 200099.9 | G25: 0.3767 | H25: S1
A26: 越疆 | B26: 28699.17 | C26: 0.4847 | D26: 37483.06 | E26: 0.4795 | F26: 49348.3 | G26: 0.4649 | H26: S1
A27: 云深处 | B27: 5011.26 | C27: 0.3348 | D27: 10320.1 | E27: 0.3876 | F27: 33749.06 | G27: 0.5283 | H27: S1
A28: 乐聚智能 | B28: 5398.83 | C28: 0.5045 | D28: 5550.03 | E28: 0.443 | F28: 25818.79 | G28: 0.4078 | H28: S1
A29: 可比公司平均值 | B29: 36169.77 | C29: 0.4098 | D29: 45972.32 | E29: 0.3992 | F29: 77254.01 | G29: 0.4444 | H29: S1
A30: 宇树科技（公司） | B30: 15913.44 | C30: 0.4475 | D30: 39277.07 | E30: 0.5722 | F30: 169926.93 | G30: 0.6044 | H30: S1
A31: 可比公司主要产品：优必选—人形机器人/教育/物流/消费类（2025年人形机器人收入占比由上年2.7%升至41.1%）；越疆—协作机器人（人形机器人收入占比未超5%）；云深处—四足及轮足机器人（人形占比未超5%）；乐聚智能—2023/2024年以教育市场中小型人形机器人为主，2025年全尺寸人形机器人成为主要收入来源。招股说明书认为公司综合毛利率高于同行业公司具合理性，主因全栈自研自产降低硬件成本、规模效应，以及产品构成差异。
A33: 表5-3 应收账款预期信用损失计提比例对比（性质A）
A34: 证券简称 | B34: 2023-12-31 | C34: 2024-12-31 | D34: 2025-12-31 | H34: 来源
A35: 越疆 | B35: 0.1449 | C35: 0.1133 | D35: 0.1109 | H35: S1
A36: 优必选 | B36: 0.2199 | C36: 0.3035 | D36: 0.2929 | H36: S1
A37: 云深处 | B37: 0.0725 | C37: 0.0818 | D37: 0.097 | H37: S1
A38: 乐聚智能 | B38: 0.0504 | C38: 0.0536 | D38: 0.062 | H38: S1
A39: 平均值 | B39: 0.1219 | C39: 0.1381 | D39: 0.1407 | H39: S1
A40: 宇树科技（公司） | B40: 0.0613 | C40: 0.0655 | D40: 0.0513 | H40: S1
A41: 公司计提比例低于同行业平均水平，招股说明书解释为应收账款账龄相对较短、周转率相对较快、回款情况良好。此为分析中需保持关注的会计估计差异点（详见表9结论与表10待核验）。
A43: 表5-4 2025年末应收账款账面余额前五名（性质A；单位：万元）
A44: 单位名称 | B44: 期末余额 | C44: 占应收账款余额比例 | D44: 坏账准备 | E44: 账龄 | H44: 来源
A45: 北京京东世纪贸易有限公司 | B45: 792.03 | C45: 0.1279 | D45: 39.6 | E45: 1年以内 | H45: S1
A46: 境外客户Y（北美洲） | B46: 287.3 | C46: 0.0464 | D46: 14.37 | E46: 1年以内 | H46: S1
A47: 杭州市消防救援支队 | B47: 250 | C47: 0.0404 | D47: 12.5 | E47: 1年以内 | H47: S1
A48: 上海柔克智能科技有限公司 | B48: 244.04 | C48: 0.0394 | D48: 12.2 | E48: 1年以内 | H48: S1
A49: 境外客户W（亚洲） | B49: 196.41 | C49: 0.0317 | D49: 9.82 | E49: 1年以内 | H49: S1
A50: 合计 | B50: 1769.78 | C50: 0.2859 | D50: 88.49 | E50: — | H50: S1
A51: 由前五大应收账款余额占比28.59%可反推2025年末应收账款账面余额约6,196万元（测算，性质E）；该反推值未经招股说明书直接披露，正式引用前需核对招股说明书“应收账款”小节原文（见表10）。

Sheet 06_股权与募投原始数据
A1: 表6-1 本次发行前后股本结构（性质A；单位：万股）
A2: 序号 | B2: 股东名称 | C2: 发行前股份数(万股) | D2: 发行前持股比例 | E2: 发行后股份数(万股) | F2: 发行后持股比例
A3: 1 | B3: 王兴兴 | C3: 8671.4964 | D3: 0.238216 | E3: 8671.4964 | F3: 0.214395
A4: 2 | B4: 上海宇翼（员工持股平台） | C4: 3982.86 | D4: 0.109414 | E4: 3982.86 | F4: 0.098472
A5: 3 | B5: 汉海信息 | C5: 2770.677 | D5: 0.076114 | E5: 2770.677 | F5: 0.068502
A6: 4 | B6: 宁波红杉 | C6: 2260.5408 | D6: 0.0621 | E6: 2260.5408 | F6: 0.05589
A7: 5 | B7: Astrend IV | C7: 1610.595 | D7: 0.044245 | E7: 1610.595 | F7: 0.03982
A8: 6 | B8: 经纬壹号 | C8: 1550.6316 | D8: 0.042598 | E8: 1550.6316 | F8: 0.038338
A9: 7 | B9: 金石成长 | C9: 1511.4204 | D9: 0.04152 | E9: 1511.4204 | F9: 0.037368
A10: 8 | B10: 机器人基金 | C10: 1392.804 | D10: 0.038262 | E10: 1392.804 | F10: 0.034436
A11: 9 | B11: 嘉兴骅茂 | C11: 1160.2332 | D11: 0.031873 | E11: 1160.2332 | F11: 0.028686
A12: 10 | B12: 君万弘毅 | C12: 1117.494 | D12: 0.030699 | E12: 1117.494 | F12: 0.027629
A13: 11 | B13: 源码资本 | C13: 947.709 | D13: 0.026035 | E13: 947.709 | F13: 0.023431
A14: 12 | B14: 中网投 | C14: 767.6676 | D14: 0.021089 | E14: 767.6676 | F14: 0.01898
... A48: 46 | B48: 上海米达 | C48: 44.6796 | D48: 0.001227 | E48: 44.6796 | F48: 0.001105
A49: 47 | B49: 本次公开发行股份 | E49: 4044.6434 | F49: 0.1
B50: 合计 | C50: 36401.791 | D50: 1 | E50: 40446.434 | F50: 1
A52: 特别表决权安排（性质A，来源S1） | B52: 数值 | C52: 说明
A53: 特别表决权设置时点 | B53: 2025年5月16日 | C53: 公司召开杭州宇树科技股份有限公司成立大会暨第一次临时股东会，表决通过《关于<股份公司关于设置特别表决权股份的方案>的议案》
A54: 王兴兴发行前直接持股比例 | B54: 0.238216 | C54: 直接持有8,671.4964万股，为公司控股股东
A55: 王兴兴发行前直接持股部分表决权比例 | B55: 0.635457 | C55: 特别表决权安排下
A56: 王兴兴发行前合计控制表决权比例 | B56: 0.687816 | C56: 直接持股表决权 + 通过杭州天则控制的上海宇翼员工股权激励持股平台
A57: 王兴兴发行后直接持股比例 | B57: 0.214395 | C57: 股份数不变，因新股发行摊薄
A58: 王兴兴发行后合计控制表决权比例 | B58: 0.65309 | C58: 本次发行不会造成公司实际控制人变更
A59: 上海宇翼发行前持股比例 | B59: 0.109414 | C59: 员工股权激励持股平台，2022年1月与2025年6月先后两次对公司增资
A60: 发行前前十名股东合计持股(万股) | B60: 26028.752 | C60: 占发行前总股本71.5041%
A62: 表6-2 最终战略配售结果（性质A，来源S2；获配金额单位：元）
A63: 序号 | B63: 参与战略配售的投资者名称 | C63: 投资者类型 | D63: 获配股数(股) | E63: 占本次发行数量比例 | F63: 获配金额(元) | G63: 限售期
A64: 1 | B64: 全国社会保障基金理事会 | C64: 具有长期投资意愿的大型保险公司或其下属企业、国家级大型投资基金或其下属企业 | D64: 933402 | E64: 0.0231 | F64: 1.4075702e+08 | G64: 12个月
A65: 1-1 | B65: 全国社保基金六零一组合 | C65: 同上（明细） | D65: 340723 | E65: 0.0084 | F65: 51381028 | G65: 12个月
A66: 1-2 | B66: 全国社保基金五零二组合 | C66: 同上（明细） | D66: 326690 | E66: 0.0081 | F66: 49264852 | G66: 12个月
A67: 1-3 | B67: 全国社保基金一零九组合 | C67: 同上（明细） | D67: 265989 | E67: 0.0066 | F67: 40111141 | G67: 12个月
A68: 2 | B68: 杭州深度求索人工智能基础技术研究有限公司 | C68: 与发行人经营业务具有战略合作关系或长期合作愿景的大型企业或其下属企业 | D68: 933399 | E68: 0.0231 | F68: 1.4075657e+08 | G68: 36个月
A69: 3 | B69: 中国石油集团昆仑资本有限公司 | C69: 同上 | D69: 903290 | E69: 0.0223 | F69: 136216132 | G69: 12个月
A70: 4 | B70: 南方电网产融控股集团有限公司 | C70: 同上 | D70: 903290 | E70: 0.0223 | F70: 136216132 | G70: 12个月
A71: 5 | B71: 天翼资本控股有限公司 | C71: 同上 | D71: 903290 | E71: 0.0223 | F71: 136216132 | G71: 12个月
A72: 6 | B72: 上海启善投资有限公司（腾讯科技（上海）有限公司） | C72: 同上 | D72: 903290 | E72: 0.0223 | F72: 136216132 | G72: 自腾讯科技（上海）首次取得发行人股份之日起36个月及自上市之日起12个月，以孰晚为准
A73: 7 | B73: 中信证券投资有限公司 | C73: 参与科创板跟投的保荐人相关子公司 | D73: 808928 | E73: 0.02 | F73: 1.2198634e+08 | G73: 24个月
A74: 8 | B74: 宇树科技员工1号资管计划 | C74: 发行人高级管理人员与核心员工参与战略配售设立的专项资产管理计划 | D74: 1356100 | E74: 0.0335 | F74: 204499880 | G74: 12个月
A75: 9 | B75: 宇树科技员工2号资管计划 | C75: 同上 | D75: 444297 | E75: 0.011 | F75: 66999988 | G75: 36个月
A76: 合计 | B76: 最终战略配售 | C76: 占本次发行数量20.00% | D76: 8089286 | E76: 0.2 | F76: 1.2198643e+09 | G76: —
A77: 员工资管计划补充信息（来源S2）：1号计划全称“中信证券资管宇树科技员工参与科创板战略配售1号集合资产管理计划”，设立于2026年6月29日，备案2026年7月10日，募集资金规模20,450万元，参与认购的发行人核心员工159名；2号计划设立于2026年7月2日，募集资金规模6,700万元，参与认购的高级管理人员和核心员工12名。两个计划的管理人及实际支配主体均为中信证券资产管理有限公司，非发行人高级管理人员及核心员工。保荐人跟投：发行规模50亿元以上，跟投比例2%，中证投资获配808,928股、金额121,986,342.40元。序号1-1至1-3为序号1的明细组合，不参与合计（合计口径已由公告给出）。
A79: 表6-3 募集资金投资项目（性质A，来源S1；单位：万元）
A80: 序号 | B80: 项目名称 | C80: 项目投资总额 | D80: 拟使用募集资金 | E80: 占拟募资比例 | F80: 来源
A81: 1 | B81: 智能机器人模型研发项目 | C81: 202245.93 | D81: 202245.93 | E81: 0.48134182 | F81: S1
A82: 2 | B82: 机器人本体研发项目 | C82: 110973.8 | D82: 110973.8 | E82: 0.26411573 | F82: S1
A83: 3 | B83: 新型智能机器人产品开发项目 | C83: 44540 | D83: 44540 | E83: 0.10600443 | F83: S1
A84: 4 | B84: 智能机器人制造基地建设项目 | C84: 62411.39 | D84: 62411.39 | E84: 0.14853803 | F84: S1
A85: — | B85: 合计 | C85: 420171.12 | D85: 420171.12 | E85: 1 | F85: S1
A86: 研发类项目（序号1+2+3）合计拟投入357,759.73万元，占拟募资总额85.15%；其中“智能机器人模型研发项目”单项占比48.13%，对应公司自研通用WMA模型与VLA模型等具身智能大模型方向。制造基地建设项目占比14.85%。募投项目已经公司第一届董事会第十四次会议、2026年第一次临时股东会审议通过。
A88: 表6-4 发行费用明细（性质A，来源S2；单位：万元，不含增值税）
A89: 内容 | B89: 发行费用金额(不含税) | C89: 占发行费用比例 | D89: 占募集资金总额比例 | F89: 来源
A90: 承销及保荐费 | B90: 14499.32 | C90: 0.79590895 | D90: 0.023772018 | F90: S2
A91: 审计及验资费 | B91: 1828.3 | C91: 0.10036059 | D91: 0.0029975462 | F91: S2
A92: 律师费 | B92: 1100 | C92: 0.060382131 | D92: 0.0018034791 | F92: S2
A93: 用于本次发行的信息披露费 | B93: 603.77 | C93: 0.033142654 | D93: 0.00098989688 | F93: S2
A94: 发行手续费及其他费用 | B94: 185.91 | C94: 0.010205129 | D94: 0.00030480436 | F94: S2
A95: 合计 | B95: 18217.31 | C95: 1 | D95: 0.029867761 | F95: S2
A96: 公告书注：以上发行费用口径均不含增值税金额，合计数与各分项数值之和尾数存在微小差异，为四舍五入造成。

Sheet 07_核心计算
A1: 核心计算表（全部由公式实时引用『02–06 原始数据』表，修改原始数据即自动重算）
A2: 本表所有数值单元格均为 Excel 公式而非硬编码（唯一例外为文字性说明）。计算结果的数据性质统一标记为“E·测算”，但公式所引用输入项的性质（A经审计 / B经审阅 / C未经审计 / D管理层预计）在“输入项性质”列中逐项保留，以免将预测数或未审计数误作已审计事实使用。单位统一为人民币万元（每股/单价指标为元，比率以小数存储、百分比格式显示）。
A3: 表7-1 成长性指标（营业收入与利润增速、复合增长率）
A4: 指标 | B4: 单位 | C4: 2024年度 | D4: 2025年度 | E4: 2026年1-3月 | F4: 2026年1-6月 | G4: 输入项性质 | H4: 计算口径与公式说明 | I4: 勾稽校验
A5: 营业收入同比增速 | B5: % | C5: ='03_财务原始数据'!D5/'03_财务原始数据'!C5-1 -> 3.9363393 | D5: ='03_财务原始数据'!E5/'03_财务原始数据'!D5-1 -> 1.1631824 | E5: ='03_财务原始数据'!C68/'03_财务原始数据'!D68-1 -> 0.68490074 | F5: ='03_财务原始数据'!C88/'03_财务原始数据'!D88-1 -> 0.48539007 | G5: A / B / C | H5: 本期营业收入 ÷ 上年同期营业收入 − 1；年度列为2024、2025年同比 | I5: Q1、H1列应与招股书/公告书披露的68.49%、48.54%一致
A6: 主营业务收入同比增速 | B6: % | C6: ='04_业务结构原始数据'!D7/'04_业务结构原始数据'!B7-1 -> 1.4608443 | D6: ='04_业务结构原始数据'!F7/'04_业务结构原始数据'!D7-1 -> 3.3235195 | E6: 未披露 | F6: 未披露 | G6: A | H6: 表4-1主营业务收入合计的同比增速 | I6: —
A7: 归母净利润同比增速 | B7: % | C7: ='03_财务原始数据'!D31/'03_财务原始数据'!C31-1 -> -9.566518 | D7: ='03_财务原始数据'!E31/'03_财务原始数据'!D31-1 -> 1.9139709 | E7: ='03_财务原始数据'!C72/'03_财务原始数据'!D72-1 -> -0.47685678 | F7: 不可比 | G7: A / B / C | H7: H1列标记“不可比”：2025年1-6月归母净利润为−3,202.45万元（受34,906.55万元股份支付费用影响），基数为负，同比增速无经济意义，上市公告书亦以“-”列示 | I7: —
A8: 扣非归母净利润同比增速 | B8: % | C8: ='03_财务原始数据'!D32/'03_财务原始数据'!C32-1 -> -5.3551842 | D8: ='03_财务原始数据'!E32/'03_财务原始数据'!D32-1 -> 6.5277669 | E8: ='03_财务原始数据'!C73/'03_财务原始数据'!D73-1 -> -0.52551555 | F8: ='03_财务原始数据'!C92/'03_财务原始数据'!D92-1 -> -0.19344153 | G8: A / B / C | H8: 扣非口径剔除了股份支付等非经常性项目，是本期最可比的盈利增速指标 | I8: H1列应与公告书披露的−19.34%一致
A9: 经营活动现金流净额同比增速 | B9: % | C9: ='03_财务原始数据'!D37/'03_财务原始数据'!C37-1 -> 37.925908 | D9: ='03_财务原始数据'!E37/'03_财务原始数据'!D37-1 -> 2.4823914 | E9: ='03_财务原始数据'!C74/'03_财务原始数据'!D74-1 -> -0.85650499 | F9: ='03_财务原始数据'!C97/'03_财务原始数据'!D97-1 -> -0.32532163 | G9: A / B / C | H9: 经营活动产生的现金流量净额同比 | I9: H1列应与公告书披露的−32.53%一致
A10: 人形机器人收入同比增速 | B10: % | C10: ='04_业务结构原始数据'!D4/'04_业务结构原始数据'!B4-1 -> 35.162448 | D10: ='04_业务结构原始数据'!F4/'04_业务结构原始数据'!D4-1 -> 7.0880831 | E10: 未披露 | F10: 未披露 | G10: A | H10: 表4-1人形机器人主营业务收入同比 | I10: —
A11: 四足机器人收入同比增速 | B11: % | C11: ='04_业务结构原始数据'!D3/'04_业务结构原始数据'!B3-1 -> 0.93116068 | D11: ='04_业务结构原始数据'!F3/'04_业务结构原始数据'!D3-1 -> 2.0260016 | E11: 未披露 | F11: 未披露 | G11: A | H11: 表4-1四足机器人主营业务收入同比 | I11: —
A12: 营业收入两年复合增长率（2023→2025，CAGR） | B12: % | C12: — | D12: =('03_财务原始数据'!E5/'03_财务原始数据'!C5)^(1/2)-1 -> 2.2677519 | E12: — | F12: — | G12: A | H12: (2025年营业收入 ÷ 2023年营业收入)^(1/2) − 1 | I12: 科创属性指标之一，应与招股书披露的226.78%一致
A13: 主营业务收入两年CAGR（2023→2025） | B13: % | C13: — | D13: =('04_业务结构原始数据'!F7/'04_业务结构原始数据'!B7)^(1/2)-1 -> 2.2618259 | E13: — | F13: — | G13: A | H13: (2025年主营收入 ÷ 2023年主营收入)^(1/2) − 1 | I13: —
A14: 扣非归母净利润增速（2023年基期为亏损，两年CAGR不适用） | B14: % | C14: =IF('03_财务原始数据'!C32>0,'03_财务原始数据'!D32/'03_财务原始数据'!C32-1,"N/M") -> N/M | D14: =IF('03_财务原始数据'!D32>0,'03_财务原始数据'!E32/'03_财务原始数据'!D32-1,"N/M") -> 6.5277669 | E14: — | F14: — | G14: A | H14: 2023年扣非归母净利润为−1,801.91万元（亏损），任何以2023年为基期的CAGR或增速均无增长解释力，且对负值比值开平方会返回 #VALUE!，故本行以 IF 守卫：基期>0 才计算，否则显示“N/M”。D列为2024→2025年增速（基期7,847.65万元为正，可计算，约+652.78%）；C列为2023→2024年增速（N/M）。 | I14: 口径受限：论证成长性应引用营业收入CAGR（226.78%），不得引用扣非净利CAGR
A15: 重要口径提示：2026年1-3月数据来源为招股说明书（性质B，经会计师审阅）；2026年1-6月数据来源为上市公告书（性质C，未经审计）。两者不属于同一保证等级，纵向拼接时必须标注。公司已在上市公告书中明示“本次发行上市后，公司将不再另行披露2026年半年度报告”，故2026年上半年数据在本底稿资料截止日（2026-08-30）之前不存在经审计版本。
A17: 表7-2 盈利能力与费用结构
A18: 指标 | B18: 单位 | C18: 2023年度 | D18: 2024年度 | E18: 2025年度 | F18: 2026年1-3月 | G18: 2026年1-6月 | H18: 计算口径与公式说明 | I18: 勾稽校验
A19: 综合毛利率（测算） | B19: % | C19: =('03_财务原始数据'!C5-'03_财务原始数据'!C8)/'03_财务原始数据'!C5 -> 0.44752046 | D19: =('03_财务原始数据'!D5-'03_财务原始数据'!D8)/'03_财务原始数据'!D5 -> 0.78607862 | E19: =('03_财务原始数据'!E5-'03_财务原始数据'!E8)/'03_财务原始数据'!E5 -> 0.60438231 | F19: 未披露 | G19: 未披露 | H19: A | I19: (营业收入 − 营业成本合计) ÷ 营业收入 | J19: 应与招股书披露的44.75%/57.22%/60.44%一致
A20: 综合毛利率（招股书披露） | B20: % | C20: ='03_财务原始数据'!C51 -> 0.4475 | D20: ='03_财务原始数据'!D51 -> 0.5722 | E20: ='03_财务原始数据'!E51 -> 0.6044 | F20: — | G20: — | H20: A | I20: 直接引用表3-1披露值，与上一行互为校验 | J20: 差异应为0
A21: 主营业务毛利率（测算） | B21: % | C21: ='03_财务原始数据'!C11/'03_财务原始数据'!C6 -> 0.44216737 | D21: ='03_财务原始数据'!D11/'03_财务原始数据'!D6 -> 0.56740169 | E21: ='03_财务原始数据'!E11/'03_财务原始数据'!E6 -> 0.60130311 | F21: 未披露 | G21: 未披露 | H21: A | I21: 主营业务毛利 ÷ 主营业务收入 | J21: 应与披露的44.22%/56.74%/60.13%一致
A22: 营业利润率 | B22: % | C22: ='03_财务原始数据'!C28/'03_财务原始数据'!C5 -> -0.13426952 | D22: ='03_财务原始数据'!D28/'03_财务原始数据'!D5 -> 0.12819503 | E22: ='03_财务原始数据'!E28/'03_财务原始数据'!E5 -> 0.21639507 | F22: ='03_财务原始数据'!C69/'03_财务原始数据'!C68 -> 0.11620457 | G22: ='03_财务原始数据'!C89/'03_财务原始数据'!C88 -> 0.2623038 | H22: A / B / C | I22: 营业利润 ÷ 营业收入 | J22: —
A23: 归母净利率 | B23: % | C23: ='03_财务原始数据'!C31/'03_财务原始数据'!C5 -> -0.070035769 | D23: ='03_财务原始数据'!D31/'03_财务原始数据'!D5 -> 0.12154 | E23: ='03_财务原始数据'!E31/'03_财务原始数据'!E5 -> 0.16372361 | F23: ='03_财务原始数据'!C72/'03_财务原始数据'!C68 -> 0.11828053 | G23: ='03_财务原始数据'!C91/'03_财务原始数据'!C88 -> 0.23779644 | H23: A / B / C | I23: 归属于母公司所有者的净利润 ÷ 营业收入 | J23: —
A24: 扣非归母净利率 | B24: % | C24: ='03_财务原始数据'!C32/'03_财务原始数据'!C5 -> -0.11323196 | D24: ='03_财务原始数据'!D32/'03_财务原始数据'!D5 -> 0.099901164 | E24: ='03_财务原始数据'!E32/'03_财务原始数据'!E5 -> 0.34765108 | F24: ='03_财务原始数据'!C73/'03_财务原始数据'!C68 -> 0.095198071 | G24: ='03_财务原始数据'!C92/'03_财务原始数据'!C88 -> 0.21169992 | H24: A / B / C | I24: 扣非后归母净利润 ÷ 营业收入；剔除股份支付等一次性项目后的真实盈利水平 | J24: 本行是评估盈利质量的核心指标
A25: 销售费用率 | B25: % | C25: ='03_财务原始数据'!C13/'03_财务原始数据'!C5 -> 0.23702166 | D25: ='03_财务原始数据'!D13/'03_财务原始数据'!D5 -> 0.075309207 | E25: ='03_财务原始数据'!E13/'03_财务原始数据'!E5 -> 0.083096423 | F25: 未披露 | G25: 未披露 | H25: A | I25: 销售费用 ÷ 营业收入 | J25: —
A26: 管理费用率 | B26: % | C26: ='03_财务原始数据'!C14/'03_财务原始数据'!C5 -> 0.083753104 | D26: ='03_财务原始数据'!D14/'03_财务原始数据'!D5 -> 0.031831804 | E26: ='03_财务原始数据'!E14/'03_财务原始数据'!E5 -> 0.23515761 | F26: 未披露 | G26: 未披露 | H26: A | I26: 管理费用 ÷ 营业收入（2025年含股份支付费用34,906.55万元） | J26: —
A27: 管理费用率（剔除股份支付费用） | B27: % | C27: ='03_财务原始数据'!C14/'03_财务原始数据'!C5 -> 0.083753104 | D27: ='03_财务原始数据'!D14/'03_财务原始数据'!D5 -> 0.031831804 | E27: =('03_财务原始数据'!E14-'03_财务原始数据'!E34)/'03_财务原始数据'!E5 -> 0.029736664 | F27: 未披露 | G27: 未披露 | H27: A + E | I27: 2025年 = (管理费用 − 股份支付费用) ÷ 营业收入。股份支付为2025年6月上海宇翼增资一次性确认，全额计入管理费用，无现金流出，属非经常性损益；2023、2024年无该项，公式退化为普通管理费用率 | J27: 剔除后2025年管理费用率约2.97%，低于2024年的6.37%，说明费用控制并未恶化
A28: 研发费用率 | B28: % | C28: ='03_财务原始数据'!C15/'03_财务原始数据'!C5 -> 0.31389693 | D28: ='03_财务原始数据'!D15/'03_财务原始数据'!D5 -> 0.089132158 | E28: ='03_财务原始数据'!E15/'03_财务原始数据'!E5 -> 0.085310551 | F28: 未披露 | G28: 未披露 | H28: A | I28: 研发费用 ÷ 营业收入 | J28: 应与披露的31.39%/17.83%/8.53%一致
A29: 财务费用率 | B29: % | C29: ='03_财务原始数据'!C16/'03_财务原始数据'!C5 -> -0.046028389 | D29: ='03_财务原始数据'!D16/'03_财务原始数据'!D5 -> -0.021878414 | E29: ='03_财务原始数据'!E16/'03_财务原始数据'!E5 -> 0.00058030825 | F29: 未披露 | G29: 未披露 | H29: A | I29: 财务费用 ÷ 营业收入；2023—2024年为负数（利息收入大于支出），2025年转正 | J29: —
A30: 期间费用率合计 | B30: % | C30: ='03_财务原始数据'!C17/'03_财务原始数据'!C5 -> 0.58864268 | D30: ='03_财务原始数据'!D17/'03_财务原始数据'!D5 -> 0.17439476 | E30: ='03_财务原始数据'!E17/'03_财务原始数据'!E5 -> 0.40414495 | F30: 未披露 | G30: 未披露 | H30: A | I30: 期间费用合计 ÷ 营业收入 | J30: —
A31: 加权平均净资产收益率（披露） | B31: % | C31: ='03_财务原始数据'!C52 -> -0.0366 | D31: ='03_财务原始数据'!D52 -> 0.1046 | E31: ='03_财务原始数据'!E52 -> 0.1352 | F31: 未披露 | G31: ='03_财务原始数据'!C95 -> 0.0999 | H31: A / C | I31: 直接引用披露值。2026H1为9.99%（性质C，未经审计） | J31: —
A32: 扣非后加权平均净资产收益率（披露） | B32: % | C32: ='03_财务原始数据'!C53 -> -0.0592 | D32: ='03_财务原始数据'!D53 -> 0.086 | E32: ='03_财务原始数据'!E53 -> 0.287 | F32: 未披露 | G32: ='03_财务原始数据'!C96 -> 0.089 | H32: A / C | I32: 2025年扣非ROE 28.70%显著高于扣非前13.52%，差额即股份支付费用的影响 | J32: 2026H1为8.90%，同比下降12.12个百分点
A33: 期末净资产收益率（简单口径，测算） | B33: % | C33: ='03_财务原始数据'!C31/'03_财务原始数据'!C42 -> -0.037268985 | D33: ='03_财务原始数据'!D31/'03_财务原始数据'!D42 -> 0.074557631 | E33: ='03_财务原始数据'!E31/'03_财务原始数据'!E42 -> 0.10681266 | F33: ='03_财务原始数据'!C72/'03_财务原始数据'!C79 -> 0.018835209 | G33: ='03_财务原始数据'!C91/'03_财务原始数据'!C105 -> 0.095139356 | H33: A / B / C | I33: 归母净利润 ÷ 期末归母权益。与加权平均ROE口径不同（未做时间加权），仅作横向比较参考 | J33: 口径不同，不应与披露的加权ROE直接比较
A34: 有效所得税率 | B34: % | C34: =IF('03_财务原始数据'!C29>0,('03_财务原始数据'!C29-'03_财务原始数据'!C30)/'03_财务原始数据'!C29,"不适用") -> 不适用 | D34: =IF('03_财务原始数据'!D29>0,('03_财务原始数据'!D29-'03_财务原始数据'!D30)/'03_财务原始数据'!D29,"不适用") -> 0.05111521 | E34: =IF('03_财务原始数据'!E29>0,('03_财务原始数据'!E29-'03_财务原始数据'!E30)/'03_财务原始数据'!E29,"不适用") -> 0.24493499 | F34: =IF('03_财务原始数据'!C70>0,('03_财务原始数据'!C70-'03_财务原始数据'!C72)/'03_财务原始数据'!C70,"不适用") -> -0.021223333 | G34: =IF('03_财务原始数据'!C90>0,('03_财务原始数据'!C90-'03_财务原始数据'!C91)/'03_财务原始数据'!C90,"不适用") -> 0.090044149 | H34: A / B / C | I34: (利润总额 − 净利润) ÷ 利润总额。2023年利润总额为负，公式返回“不适用”；2026Q1净利润高于利润总额（所得税费用为负），结果为负值，属税收优惠/递延所得税影响 | J34: 2024年约5.11%、2025年约24.49%，差异主要来自股份支付费用的税前扣除限制及优惠税率适用期间
A35: 非经常性损益净额（归母 − 扣非） | B35: 万元 | C35: ='03_财务原始数据'!C31-'03_财务原始数据'!C32 -> 687.4 | D35: ='03_财务原始数据'!D31-'03_财务原始数据'!D32 -> 1699.82 | E35: ='03_财务原始数据'!E31-'03_财务原始数据'!E32 -> -31254.23 | F35: ='03_财务原始数据'!C72-'03_财务原始数据'!C73 -> 976.02 | G35: ='03_财务原始数据'!C91-'03_财务原始数据'!C92 -> 3006.96 | H35: A / B / C | I35: 归母净利润减去扣非归母净利润。2025年为−31,254.23万元（负数），即非经常性项目净损失，主因是34,906.55万元股份支付费用 | J35: 2026Q1测算值应精确等于披露的非经常性损益净额976.02万元，构成闭环校验
A36: 披露的非经常性损益净额（校验用） | B36: 万元 | C36: 未披露 | D36: 未披露 | E36: 未披露 | F36: ='03_财务原始数据'!C80 -> 976.02 | G36: 未披露 | H36: A / B | I36: 表3-2直接披露值，与上一行2026Q1测算值比对 | J36: 两值必须相等，否则说明归母/扣非取数有误
A38: 表7-3 分产品毛利率与收入结构（依据表4-1收入、表4-2成本用公式测算）
A39: 产品分类 | B39: 2023毛利率 | C39: 2024毛利率 | D39: 2025毛利率 | E39: 2025收入占比 | F39: 2025毛利贡献占比 | G39: 毛利率三年变动(百分点) | H39: 计算口径与公式说明 | I39: 勾稽校验
A40: 四足机器人 | B40: =('04_业务结构原始数据'!B3-'04_业务结构原始数据'!B11)/'04_业务结构原始数据'!B3 -> 0.43710677 | C40: =('04_业务结构原始数据'!D3-'04_业务结构原始数据'!D11)/'04_业务结构原始数据'!D3 -> 0.51646955 | D40: =('04_业务结构原始数据'!F3-'04_业务结构原始数据'!F11)/'04_业务结构原始数据'!F3 -> 0.56719765 | E40: ='04_业务结构原始数据'!F3/'04_业务结构原始数据'!F7 -> 0.41621685 | F40: =('04_业务结构原始数据'!F3-'04_业务结构原始数据'!F11)/('04_业务结构原始数据'!F7-'04_业务结构原始数据'!F11-'04_业务结构原始数据'!F12-'04_业务结构原始数据'!F13-'04_业务结构原始数据'!F14) -> 0.39260938 | G40: =(('04_业务结构原始数据'!F3-'04_业务结构原始数据'!F11)/'04_业务结构原始数据'!F3-('04_业务结构原始数据'!B3-'04_业务结构原始数据'!B11)/'04_业务结构原始数据'!B3)*100 -> 13.009088 | H40: 毛利率 = (该产品主营收入 − 该产品主营成本) ÷ 该产品主营收入；毛利贡献占比 = 该产品毛利 ÷ 主营业务毛利合计 | I40: 机器人组件行应与招股书直接披露的48.76%/56.94%/59.36%一致
A41: 人形机器人 | B41: =('04_业务结构原始数据'!B4-'04_业务结构原始数据'!B12)/'04_业务结构原始数据'!B4 -> 0.87668093 | C41: =('04_业务结构原始数据'!D4-'04_业务结构原始数据'!D12)/'04_业务结构原始数据'!D4 -> 0.6925579 | D41: =('04_业务结构原始数据'!F4-'04_业务结构原始数据'!F12)/'04_业务结构原始数据'!F4 -> 0.63176521 | E41: ='04_业务结构原始数据'!F4/'04_业务结构原始数据'!F7 -> 0.5177652 | F41: =('04_业务结构原始数据'!F4-'04_业务结构原始数据'!F12)/('04_业务结构原始数据'!F7-'04_业务结构原始数据'!F11-'04_业务结构原始数据'!F12-'04_业务结构原始数据'!F13-'04_业务结构原始数据'!F14) -> 0.54399531 | G41: =(('04_业务结构原始数据'!F4-'04_业务结构原始数据'!F12)/'04_业务结构原始数据'!F4-('04_业务结构原始数据'!B4-'04_业务结构原始数据'!B12)/'04_业务结构原始数据'!B4)*100 -> -24.491573 | H41: 毛利率 = (该产品主营收入 − 该产品主营成本) ÷ 该产品主营收入；毛利贡献占比 = 该产品毛利 ÷ 主营业务毛利合计 | I41: 机器人组件行应与招股书直接披露的48.76%/56.94%/59.36%一致
A42: 机器人组件 | B42: =('04_业务结构原始数据'!B5-'04_业务结构原始数据'!B13)/'04_业务结构原始数据'!B5 -> 0.48764272 | C42: =('04_业务结构原始数据'!D5-'04_业务结构原始数据'!D13)/'04_业务结构原始数据'!D5 -> 0.5693517 | D42: =('04_业务结构原始数据'!F5-'04_业务结构原始数据'!F13)/'04_业务结构原始数据'!F5 -> 0.59356139 | E42: ='04_业务结构原始数据'!F5/'04_业务结构原始数据'!F7 -> 0.06189131 | F42: =('04_业务结构原始数据'!F5-'04_业务结构原始数据'!F13)/('04_业务结构原始数据'!F7-'04_业务结构原始数据'!F11-'04_业务结构原始数据'!F12-'04_业务结构原始数据'!F13-'04_业务结构原始数据'!F14) -> 0.061094472 | G42: =(('04_业务结构原始数据'!F5-'04_业务结构原始数据'!F13)/'04_业务结构原始数据'!F5-('04_业务结构原始数据'!B5-'04_业务结构原始数据'!B13)/'04_业务结构原始数据'!B5)*100 -> 10.591867 | H42: 毛利率 = (该产品主营收入 − 该产品主营成本) ÷ 该产品主营收入；毛利贡献占比 = 该产品毛利 ÷ 主营业务毛利合计 | I42: 机器人组件行应与招股书直接披露的48.76%/56.94%/59.36%一致
A43: 其他 | B43: =('04_业务结构原始数据'!B6-'04_业务结构原始数据'!B14)/'04_业务结构原始数据'!B6 -> 0.21114082 | C43: =('04_业务结构原始数据'!D6-'04_业务结构原始数据'!D14)/'04_业务结构原始数据'!D6 -> 0.23229365 | D43: =('04_业务结构原始数据'!F6-'04_业务结构原始数据'!F14)/'04_业务结构原始数据'!F6 -> 0.33526103 | E43: ='04_业务结构原始数据'!F6/'04_业务结构原始数据'!F7 -> 0.0041266363 | F43: =('04_业务结构原始数据'!F6-'04_业务结构原始数据'!F14)/('04_业务结构原始数据'!F7-'04_业务结构原始数据'!F11-'04_业务结构原始数据'!F12-'04_业务结构原始数据'!F13-'04_业务结构原始数据'!F14) -> 0.002300837 | G43: =(('04_业务结构原始数据'!F6-'04_业务结构原始数据'!F14)/'04_业务结构原始数据'!F6-('04_业务结构原始数据'!B6-'04_业务结构原始数据'!B14)/'04_业务结构原始数据'!B6)*100 -> 12.412021 | H43: 毛利率 = (该产品主营收入 − 该产品主营成本) ÷ 该产品主营收入；毛利贡献占比 = 该产品毛利 ÷ 主营业务毛利合计 | I43: 机器人组件行应与招股书直接披露的48.76%/56.94%/59.36%一致
A44: 主营业务合计 | B44: =('04_业务结构原始数据'!B7-'04_业务结构原始数据'!B11-'04_业务结构原始数据'!B12-'04_业务结构原始数据'!B13-'04_业务结构原始数据'!B14)/'04_业务结构原始数据'!B7 -> 0.44216737 | C44: =('04_业务结构原始数据'!D7-'04_业务结构原始数据'!D11-'04_业务结构原始数据'!D12-'04_业务结构原始数据'!D13-'04_业务结构原始数据'!D14)/'04_业务结构原始数据'!D7 -> 0.56740143 | D44: =('04_业务结构原始数据'!F7-'04_业务结构原始数据'!F11-'04_业务结构原始数据'!F12-'04_业务结构原始数据'!F13-'04_业务结构原始数据'!F14)/'04_业务结构原始数据'!F7 -> 0.60130305 | E44: 1 | F44: 1 | G44: — | H44: 合计毛利率 = (主营收入合计 − 主营成本合计) ÷ 主营收入合计 | I44: 应与表7-2“主营业务毛利率（测算）”一致
A45: 结构性发现：人形机器人2023年毛利率高达87.67%，但当年仅销售5台（收入296.71万元），属小批量样机性质，不具代表性；随着2024年放量至412台、2025年放量至5,215台，毛利率回落至69.26%、63.18%，呈现典型的“新品溢价→规模定价”曲线。同期四足机器人毛利率由43.71%提升至51.65%、56.72%（规模效应与成本下探），两者走势相反，说明公司整体毛利率上行（44.75%→60.44%）主要由高毛利的人形机器人收入占比提升（1.88%→51.78%）驱动，而非单一产品盈利能力的普遍改善。
A47: 表7-4 销售量与平均单价对收入变动的贡献拆解（量价分析）
A48: 拆解项 | B48: 单位 | C48: 四足2024 | D48: 四足2025 | E48: 人形2024 | F48: 人形2025 | G48: 输入项性质 | H48: 计算口径与公式说明 | I48: 勾稽校验
A49: 收入变动总额 | B49: 万元 | C49: ='04_业务结构原始数据'!D21-'04_业务结构原始数据'!C21 -> 11116.28 | D49: ='04_业务结构原始数据'!F21-'04_业务结构原始数据'!D21 -> 46708.19 | E49: ='04_业务结构原始数据'!D24-'04_业务结构原始数据'!C24 -> 10433.05 | F49: ='04_业务结构原始数据'!F24-'04_业务结构原始数据'!D24 -> 76053.43 | G49: A | H49: 本期该产品主营业务收入 − 上期该产品主营业务收入 | I49: —
A50: 其中：销量变动贡献 | B50: 万元 | C50: =('04_业务结构原始数据'!D19-'04_业务结构原始数据'!C19)*('04_业务结构原始数据'!C21/'04_业务结构原始数据'!C19) -> 15357.716 | D50: =('04_业务结构原始数据'!F19-'04_业务结构原始数据'!D19)*('04_业务结构原始数据'!D21/'04_业务结构原始数据'!D19) -> 51371.572 | E50: =('04_业务结构原始数据'!D22-'04_业务结构原始数据'!C22)*('04_业务结构原始数据'!C24/'04_业务结构原始数据'!C22) -> 24152.194 | F50: =('04_业务结构原始数据'!F22-'04_业务结构原始数据'!D22)*('04_业务结构原始数据'!D24/'04_业务结构原始数据'!D22) -> 125085.04 | G50: A + E | H50: (本期销量 − 上期销量) × 上期平均单价；上期平均单价按“上期收入 ÷ 上期销量”现场计算 | I50: 与招股书披露的2025年四足51,371.57万元、人形125,085.09万元核对
A51: 其中：单价变动贡献 | B51: 万元 | C51: =('04_业务结构原始数据'!D19)*(('04_业务结构原始数据'!D21/'04_业务结构原始数据'!D19)-('04_业务结构原始数据'!C21/'04_业务结构原始数据'!C19)) -> -4241.4359 | D51: =('04_业务结构原始数据'!F19)*(('04_业务结构原始数据'!F21/'04_业务结构原始数据'!F19)-('04_业务结构原始数据'!D21/'04_业务结构原始数据'!D19)) -> -4663.3819 | E51: =('04_业务结构原始数据'!D22)*(('04_业务结构原始数据'!D24/'04_业务结构原始数据'!D22)-('04_业务结构原始数据'!C24/'04_业务结构原始数据'!C22)) -> -13719.144 | F51: =('04_业务结构原始数据'!F22)*(('04_业务结构原始数据'!F24/'04_业务结构原始数据'!F22)-('04_业务结构原始数据'!D24/'04_业务结构原始数据'!D22)) -> -49031.612 | G51: A + E | H51: 本期销量 × (本期平均单价 − 上期平均单价)；本期平均单价按“本期收入 ÷ 本期销量”现场计算 | I51: 与招股书披露的2025年四足−4,663.39万元、人形−49,031.66万元核对
A52: 拆解合计校验（销量贡献 + 单价贡献） | B52: 万元 | C52: =C50+C51 -> 11116.28 | D52: =D50+D51 -> 46708.19 | E52: =E50+E51 -> 10433.05 | F52: =F50+F51 -> 76053.43 | G52: E | H52: 应与本表第49行“收入变动总额”完全相等（量价拆解闭合性检验） | I52: 差异应为0；若不为0说明销量或收入取数有误
A53: 销量贡献占收入变动比例 | B53: % | C53: =C50/C49 -> 1.3815517 | D53: =D50/D49 -> 1.0998408 | E53: =E50/E49 -> 2.3149696 | F53: =F50/F49 -> 1.6446995 | G53: E | H53: 销量变动贡献 ÷ 收入变动总额；超过100%表示单价变动为负向拖累 | I53: 2025年四足约109.98%、人形约164.47%，与招股书披露一致
A54: 披露的平均单价（四舍五入值，仅作对照） | B54: 万元/台 | C54: ='04_业务结构原始数据'!D20 -> 3.23 | D54: ='04_业务结构原始数据'!F20 -> 3.03 | E54: ='04_业务结构原始数据'!D23 -> 26.04 | F54: ='04_业务结构原始数据'!F23 -> 16.64 | G54: A | H54: 招股书直接披露的四舍五入单价（D列为2024、F列为2025）；用该值拆解会产生微小尾差，故上方测算不使用本行 | I54: —
A55: 测算的平均单价（收入 ÷ 销量，精确值） | B55: 万元/台 | C55: ='04_业务结构原始数据'!D21/'04_业务结构原始数据'!D19 -> 3.2307133 | D55: ='04_业务结构原始数据'!F21/'04_业务结构原始数据'!F19 -> 3.0282832 | E55: ='04_业务结构原始数据'!D24/'04_业务结构原始数据'!D22 -> 26.043107 | F55: ='04_业务结构原始数据'!F24/'04_业务结构原始数据'!F22 -> 16.641072 | G55: A + E | H55: 四足2024约3.2307、四足2025约3.0283；人形2024约26.0431、人形2025约16.6410 | I55: 与披露的四舍五入单价一致（差异<0.01万元/台）
A56: 量价拆解结论：两大产品线2025年的收入增长均由销量驱动、并被单价下行部分抵消。四足机器人销量贡献+51,371.57万元（占变动额109.98%）、单价拖累−4,663.39万元（−9.98%）；人形机器人销量贡献+125,085.09万元（占164.47%）、单价拖累−49,031.66万元（−64.47%）。人形机器人平均单价由2023年59.34万元/台降至2025年16.64万元/台（累计降幅71.96%），是公司主动价格下探以换取市场规模的直接证据，也是未来毛利率能否维持60%以上的关键变量。
A58: 表7-5 现金流质量、营运能力与资产结构
A59: 指标 | B59: 单位 | C59: 2023年度 | D59: 2024年度 | E59: 2025年度 | F59: 2026年1-3月 | G59: 2026年1-6月 | H59: 计算口径与公式说明 | I59: 数据质量提示
A60: 经营活动现金流净额 ÷ 营业收入 | B60: % | C60: ='03_财务原始数据'!C37/'03_财务原始数据'!C5 -> 0.031058652 | D60: ='03_财务原始数据'!D37/'03_财务原始数据'!D5 -> 0.24491554 | E60: ='03_财务原始数据'!E37/'03_财务原始数据'!E5 -> 0.39427641 | F60: ='03_财务原始数据'!C74/'03_财务原始数据'!C68 -> 0.081353607 | G60: ='03_财务原始数据'!C97/'03_财务原始数据'!C88 -> 0.20095134 | H60: A / B / C | I60: 衡量收入的现金含量（收现比） | J60: 2023年仅3.11%，2024年跃升至约48.98%，2025年约39.43%，2026H1降至20.09%（半年口径，未年化）
A61: 净现比：经营现金流净额 ÷ 扣非归母净利润 | B61: 倍 | C61: =IF('03_财务原始数据'!C32>0,'03_财务原始数据'!C37/'03_财务原始数据'!C32,"不适用") -> 不适用 | D61: =IF('03_财务原始数据'!D32>0,'03_财务原始数据'!D37/'03_财务原始数据'!D32,"不适用") -> 2.4515785 | E61: =IF('03_财务原始数据'!E32>0,'03_财务原始数据'!E37/'03_财务原始数据'!E32,"不适用") -> 1.1341153 | F61: =IF('03_财务原始数据'!C73>0,'03_财务原始数据'!C74/'03_财务原始数据'!C73,"不适用") -> 0.85457201 | G61: =IF('03_财务原始数据'!C92>0,'03_财务原始数据'!C97/'03_财务原始数据'!C92,"不适用") -> 0.9492273 | H61: A / B / C | I61: 扣非净利润的现金保障倍数，>1 表示利润有充足现金支撑 | J61: 2023年扣非为亏损，返回“不适用”
A62: 净现比：经营现金流净额 ÷ 归母净利润 | B62: 倍 | C62: =IF('03_财务原始数据'!C31>0,'03_财务原始数据'!C37/'03_财务原始数据'!C31,"不适用") -> 不适用 | D62: =IF('03_财务原始数据'!D31>0,'03_财务原始数据'!D37/'03_财务原始数据'!D31,"不适用") -> 2.0151024 | E62: =IF('03_财务原始数据'!E31>0,'03_财务原始数据'!E37/'03_财务原始数据'!E31,"不适用") -> 2.408183 | F62: =IF('03_财务原始数据'!C72>0,'03_财务原始数据'!C74/'03_财务原始数据'!C72,"不适用") -> 0.68780217 | G62: =IF('03_财务原始数据'!C91>0,'03_财务原始数据'!C97/'03_财务原始数据'!C91,"不适用") -> 0.84505615 | H62: A / B / C | I62: 归母净利润的现金保障倍数。2025年该倍数（约2.41倍）远高于扣非口径（约1.13倍），差额正是股份支付费用“减少账面利润但不流出现金”的结果 | J62: 重要分析线索
A63: 总资产周转率 | B63: 次 | C63: 期初数未披露 | D63: ='03_财务原始数据'!D5/(('03_财务原始数据'!C39+'03_财务原始数据'!D39)/2) -> 0.81863859 | E63: ='03_财务原始数据'!E5/(('03_财务原始数据'!D39+'03_财务原始数据'!E39)/2) -> 0.71753506 | F63: 期初数不足 | G63: ='03_财务原始数据'!C88/(('03_财务原始数据'!E39+'03_财务原始数据'!C101)/2) -> 0.32669247 | H63: A / C | I63: 营业收入 ÷ 平均资产总额。2026H1列为半年数，未年化，不可与年度值直接比较 | J63: 2024年约0.41次、2025年约0.72次，资产使用效率显著提升
A64: 资产负债率（合并，测算） | B64: % | C64: =1-'03_财务原始数据'!C42/'03_财务原始数据'!C39 -> 0.23570999 | D64: =1-'03_财务原始数据'!D42/'03_财务原始数据'!D39 -> 0.16187274 | E64: =1-'03_财务原始数据'!E42/'03_财务原始数据'!E39 -> 0.18821025 | F64: =1-'03_财务原始数据'!C79/'03_财务原始数据'!C77 -> 0.23235606 | G64: ='03_财务原始数据'!C104 -> 0.2511 | H64: A / B / C | I64: 测算口径 = 1 − 归母权益 ÷ 资产总额（假定少数股东权益极小）。2026H1列直接引用公告书披露值 | J64: 2025年测算值应与披露的18.82%基本一致；若差异明显说明存在少数股东权益
A65: 资产负债率（合并，披露） | B65: % | C65: ='03_财务原始数据'!C48 -> 0.2357 | D65: ='03_财务原始数据'!D48 -> 0.1619 | E65: ='03_财务原始数据'!E48 -> 0.1882 | F65: 未披露 | G65: ='03_财务原始数据'!C104 -> 0.2511 | H65: A / C | I65: 直接引用披露值，与上一行互为校验 | J65: 差异应为0
A66: 流动资产占总资产比例 | B66: % | C66: ='03_财务原始数据'!C40/'03_财务原始数据'!C39 -> 0.83395341 | D66: ='03_财务原始数据'!D40/'03_财务原始数据'!D39 -> 0.83181108 | E66: ='03_财务原始数据'!E40/'03_财务原始数据'!E39 -> 0.69179988 | F66: 未披露 | G66: ='03_财务原始数据'!C99/'03_财务原始数据'!C101 -> 0.75113954 | H66: A / C | I66: 资产轻量化程度。2025年末流动资产占比约69.18%，非流动资产占比约30.82% | J66: —
A67: 存货占流动资产比例 | B67: % | C67: 未提取 | D67: 未提取 | E67: ='03_财务原始数据'!E44/'03_财务原始数据'!E40 -> 0.16567958 | F67: 未披露 | G67: 未披露 | H67: A / C | I67: 存货（账面价值）÷ 流动资产。2023、2024年存货数据未从招股书中提取（见表10待核验） | J67: 2025年末存货36,775.34万元，占流动资产约16.57%；已计提跌价准备2,457.37万元
A68: 存货跌价准备计提率 | B68: % | C68: 未提取 | D68: 未提取 | E68: ='03_财务原始数据'!E45/('03_财务原始数据'!E44+'03_财务原始数据'!E45) -> 0.062635745 | F68: 未披露 | G68: 未披露 | H68: A | I68: 存货跌价准备 ÷ 存货账面余额（= 账面价值 + 跌价准备） | J68: 2025年末约6.26%
A69: 存货周转率（近似口径） | B69: 次 | C69: 数据缺失 | D69: 数据缺失 | E69: ='03_财务原始数据'!E9/'03_财务原始数据'!E44 -> 1.8171424 | F69: 数据缺失 | G69: 数据缺失 | H69: A + E | I69: 受限于期初存货未提取，此处以“主营业务成本 ÷ 期末存货”近似，非标准平均余额口径，仅供参考 | J69: 口径受限，正式引用前必须补齐2024年末存货数（见表10）
A70: 应收账款周转率 | B70: 次 | C70: 数据缺失 | D70: 数据缺失 | E70: 数据缺失 | F70: 数据缺失 | G70: 数据缺失 | H70: — | I70: 招股书未在本次提取范围内直接披露报告期各期末应收账款账面余额；由表5-4前五大应收合计1,769.78万元占比28.59%可反推2025年末余额约6,196万元，但该反推未经原文确认（见表10） | J70: 本行暂不计算，待人工核验原始披露后补入
A71: 应收账款坏账计提比例（公司） | B71: % | C71: ='03_财务原始数据'!C57 -> 0.0613 | D71: ='03_财务原始数据'!D57 -> 0.0655 | E71: ='03_财务原始数据'!E57 -> 0.0513 | F71: 未披露 | G71: 未披露 | H71: A | I71: 公司自身预期信用损失计提比例 | J71: 三年均显著低于同业平均（2025年5.13% vs 14.07%）
A72: 坏账计提比例差额（公司 − 同业，百分点） | B72: 百分点 | C72: =('03_财务原始数据'!C57-'03_财务原始数据'!C58)*100 -> -6.06 | D72: =('03_财务原始数据'!D57-'03_财务原始数据'!D58)*100 -> -7.26 | E72: =('03_财务原始数据'!E57-'03_财务原始数据'!E58)*100 -> -8.94 | F72: 未披露 | G72: 未披露 | H72: A + E | I72: 负值表示公司计提比例低于同业平均。若按同业平均比例计提，2025年将额外减少利润，该敏感性影响需以确认后的应收账款余额测算 | J72: 会计估计差异点，属重要关注事项
A73: 现金流质量结论：报告期经营活动现金流净额持续为正，2024—2025年大幅超过账面净利润，2025年达66,998.18万元（占营业收入39.43%），显示公司具有较强的回款能力和较低的应收依赖。但2026年1-3月经营现金流净额仅3,439.96万元，同比下降85.65%；2026年1-6月为23,154.53万元，同比下降32.53%，与同期收入+48.54%的增速形成明显背离，是本底稿识别出的最需要跟踪的先行指标。
A75: 表7-6 研发投入与科创板科创属性指标校验
A76: 指标 | B76: 单位 | C76: 2023年度 | D76: 2024年度 | E76: 2025年度 | F76: 2026年1-3月 | G76: 2026年1-6月 | H76: 计算口径与公式说明 | I76: 勾稽校验
A77: 研发费用 | B77: 万元 | C77: ='03_财务原始数据'!C15 -> 4995.18 | D77: ='03_财务原始数据'!D15 -> 7001.7 | E77: ='03_财务原始数据'!E15 -> 14496.56 | F77: 仅披露同比增额 | G77: 仅披露同比增额 | H77: A | I77: 直接引用表3-1研发费用 | J77: Q1披露同比增额3,832.80万元、H1披露同比增额8,203.74万元，均未披露绝对值
A78: 研发费用同比增速 | B78: % | C78: 上年数未披露 | D78: ='03_财务原始数据'!D15/'03_财务原始数据'!C15-1 -> 0.40169123 | E78: ='03_财务原始数据'!E15/'03_财务原始数据'!D15-1 -> 1.0704343 | F78: 披露为增额 | G78: 披露为增额 | H78: A / B / C | I78: 研发费用 ÷ 上年研发费用 − 1 | J78: 2026Q1、H1招股书与公告书仅披露同比增加额，未披露绝对值，故本表不推算
A79: 研发费用率（测算） | B79: % | C79: ='03_财务原始数据'!C15/'03_财务原始数据'!C5 -> 0.31389693 | D79: ='03_财务原始数据'!D15/'03_财务原始数据'!D5 -> 0.089132158 | E79: ='03_财务原始数据'!E15/'03_财务原始数据'!E5 -> 0.085310551 | F79: 未披露 | G79: 未披露 | H79: A | I79: 研发费用 ÷ 营业收入 | J79: 应与披露的31.39%/17.83%/8.53%一致
A80: 研发投入占营业收入比例（披露） | B80: % | C80: ='03_财务原始数据'!C54 -> 0.3139 | D80: ='03_财务原始数据'!D54 -> 0.1783 | E80: ='03_财务原始数据'!E54 -> 0.0853 | F80: — | G80: — | H80: A | I80: 直接引用披露值，与上一行互为校验 | J80: 差异应为0
A81: 三年研发费用累计（科创属性指标） | B81: 万元 | C81: — | D81: =SUM('03_财务原始数据'!C15:E15) -> 26493.44 | E81: — | F81: — | G81: — | H81: A | I81: 2023+2024+2025年研发费用之和 | J81: 科创属性要求最近三年累计研发费用≥8,000万元；测算值应约等于26,493.44万元，达标
A82: 人均研发费用 | B82: 万元/人 | C82: 研发人数未披露 | D82: 研发人数未披露 | E82: ='03_财务原始数据'!E15/'03_财务原始数据'!E60 -> 78.785652 | F82: 未披露 | G82: 未披露 | H82: A + E | I82: 2025年研发费用 ÷ 2025年末研发人员数（184人） | J82: 2025年约78.79万元/人
A83: 研发人员占员工总数比例（测算） | B83: % | C83: 未披露 | D83: 未披露 | E83: ='03_财务原始数据'!E60/'03_财务原始数据'!E61 -> 0.35658915 | F83: 未披露 | G83: 未披露 | H83: A | I83: 研发人员 ÷ 员工总数 | J83: 科创属性要求≥10%；测算值应约等于披露的35.66%，达标
A84: 研发费用 ÷ 扣非归母净利润 | B84: % | C84: =IF('03_财务原始数据'!C32>0,'03_财务原始数据'!C15/'03_财务原始数据'!C32,"不适用") -> 不适用 | D84: =IF('03_财务原始数据'!D32>0,'03_财务原始数据'!D15/'03_财务原始数据'!D32,"不适用") -> 0.8922034 | E84: =IF('03_财务原始数据'!E32>0,'03_财务原始数据'!E15/'03_财务原始数据'!E32,"不适用") -> 0.2453913 | F84: 未披露 | G84: 未披露 | H84: A | I84: 衡量研发投入相对于自身盈利能力的强度 | J84: 2024年约89.22%、2025年约24.54%
A85: 研发费用 ÷ 营业成本 | B85: % | C85: ='03_财务原始数据'!C15/'03_财务原始数据'!C8 -> 0.56816028 | D85: ='03_财务原始数据'!D15/'03_财务原始数据'!D8 -> 0.41665848 | E85: ='03_财务原始数据'!E15/'03_财务原始数据'!E8 -> 0.21563887 | F85: 未披露 | G85: 未披露 | H85: A | I85: 研发强度相对于生产投入的比例 | J85: —
A86: 科创属性指标校验结果（依据表2-1与表3-1）：①最近三年累计研发费用26,493.44万元 > 8,000万元门槛；②研发人员占员工总数35.66% > 10%门槛；③截至2026年1月31日拥有境内发明专利20项（境内外注册专利合计262项），满足发明专利数量要求；④最近三年营业收入复合增长率226.78%，远高于门槛。四项指标均达标。需要关注：研发费用率由2023年的31.39%快速降至2025年的8.53%，绝对额虽仍在增长（4,995.18万→14,496.56万元），但增速远低于收入增速；后续能否支撑“智能机器人模型研发项目”202,245.93万元的募投强度，是判断技术领先性可持续性的关键。
A88: 表7-7 发行定价、估值倍数复算与募集资金超募测算
A89: 指标 | B89: 单位 | C89: 本底稿复算值 | D89: 披露值 | E89: 复算 − 披露 | F89: 输入项性质 | G89: 披露来源 | H89: 计算口径与公式说明 | I89: 校验判定
A90: 按发行价计算的募集资金总额 | B90: 万元 | C90: ='02_发行上市原始数据'!B5*'02_发行上市原始数据'!B6/10000 -> 609932.22 | D90: ='02_发行上市原始数据'!B26 -> 609932.22 | E90: =C90-D90 -> 0.0047200001 | F90: A + E | G90: S2 | H90: 发行价格 × 发行股票数量 ÷ 10,000 | I90: 应等于609,932.22万元
A91: 募集资金净额（复算） | B91: 万元 | C91: ='02_发行上市原始数据'!B26-'02_发行上市原始数据'!B27 -> 591714.91 | D91: ='02_发行上市原始数据'!B33 -> 591714.92 | E91: =C91-D91 -> -0.01 | F91: A + E | G91: S2 | H91: 募集资金总额 − 发行费用合计（不含增值税） | I91: 允许±0.02万元四舍五入尾差
A92: 按发行价计算的发行后总市值 | B92: 万元 | C92: ='02_发行上市原始数据'!B5*'02_发行上市原始数据'!B10/10000 -> 6099322.2 | D92: ='02_发行上市原始数据'!B45*10000 -> 6099300 | E92: =C92-D92 -> 22.2472 | F92: A + E | G92: S2 | H92: 复算：发行价格 × 发行后总股本 ÷ 10,000，单位万元。披露值原单位为亿元，本行已按 ×10,000 换算为万元后再作差额比较，避免单位不一致造成的伪差异 | I92: 允许±1万元（披露值609.93亿元仅保留两位小数，换算后尾差属正常）
A93: 【发行市盈率复算】
A94: 发行市盈率①：扣非后净利 ÷ 发行前总股本 | B94: 倍 | C94: ='02_发行上市原始数据'!B5/('03_财务原始数据'!E32/('02_发行上市原始数据'!B9)) -> 92.921947 | D94: ='02_发行上市原始数据'!B36 -> 92.92 | E94: =C94-D94 -> 0.0019467513 | F94: A + E | G94: S2/S3 | H94: 发行价 ÷ (2025年扣非后归母净利润 ÷ 发行前总股本)。扣非后净利59,075.28万元高于扣非前27,821.05万元，故该口径市盈率最低 | I94: 差异应为0
A95: 发行市盈率②：扣非前净利 ÷ 发行前总股本 | B95: 倍 | C95: ='02_发行上市原始数据'!B5/('03_财务原始数据'!E31/('02_发行上市原始数据'!B9)) -> 197.31067 | D95: ='02_发行上市原始数据'!B37 -> 197.31 | E95: =C95-D95 -> 0.00067024717 | F95: A + E | G95: S2/S3 | H95: 发行价 ÷ (2025年归母净利润 ÷ 发行前总股本) | I95: 差异应为0
A96: 发行市盈率③：扣非后净利 ÷ 发行后总股本 | B96: 倍 | C96: ='02_发行上市原始数据'!B5/('03_财务原始数据'!E32/('02_发行上市原始数据'!B11)) -> 103.24661 | D96: ='02_发行上市原始数据'!B38 -> 103.25 | E96: =C96-D96 -> -0.0033924985 | F96: A + E | G96: S2/S3 | H96: 发行价 ÷ (2025年扣非后归母净利润 ÷ 发行后总股本)；等价于发行后市值 ÷ 扣非后净利 | I96: 差异应为0
A97: 发行市盈率④：扣非前净利 ÷ 发行后总股本（公告书对外口径） | B97: 倍 | C97: ='02_发行上市原始数据'!B5/('03_财务原始数据'!E31/('02_发行上市原始数据'!B11)) -> 219.23408 | D97: ='02_发行上市原始数据'!B39 -> 219.23 | E97: =C97-D97 -> 0.0040780524 | F97: A + E | G97: S2/S3 | H97: 发行价 ÷ (2025年归母净利润 ÷ 发行后总股本)。按“扣非前后孰低”原则，公告书以本口径219.23倍作为对外披露的发行市盈率 | I97: 该值为对外正式口径，引用时应以此为准
A98: 发行市销率①：营收 ÷ 发行前总股本 | B98: 倍 | C98: ='02_发行上市原始数据'!B5/('03_财务原始数据'!E5/('02_发行上市原始数据'!B9)) -> 32.304415 | D98: ='02_发行上市原始数据'!B40 -> 32.3 | E98: =C98-D98 -> 0.0044147416 | F98: A + E | G98: S2 | H98: 发行价 ÷ (2025年营业收入 ÷ 发行前总股本) | I98: 差异应为0
A99: 发行市销率②：营收 ÷ 发行后总股本（摊薄后静态） | B99: 倍 | C99: ='02_发行上市原始数据'!B5/('03_财务原始数据'!E5/('02_发行上市原始数据'!B11)) -> 35.893794 | D99: ='02_发行上市原始数据'!B41 -> 35.89 | E99: =C99-D99 -> 0.0037941573 | F99: A + E | G99: S2 | H99: 发行价 ÷ (2025年营业收入 ÷ 发行后总股本)；等价于发行后市值 ÷ 2025年营业收入 | I99: 差异应为0
A100: 发行后每股收益（扣非前后孰低） | B100: 元/股 | C100: =MIN('03_财务原始数据'!E31,'03_财务原始数据'!E32)*10000/('02_发行上市原始数据'!B10) -> 0.68784927 | D100: ='02_发行上市原始数据'!B43 -> 0.69 | E100: =C100-D100 -> -0.0021507325 | F100: A + E | G100: S2 | H100: MIN(2025年归母净利, 2025年扣非归母净利) ÷ 发行后总股本（股） | I100: 差异应为0
A101: 发行后每股净资产 | B101: 元/股 | C101: =('03_财务原始数据'!E42+'02_发行上市原始数据'!B33)*10000/('02_发行上市原始数据'!B10) -> 21.069367 | D101: ='02_发行上市原始数据'!B44 -> 21.07 | E101: =C101-D101 -> -0.00063279695 | F101: A + E | G101: S2 | H101: (2025年末归母所有者权益 + 募集资金净额) ÷ 发行后总股本 | I101: 差异应为0
A102: 发行市净率 | B102: 倍 | C102: ='02_发行上市原始数据'!B5/(('03_财务原始数据'!E42+'02_发行上市原始数据'!B33)*10000/('02_发行上市原始数据'!B10)) -> 7.1573104 | D102: ='02_发行上市原始数据'!B42 -> 7.16 | E102: =C102-D102 -> -0.0026896476 | F102: A + E | G102: S2 | H102: 发行价 ÷ 发行后每股净资产 | I102: 差异应为0
A103: 【相对估值参照】
A104: 发行市盈率④ ÷ 行业平均静态市盈率 | B104: 倍 | C104: ='02_发行上市原始数据'!B39/'02_发行上市原始数据'!B47 -> 5.6854253 | F104: A + E | G104: S2 | H104: 公司发行市盈率 ÷ 所属行业（C34通用设备制造业）最近一个月平均静态市盈率38.56倍 | I104: 测算约5.69倍，发行定价显著高于行业均值
A105: 发行市销率② ÷ 可比公司静态市销率均值 | B105: 倍 | C105: ='02_发行上市原始数据'!B41/'02_发行上市原始数据'!B48 -> 1.8181358 | F105: A + E | G105: S2 | H105: 公司发行市销率35.89倍 ÷ 可比公司（优必选、越疆）2025年静态市销率算术平均19.74倍 | I105: 测算约1.82倍，即较可比公司溢价约82%
A106: 【募集资金与超募测算】
...

Sheet 08_趋势图表
A1: 趋势图表（图表数据区全部为公式，实时引用『03 / 04 / 05 / 02』表；修改原始数据后图表自动更新）
A2: 使用方式：下方“图表数据区”（A–H列）是全部19张图表的唯一数据源，均为公式引用，不含硬编码数值，可直接编辑、替换或增删行。图表本体自数据区之后排列。在 Excel 中调整图表类型、配色或坐标轴时直接选中图表操作即可，不会影响公式区。
A3: 图表数据区 1：年度营业收入、净利润、非经常性损益与经营现金流（单位：万元，性质A）
A4: 报告期 | B4: 营业收入 | C4: 营业收入同比 | D4: 归母净利润 | E4: 扣非归母净利润 | F4: 非经常性损益净额 | G4: 经营活动现金流净额 | H4: 口径说明
A5: 2023年度 | B5: ='03_财务原始数据'!C5 -> 15913.44 | C5: — | D5: ='03_财务原始数据'!C31 -> -1114.51 | E5: ='03_财务原始数据'!C32 -> -1801.91 | F5: ='03_财务原始数据'!C31-'03_财务原始数据'!C32 -> 687.4 | G5: ='03_财务原始数据'!C37 -> 494.25 | H5: 性质A（经审计）
A6: 2024年度 | B6: ='03_财务原始数据'!D5 -> 78554.14 | C6: ='03_财务原始数据'!D5/'03_财务原始数据'!C5-1 -> 3.9363393 | D6: ='03_财务原始数据'!D31 -> 9547.47 | E6: ='03_财务原始数据'!D32 -> 7847.65 | F6: ='03_财务原始数据'!D31-'03_财务原始数据'!D32 -> 1699.82 | G6: ='03_财务原始数据'!D37 -> 19239.13 | H6: 性质A（经审计）
A7: 2025年度 | B7: ='03_财务原始数据'!E5 -> 169926.93 | C7: ='03_财务原始数据'!E5/'03_财务原始数据'!D5-1 -> 1.1631824 | D7: ='03_财务原始数据'!E31 -> 27821.05 | E7: ='03_财务原始数据'!E32 -> 59075.28 | F7: ='03_财务原始数据'!E31-'03_财务原始数据'!E32 -> -31254.23 | G7: ='03_财务原始数据'!E37 -> 66998.18 | H7: 性质A（经审计）
A9: 图表数据区 2：盈利能力与费用率趋势（性质A；剔除股份支付列为性质E·测算）
A10: 报告期 | B10: 综合毛利率 | C10: 扣非归母净利率 | D10: 销售费用率 | E10: 管理费用率 | F10: 管理费用率(剔除股份支付) | G10: 研发费用率 | H10: 口径说明
A11: 2023年度 | B11: ='03_财务原始数据'!C51 -> 0.4475 | C11: ='03_财务原始数据'!C32/'03_财务原始数据'!C5 -> -0.11323196 | D11: ='03_财务原始数据'!C13/'03_财务原始数据'!C5 -> 0.23702166 | E11: ='03_财务原始数据'!C14/'03_财务原始数据'!C5 -> 0.083753104 | F11: =('03_财务原始数据'!C14-IF('03_财务原始数据'!C34="",0,'03_财务原始数据'!C34))/'03_财务原始数据'!C5 -> 0.083753104 | G11: ='03_财务原始数据'!C15/'03_财务原始数据'!C5 -> 0.31389693 | H11: 剔除股份支付列 = (管理费用 − 股份支付费用) ÷ 营业收入，性质E·测算
A12: 2024年度 | B12: ='03_财务原始数据'!D51 -> 0.5722 | C12: ='03_财务原始数据'!D32/'03_财务原始数据'!D5 -> 0.099901164 | D12: ='03_财务原始数据'!D13/'03_财务原始数据'!D5 -> 0.075309207 | E12: ='03_财务原始数据'!D14/'03_财务原始数据'!D5 -> 0.031831804 | F12: =('03_财务原始数据'!D14-IF('03_财务原始数据'!D34="",0,'03_财务原始数据'!D34))/'03_财务原始数据'!D5 -> 0.031831804 | G12: ='03_财务原始数据'!D15/'03_财务原始数据'!D5 -> 0.089132158 | H12: 剔除股份支付列 = (管理费用 − 股份支付费用) ÷ 营业收入，性质E·测算
A13: 2025年度 | B13: ='03_财务原始数据'!E51 -> 0.6044 | C13: ='03_财务原始数据'!E32/'03_财务原始数据'!E5 -> 0.34765108 | D13: ='03_财务原始数据'!E13/'03_财务原始数据'!E5 -> 0.083096423 | E13: ='03_财务原始数据'!E14/'03_财务原始数据'!E5 -> 0.23515761 | F13: =('03_财务原始数据'!E14-IF('03_财务原始数据'!E34="",0,'03_财务原始数据'!E34))/'03_财务原始数据'!E5 -> 0.029736664 | G13: ='03_财务原始数据'!E15/'03_财务原始数据'!E5 -> 0.085310551 | H13: 剔除股份支付列 = (管理费用 − 股份支付费用) ÷ 营业收入，性质E·测算
A15: 图表数据区 3：主营业务收入产品构成（万元，性质A）
A16: 产品分类 | B16: 2023收入 | C16: 2024收入 | D16: 2025收入 | E16: 2025收入占比 | F16: 2023→2025增长倍数 | H16: 口径说明
A17: 四足机器人 | B17: ='04_业务结构原始数据'!B3 -> 11938.09 | C17: ='04_业务结构原始数据'!D3 -> 23054.37 | D17: ='04_业务结构原始数据'!F3 -> 69762.56 | E17: ='04_业务结构原始数据'!F3/'04_业务结构原始数据'!F7 -> 0.41621685 | F17: ='04_业务结构原始数据'!F3/'04_业务结构原始数据'!B3-1 -> 4.8436953 | H17: 性质A
A18: 人形机器人 | B18: ='04_业务结构原始数据'!B4 -> 296.71 | C18: ='04_业务结构原始数据'!D4 -> 10729.76 | D18: ='04_业务结构原始数据'!F4 -> 86783.19 | E18: ='04_业务结构原始数据'!F4/'04_业务结构原始数据'!F7 -> 0.5177652 | F18: ='04_业务结构原始数据'!F4/'04_业务结构原始数据'!B4-1 -> 291.48488 | H18: 性质A
A19: 机器人组件 | B19: ='04_业务结构原始数据'!B5 -> 2692.34 | C19: ='04_业务结构原始数据'!D5 -> 4453.82 | D19: ='04_业务结构原始数据'!F5 -> 10373.67 | E19: ='04_业务结构原始数据'!F5/'04_业务结构原始数据'!F7 -> 0.06189131 | F19: ='04_业务结构原始数据'!F5/'04_业务结构原始数据'!B5-1 -> 2.8530312 | H19: 性质A
A20: 其他 | B20: ='04_业务结构原始数据'!B6 -> 826.51 | C20: ='04_业务结构原始数据'!D6 -> 529.33 | D20: ='04_业务结构原始数据'!F6 -> 691.67 | E20: ='04_业务结构原始数据'!F6/'04_业务结构原始数据'!F7 -> 0.0041266363 | F20: ='04_业务结构原始数据'!F6/'04_业务结构原始数据'!B6-1 -> -0.16314382 | H20: 性质A
A22: 图表数据区 4：分产品毛利率趋势（性质E·测算，基于表4-1收入与表4-2成本）
A23: 产品分类 | B23: 2023毛利率 | C23: 2024毛利率 | D23: 2025毛利率 | E23: 三年变动(百分点) | H23: 口径说明
A24: 四足机器人 | B24: =('04_业务结构原始数据'!B3-'04_业务结构原始数据'!B11)/'04_业务结构原始数据'!B3 -> 0.43710677 | C24: =('04_业务结构原始数据'!D3-'04_业务结构原始数据'!D11)/'04_业务结构原始数据'!D3 -> 0.51646955 | D24: =('04_业务结构原始数据'!F3-'04_业务结构原始数据'!F11)/'04_业务结构原始数据'!F3 -> 0.56719765 | E24: =(('04_业务结构原始数据'!F3-'04_业务结构原始数据'!F11)/'04_业务结构原始数据'!F3-('04_业务结构原始数据'!B3-'04_业务结构原始数据'!B11)/'04_业务结构原始数据'!B3)*100 -> 13.009088 | H24: 机器人组件行可与招股书直接披露的48.76%/56.94%/59.36%互校
A25: 人形机器人 | B25: =('04_业务结构原始数据'!B4-'04_业务结构原始数据'!B12)/'04_业务结构原始数据'!B4 -> 0.87668093 | C25: =('04_业务结构原始数据'!D4-'04_业务结构原始数据'!D12)/'04_业务结构原始数据'!D4 -> 0.6925579 | D25: =('04_业务结构原始数据'!F4-'04_业务结构原始数据'!F12)/'04_业务结构原始数据'!F4 -> 0.63176521 | E25: =(('04_业务结构原始数据'!F4-'04_业务结构原始数据'!F12)/'04_业务结构原始数据'!F4-('04_业务结构原始数据'!B4-'04_业务结构原始数据'!B12)/'04_业务结构原始数据'!B4)*100 -> -24.491573 | H25: 机器人组件行可与招股书直接披露的48.76%/56.94%/59.36%互校
A26: 机器人组件 | B26: =('04_业务结构原始数据'!B5-'04_业务结构原始数据'!B13)/'04_业务结构原始数据'!B5 -> 0.48764272 | C26: =('04_业务结构原始数据'!D5-'04_业务结构原始数据'!D13)/'04_业务结构原始数据'!D5 -> 0.5693517 | D26: =('04_业务结构原始数据'!F5-'04_业务结构原始数据'!F13)/'04_业务结构原始数据'!F5 -> 0.59356139 | E26: =(('04_业务结构原始数据'!F5-'04_业务结构原始数据'!F13)/'04_业务结构原始数据'!F5-('04_业务结构原始数据'!B5-'04_业务结构原始数据'!B13)/'04_业务结构原始数据'!B5)*100 -> 10.591867 | H26: 机器人组件行可与招股书直接披露的48.76%/56.94%/59.36%互校
A28: 图表数据区 5：销售量与平均单价（销量为性质A；单价按“收入÷销量”测算，性质E）
A29: 报告期 | B29: 人形机器人销量(台) | C29: 人形机器人单价(万元/台) | D29: 四足机器人销量(台) | E29: 四足机器人单价(万元/台) | H29: 口径说明
A30: 2023年 | B30: ='04_业务结构原始数据'!C22 -> 5 | C30: ='04_业务结构原始数据'!C24/'04_业务结构原始数据'!C22 -> 59.342 | D30: ='04_业务结构原始数据'!C19 -> 3121 | E30: ='04_业务结构原始数据'!C21/'04_业务结构原始数据'!C19 -> 3.8250849 | H30: 销量为招股书披露的主营业务收入口径销量
A31: 2024年 | B31: ='04_业务结构原始数据'!D22 -> 412 | C31: ='04_业务结构原始数据'!D24/'04_业务结构原始数据'!D22 -> 26.043107 | D31: ='04_业务结构原始数据'!D19 -> 7136 | E31: ='04_业务结构原始数据'!D21/'04_业务结构原始数据'!D19 -> 3.2307133 | H31: 销量为招股书披露的主营业务收入口径销量
A32: 2025年 | B32: ='04_业务结构原始数据'!F22 -> 5215 | C32: ='04_业务结构原始数据'!F24/'04_业务结构原始数据'!F22 -> 16.641072 | D32: ='04_业务结构原始数据'!F19 -> 23037 | E32: ='04_业务结构原始数据'!F21/'04_业务结构原始数据'!F19 -> 3.0282832 | H32: 销量为招股书披露的主营业务收入口径销量
A33: 口径提醒：2025年人形机器人“销量”5,215台为主营业务收入口径（性质A）；招股说明书概览部分所称“出货量已超5,500台（全球第一）”为出货量口径，两者相差约300台，不可混用。本图表统一使用5,215台销量口径。
A35: 图表数据区 6：主营业务收入境内外结构（万元，性质A）
A36: 报告期 | B36: 境内销售 | C36: 境外销售 | D36: 境外占比 | H36: 口径说明
A37: 2023年 | B37: ='04_业务结构原始数据'!B29 -> 6989.41 | C37: ='04_业务结构原始数据'!B30 -> 8764.24 | D37: ='04_业务结构原始数据'!C30 -> 0.5563 | H37: 2025年境内占比首次超过境外（56.35% vs 43.65%）
A38: 2024年 | B38: ='04_业务结构原始数据'!D29 -> 17156.55 | C38: ='04_业务结构原始数据'!D30 -> 21610.74 | D38: ='04_业务结构原始数据'!E30 -> 0.5574 | H38: 2025年境内占比首次超过境外（56.35% vs 43.65%）
A39: 2025年 | B39: ='04_业务结构原始数据'!F29 -> 94445.56 | C39: ='04_业务结构原始数据'!F30 -> 73165.53 | D39: ='04_业务结构原始数据'!G30 -> 0.4365 | H39: 2025年境内占比首次超过境外（56.35% vs 43.65%）
A41: 图表数据区 6B：主营业务收入季度分布（万元，性质A）
A42: 季度 | B42: 2023收入 | C42: 2024收入 | D42: 2025收入 | E42: 2025占比 | H42: 口径说明
A43: 第一季度 | B43: ='04_业务结构原始数据'!B36 -> 3093.17 | C43: ='04_业务结构原始数据'!D36 -> 6510.98 | D43: ='04_业务结构原始数据'!F36 -> 24815.92 | E43: ='04_业务结构原始数据'!G36 -> 0.1481 | H43: 第四季度占比常年偏高，存在季节性
A44: 第二季度 | B44: ='04_业务结构原始数据'!B37 -> 4143.92 | C44: ='04_业务结构原始数据'!D37 -> 6707.3 | D44: ='04_业务结构原始数据'!F37 -> 52095.34 | E44: ='04_业务结构原始数据'!G37 -> 0.3108 | H44: 第四季度占比常年偏高，存在季节性
A45: 第三季度 | B45: ='04_业务结构原始数据'!B38 -> 3222.43 | C45: ='04_业务结构原始数据'!D38 -> 9765.44 | D45: ='04_业务结构原始数据'!F38 -> 38543.68 | E45: ='04_业务结构原始数据'!G38 -> 0.23 | H45: 第四季度占比常年偏高，存在季节性
A46: 第四季度 | B46: ='04_业务结构原始数据'!B39 -> 5294.13 | C46: ='04_业务结构原始数据'!D39 -> 15783.55 | D46: ='04_业务结构原始数据'!F39 -> 52156.15 | E46: ='04_业务结构原始数据'!G39 -> 0.3112 | H46: 第四季度占比常年偏高，存在季节性
A48: 图表数据区 7：研发投入（性质A）
A49: 报告期 | B49: 研发费用 | C49: 研发投入占营收比例 | D49: 研发费用同比 | H49: 口径说明
A50: 2023年度 | B50: ='03_财务原始数据'!C15 -> 4995.18 | C50: ='03_财务原始数据'!C54 -> 0.3139 | D50: — | H50: 研发费用绝对额持续上升，但费用率快速下降
A51: 2024年度 | B51: ='03_财务原始数据'!D15 -> 7001.7 | C51: ='03_财务原始数据'!D54 -> 0.1783 | D51: ='03_财务原始数据'!D15/'03_财务原始数据'!C15-1 -> 0.40169123 | H51: 研发费用绝对额持续上升，但费用率快速下降
A52: 2025年度 | B52: ='03_财务原始数据'!E15 -> 14496.56 | C52: ='03_财务原始数据'!E54 -> 0.0853 | D52: ='03_财务原始数据'!E15/'03_财务原始数据'!D15-1 -> 1.0704343 | H52: 研发费用绝对额持续上升，但费用率快速下降
A54: 图表数据区 8：同行业可比公司对标（营业收入万元 / 综合毛利率，性质A）
A55: 公司 | B55: 2023营收 | C55: 2024营收 | D55: 2025营收 | E55: 2023毛利率 | F55: 2024毛利率 | G55: 2025毛利率 | H55: 口径说明
A56: 优必选 | B56: ='05_客户与同业原始数据'!B25 -> 105569.8 | C56: ='05_客户与同业原始数据'!D25 -> 130536.1 | D56: ='05_客户与同业原始数据'!F25 -> 200099.9 | E56: ='05_客户与同业原始数据'!C25 -> 0.3153 | F56: ='05_客户与同业原始数据'!E25 -> 0.2865 | G56: ='05_客户与同业原始数据'!G25 -> 0.3767 | H56: 性质A（招股书同业对比表）
A57: 越疆 | B57: ='05_客户与同业原始数据'!B26 -> 28699.17 | C57: ='05_客户与同业原始数据'!D26 -> 37483.06 | D57: ='05_客户与同业原始数据'!F26 -> 49348.3 | E57: ='05_客户与同业原始数据'!C26 -> 0.4847 | F57: ='05_客户与同业原始数据'!E26 -> 0.4795 | G57: ='05_客户与同业原始数据'!G26 -> 0.4649 | H57: 性质A（招股书同业对比表）
A58: 云深处 | B58: ='05_客户与同业原始数据'!B27 -> 5011.26 | C58: ='05_客户与同业原始数据'!D27 -> 10320.1 | D58: ='05_客户与同业原始数据'!F27 -> 33749.06 | E58: ='05_客户与同业原始数据'!C27 -> 0.3348 | F58: ='05_客户与同业原始数据'!E27 -> 0.3876 | G58: ='05_客户与同业原始数据'!G27 -> 0.5283 | H58: 性质A（招股书同业对比表）
A59: 乐聚智能 | B59: ='05_客户与同业原始数据'!B28 -> 5398.83 | C59: ='05_客户与同业原始数据'!D28 -> 5550.03 | D59: ='05_客户与同业原始数据'!F28 -> 25818.79 | E59: ='05_客户与同业原始数据'!C28 -> 0.5045 | F59: ='05_客户与同业原始数据'!E28 -> 0.443 | G59: ='05_客户与同业原始数据'!G28 -> 0.4078 | H59: 性质A（招股书同业对比表）
A60: 可比公司平均值 | B60: ='05_客户与同业原始数据'!B29 -> 36169.77 | C60: ='05_客户与同业原始数据'!D29 -> 45972.32 | D60: ='05_客户与同业原始数据'!F29 -> 77254.01 | E60: ='05_客户与同业原始数据'!C29 -> 0.4098 | F60: ='05_客户与同业原始数据'!E29 -> 0.3992 | G60: ='05_客户与同业原始数据'!G29 -> 0.4444 | H60: 性质A（招股书同业对比表）
A61: 宇树科技 | B61: ='05_客户与同业原始数据'!B30 -> 15913.44 | C61: ='05_客户与同业原始数据'!D30 -> 39277.07 | D61: ='05_客户与同业原始数据'!F30 -> 169926.93 | E61: ='05_客户与同业原始数据'!C30 -> 0.4475 | F61: ='05_客户与同业原始数据'!E30 -> 0.5722 | G61: ='05_客户与同业原始数据'!G30 -> 0.6044 | H61: 性质A（招股书同业对比表）
A63: 图表数据区 9：上市后二级市场表现（2026-08-19 至 2026-08-28；行情来源S9，性质E）
A64: 交易日 | B64: 收盘价 | C64: 单日涨跌幅 | D64: 成交额(亿元) | E64: 换手率 | F64: 收盘市值(亿元) | H64: 口径说明
A65: ='02_发行上市原始数据'!A66 -> 2026-08-19 | B65: ='02_发行上市原始数据'!C66 -> 845 | C65: ='02_发行上市原始数据'!I66 -> 4.6034 | D65: ='02_发行上市原始数据'!G66/100000000 -> 231.59535 | E65: ='02_发行上市原始数据'!K66 -> 0.8528 | F65: ='02_发行上市原始数据'!C66*'02_发行上市原始数据'!B10/100000000 -> 3417.7237 | H65: 性质E（第三方行情，非公司披露）
A66: ='02_发行上市原始数据'!A67 -> 2026-08-20 | B66: ='02_发行上市原始数据'!C67 -> 687 | C66: ='02_发行上市原始数据'!I67 -> -0.187 | D66: ='02_发行上市原始数据'!G67/100000000 -> 90.718691 | E66: ='02_发行上市原始数据'!K67 -> 0.4198 | F66: ='02_发行上市原始数据'!C67*'02_发行上市原始数据'!B10/100000000 -> 2778.67 | H66: 性质E（第三方行情，非公司披露）
A67: ='02_发行上市原始数据'!A68 -> 2026-08-21 | B67: ='02_发行上市原始数据'!C68 -> 672.41 | C67: ='02_发行上市原始数据'!I68 -> -0.0212 | D67: ='02_发行上市原始数据'!G68/100000000 -> 51.38832 | E67: ='02_发行上市原始数据'!K68 -> 0.2528 | F67: ='02_发行上市原始数据'!C68*'02_发行上市原始数据'!B10/100000000 -> 2719.6587 | H67: 性质E（第三方行情，非公司披露）
A68: ='02_发行上市原始数据'!A69 -> 2026-08-24 | B68: ='02_发行上市原始数据'!C69 -> 603.08 | C68: ='02_发行上市原始数据'!I69 -> -0.1031 | D68: ='02_发行上市原始数据'!G69/100000000 -> 50.155499 | E68: ='02_发行上市原始数据'!K69 -> 0.2702 | F68: ='02_发行上市原始数据'!C69*'02_发行上市原始数据'!B10/100000000 -> 2439.2435 | H68: 性质E（第三方行情，非公司披露）
A69: ='02_发行上市原始数据'!A70 -> 2026-08-25 | B69: ='02_发行上市原始数据'!C70 -> 602.8 | C69: ='02_发行上市原始数据'!I70 -> -0.0005 | D69: ='02_发行上市原始数据'!G70/100000000 -> 32.447769 | E69: ='02_发行上市原始数据'!K70 -> 0.1769 | F69: ='02_发行上市原始数据'!C70*'02_发行上市原始数据'!B10/100000000 -> 2438.111 | H69: 性质E（第三方行情，非公司披露）
A70: ='02_发行上市原始数据'!A71 -> 2026-08-26 | B70: ='02_发行上市原始数据'!C71 -> 591.53 | C70: ='02_发行上市原始数据'!I71 -> -0.0187 | D70: ='02_发行上市原始数据'!G71/100000000 -> 33.248508 | E70: ='02_发行上市原始数据'!K71 -> 0.1856 | F70: ='02_发行上市原始数据'!C71*'02_发行上市原始数据'!B10/100000000 -> 2392.5279 | H70: 性质E（第三方行情，非公司披露）
A71: ='02_发行上市原始数据'!A72 -> 2026-08-27 | B71: ='02_发行上市原始数据'!C72 -> 615.03 | C71: ='02_发行上市原始数据'!I72 -> 0.0397 | D71: ='02_发行上市原始数据'!G72/100000000 -> 37.954479 | E71: ='02_发行上市原始数据'!K72 -> 0.2107 | F71: ='02_发行上市原始数据'!C72*'02_发行上市原始数据'!B10/100000000 -> 2487.577 | H71: 性质E（第三方行情，非公司披露）
A72: ='02_发行上市原始数据'!A73 -> 2026-08-28 | B72: ='02_发行上市原始数据'!C73 -> 585 | C72: ='02_发行上市原始数据'!I73 -> -0.0488 | D72: ='02_发行上市原始数据'!G73/100000000 -> 33.626082 | E72: ='02_发行上市原始数据'!K73 -> 0.1886 | F72: ='02_发行上市原始数据'!C73*'02_发行上市原始数据'!B10/100000000 -> 2366.1164 | H72: 性质E（第三方行情，非公司披露）
A73: 2026-08-29、08-30为周末非交易日；2026-08-31行情虽已产生，但超出本底稿资料截止日（2026-08-30），已排除。
A75: 图表数据区 10：2026年1-6月 管理层预计（性质D）与已实现（性质C）
A76: 项目 | B76: 预计下限(D) | C76: 预计上限(D) | D76: 已实现(C) | E76: 上年同期(A/C) | H76: 口径说明
A77: 营业收入 | B77: ='03_财务原始数据'!C112 -> 105200 | C77: ='03_财务原始数据'!D112 -> 112800 | D77: ='03_财务原始数据'!C88 -> 115224.56 | E77: ='03_财务原始数据'!D88 -> 77571.92 | H77: 预计数为性质D（管理层估计，不构成盈利预测或业绩承诺）；已实现数为性质C（未经审计）
A78: 归母净利润 | B78: ='03_财务原始数据'!C113 -> 25800 | C78: ='03_财务原始数据'!D113 -> 30600 | D78: ='03_财务原始数据'!C91 -> 27399.99 | E78: ='03_财务原始数据'!D91 -> -3202.45 | H78: 预计数为性质D（管理层估计，不构成盈利预测或业绩承诺）；已实现数为性质C（未经审计）
A79: 扣非归母净利润 | B79: ='03_财务原始数据'!C114 -> 23600 | C79: ='03_财务原始数据'!D114 -> 28300 | D79: ='03_财务原始数据'!C92 -> 24393.03 | E79: ='03_财务原始数据'!D92 -> 30243.35 | H79: 预计数为性质D（管理层估计，不构成盈利预测或业绩承诺）；已实现数为性质C（未经审计）
A80: 本区数据严禁用于表述“公司实现了盈利预测”。招股说明书原文载明预计数“不构成公司的盈利预测或业绩承诺”。
A83: ↓ 以下为图表区（共19张），数据全部取自上方公式区
A465: 图表清单（共19张）：图1 营收与增速｜图2 归母 vs 扣非净利｜图3 非经常性损益净额｜图4 经营现金流 vs 营收｜图5 毛利率与扣非净利率｜图6 费用率（含剔除股份支付）｜图7 产品构成堆积｜图8 分产品毛利率｜图9 人形机器人量价｜图10 四足机器人量价｜图11 境内外结构｜图12 季度分布｜图13 研发投入｜图14 同业营收｜图15 同业毛利率｜图16 收盘价走势｜图17 收盘市值｜图18 涨跌幅与换手率｜图19 预计 vs 实际。全部图表数据均来自本页上方公式区，未使用任何硬编码数值；若某张图表显示为空白，通常是因为 Excel 尚未完成公式重算（按 F9 或 Ctrl+Alt+F9 强制重算即可）。

Sheet 09_分析结论
A1: 分析结论（每条结论均附支撑数据、来源编号与数据性质，可逐条回溯至原始数据表）
A2: 阅读顺序建议：先看“结论（一句话）”，再看“支撑数据与计算依据”，最后核对“来源 / 数据性质”与“局限、反证与需跟踪事项”。凡性质标注含 D 的均为管理层预计，不得作为已实现事实引用；凡含 E 的为本底稿测算，须按局限列说明使用；凡含 C 的为未经审计数据，引用时必须注明。
A3: 编号 | B3: 结论（一句话） | C3: 支撑数据与计算依据 | D3: 来源 | E3: 数据性质 | F3: 局限、反证与需跟踪事项
A4: 一、总体判断
A5: C-01 | B5: 报告期内公司完成了从“四足机器人厂商”到“人形机器人主导”的业务结构跃迁，收入规模三年增长约9.7倍，这是本次分析中最强的事实性发现。 | C5: 营业收入15,913.44万元（2023）→39,277.07万元（2024）→169,926.93万元（2025），两年CAGR约226.78%（见表7-1）；人形机器人占主营业务收入比重由1.88%升至27.68%再升至51.78%，2025年首次超过四足机器人（41.62%）成为第一大产品线（见表4-1）。 | D5: S1 | E5: A | F5: 高增长建立在极低基数之上（2023年人形机器人仅销售5台、收入296.71万元），百分比增速对基数高度敏感，不宜线性外推。
A6: C-02 | B6: 公司账面利润与真实盈利能力之间存在系统性偏离，必须以扣非口径而非归母口径评估其盈利水平。 | C6: 2025年归母净利润27,821.05万元，而扣非归母净利润59,075.28万元，扣非后反而高出31,254.23万元（见表7-2）；差额来自2025年6月上海宇翼增资确认的股份支付费用34,906.55万元，全额计入管理费用、列为非经常性损益、无现金流出。剔除该项后2025年管理费用率由23.52%降至约2.97%（见表7-2）；2025年扣非加权ROE 28.70%，为扣非前13.52%的2.1倍。 | D6: S1 | E6: A + E | F6: 股份支付费用属一次性会计确认，不代表经营恶化。但由此产生的基数效应会使2026年“归母净利润同比”严重失真——2026H1归母净利润27,399.99万元 vs 上年同期−3,202.45万元，上市公告书已直接标注“不可比”（见表3-3）。分析中应以扣非口径为主轴。
A7: C-03 | B7: 2026年上半年收入继续高增长，但盈利与现金流两项指标同步走弱，构成本底稿识别出的最重要预警信号。 | C7: 2026H1营业总收入115,224.56万元（同比+48.54%），但扣非归母净利润24,393.03万元（−19.34%）、经营活动现金流净额23,154.53万元（−32.53%）、扣非加权ROE 8.90%（同比−12.12个百分点）（见表3-3、表7-1、表7-5）；2026Q1更为极端：营收+68.49%而扣非归母净利−52.55%、经营现金流−85.65%（见表3-2）。收入增而利润减的直接线索是单价持续下行（见表7-4）与研发费用同比增加8,203.74万元（H1口径）。 | D7: S1 / S2 | E7: B / C | F7: 2026H1数据未经审计（性质C），2026Q1仅经审阅（性质B），且公司已明示上市后不再单独披露2026年半年报，故无法通过后续定期报告验证。利润下滑的成因（价格下探、研发投入加大、销售费用前置、产品结构变化）在披露文件中未逐项量化，须以2026年年度报告核实。这是本底稿优先级最高的跟踪事项。
A8: 二、成长性与收入质量
A9: C-04 | B9: 收入增长几乎完全由销量驱动、并被单价下行部分抵消，属“以价换量”的扩张模式。 | C9: 2025年四足机器人销量贡献+51,371.57万元（占收入变动额109.98%）、单价拖累−4,663.39万元（−9.98%）；人形机器人销量贡献+125,085.09万元（164.47%）、单价拖累−49,031.66万元（−64.47%）（见表7-4，与招股书披露值一致）。人形机器人平均单价由59.34万元/台（2023）→26.04万元/台（2024）→16.64万元/台（2025），累计降幅71.96%。 | D9: S1 | E9: A + E | F9: 单价下降可能同时反映产品结构下沉（不同型号混合）与主动降价，招股书未拆分型号级单价，无法区分两种成因。若为主动降价，则毛利率可持续性存疑；若为结构下沉，则需关注高端产品的竞争力与品牌形象。
A10: C-05 | B10: 客户结构分散、无单一大客户依赖，收入集中度风险较低。 | C10: 报告期前五大客户合计占营业收入比例稳定在12.69%（2023）、12.45%（2024）、12.08%（2025）（见表5-1）；2025年第一大客户为境外客户N（欧洲），占比仅3.11%；招股说明书明确不存在向单个客户销售比例超过50%的情形，且与前五大客户均不存在关联关系。 | D10: S1 | E10: A | F10: 前五大客户中多家以“境外客户X（地区）”匿名披露，无法独立核实其真实身份、是否为经销商、以及最终销售是否实现；2025年新进入前五大名单的京东集团（4,887.32万元，2.88%）与北京朝元时代科技（3,070.69万元，1.81%）在2023、2024年名单中均未出现，属新增渠道，其持续性需跟踪。
A11: C-06 | B11: 收入存在明显的第四季度集中特征，季节性会放大单季数据的解读风险。 | C11: 第四季度主营业务收入占比：2023年33.61%、2024年40.71%、2025年31.12%（见表4-5）；招股说明书解释为新产品多在下半年陆续形成收入并于第四季度形成规模收入，且部分客户实行集中采购与预算管理。 | D11: S1 | E11: A | F11: 由于Q4占比偏高，将2026H1数据×2得到的年化值（230,449.12万元，见表7-9）会系统性低估全年，该测算值仅为机械结果，严禁作为全年业绩预测或估值输入使用。
A12: C-07 | B12: 2025年收入区域结构发生反转，境内首次超过境外。 | C12: 境内主营业务收入占比由44.37%（2023）、44.26%（2024）升至56.35%（2025），境外由55.63%降至43.65%（见表4-4）；招股说明书归因于2025年年初春晚演出提升全国品牌知名度，以及国内人工智能与机器人产业快速发展与政策支持带动科研教育、商业消费、行业应用客户采购需求。 | D12: S1 | E12: A | F12: 归因中包含“春晚演出”这一一次性营销事件，其需求拉动的可持续性无法从披露文件判断；境外收入占比下降也可能隐含出口管制、关税或地缘政治因素，招股说明书风险因素章节的相关表述需人工复核。
A13: C-08 | B13: 销售模式仍以线下为主，但线上（含电商入仓）已成为新的增量渠道。 | C13: 线下销售占比常年维持在86.86%→89.61%→89.28%；线上销售2025年为17,970.42万元（占10.72%），其中首次出现“电商入仓”模式4,885.16万元（占2.91%）；线下经销占比由35.59%升至38.18%（见表4-6）。 | D13: S1 | E13: A | F13: 经销收入占比上升意味着收入确认依赖经销商提货而非终端销售，存在渠道压货的可能性；招股说明书对经销商期末库存、退换货政策的披露需人工复核。
A14: 三、盈利能力与成本结构
A15: C-09 | B15: 综合毛利率三年持续提升且显著高于同业，但其提升主要来自产品结构变化，而非单一产品盈利能力的普遍改善。 | C15: 综合毛利率44.75%→57.22%→60.44%，2025年高出可比公司平均值（44.44%）16.00个百分点（见表7-10）。分产品测算：人形机器人毛利率87.67%→69.26%→63.18%（下行），四足机器人43.71%→51.65%→56.72%（上行），机器人组件48.76%→56.94%→59.36%（上行）（见表7-3）。整体上行主要由高毛利的人形机器人收入占比从1.88%升至51.78%所驱动。 | D15: S1 | E15: A + E | F15: 结构驱动型毛利率提升的可持续性取决于两点：人形机器人收入占比能否维持，以及其自身毛利率能否止住下滑。若人形机器人毛利率继续按每年约6个百分点的速度回落，即使收入占比不变，综合毛利率也将见顶。
A16: C-10 | B16: 成本结构中直接材料占比快速上升，公司盈利的敏感度正从“人工与制造费用”转向“上游物料价格”。 | C16: 主营业务成本中直接材料占比72.87%（2023）→72.93%（2024）→81.73%（2025），直接人工由13.97%降至8.08%，制造费用由13.16%降至10.20%（见表4-7）；招股说明书解释为规模效应、生产标准化与人员熟练度提升带来效率提高，以及材料成本占比较高的人形机器人收入占比由27.68%升至51.78%。 | D16: S1 | E16: A | F16: 人工与制造费用占比下降部分来自收入结构变化的分母效应，不完全是效率提升；直接材料占比升至81.73%后，核心零部件（电机、减速器、传感器、芯片）价格波动对毛利率的弹性显著放大，而招股书未披露主要原材料的采购集中度与价格锁定安排，需人工复核“主要供应商”章节。
A17: C-11 | B17: 2025年存货规模与跌价准备均处于需关注水平，与高速放量相匹配但也隐含跌价风险。 | C17: 2025年末存货账面余额39,232.70万元、跌价准备2,457.37万元、账面价值36,775.34万元（计提率约6.26%）；其中在产品15,887.54万元（占43.20%）、原材料11,695.51万元（占31.80%）、库存商品3,757.68万元（占10.22%）、发出商品3,678.85万元（占10.00%）（见表4-8附注与表7-5）。存货占流动资产约16.57%。 | D17: S1 | E17: A + E | F17: 2023、2024年存货数据未在本次提取范围内获得，无法计算存货增速与存货周转率的时序变化（见表10）；在产品占比高达43.20%，若下游需求或产品迭代节奏变化，跌价风险集中于该科目。另外发出商品3,678.85万元与“出货量>5,500台 vs 销量5,215台”的口径差异可能存在关联，值得核验。
A18: 四、现金流、资产结构与会计估计
A19: C-12 | B19: 2023—2025年经营现金流质量优秀，但2026年上半年出现收入与现金流的明显背离。 | C19: 经营活动现金流净额494.25万元（2023）→19,239.13万元（2024）→66,998.18万元（2025），占营业收入比例分别为3.11%、48.98%、39.43%（见表7-5）；2025年经营现金流÷归母净利润约2.41倍，÷扣非归母净利润约1.13倍，两者差额正是股份支付费用“减利不出现金”的结果。但2026Q1经营现金流净额仅3,439.96万元（−85.65%），2026H1为23,154.53万元（−32.53%），同期收入分别+68.49%、+48.54%。 | D19: S1 / S2 | E19: A / B / C | F19: 现金流背离的可能原因（预付款项增加、存货备货、应收账期放宽、税费缴纳节奏）在披露文件中未量化说明；2026H1流动资产较上年末+30.13%、流动负债+55.57%、负债总额+59.88%、资产负债率由18.82%升至25.11%，显示营运资金占用明显加大，需在2026年年报中核实。
A20: C-13 | B20: 应收账款坏账计提比例连续三年显著低于同业平均，是本底稿识别出的最重要的会计估计差异点。 | C20: 公司计提比例6.13%（2023）、6.55%（2024）、5.13%（2025），同业平均12.19%、13.81%、14.07%（见表5-3），2025年低8.94个百分点；同业中优必选高达29.29%。招股说明书解释为公司应收账款账龄相对较短、周转率相对较快、回款情况良好。2025年末应收账款前五名合计1,769.78万元（占余额28.59%），账龄全部为1年以内（见表5-4）。 | D20: S1 | E20: A | F20: 该解释与2026年上半年经营现金流大幅下降（C-12）之间存在需要解释的张力：若回款确实良好，现金流为何与收入增速背离？此外，招股说明书未在本次提取范围内直接披露各期末应收账款账面余额，由前五大占比28.59%反推的2025年末余额约6,196万元属测算值（性质E），敏感性分析（若按同业14.07%计提将减少多少利润）必须在余额核实后才能给出。
A21: C-14 | B21: 资产结构轻、杠杆低，上市后资产负债率上升主要源于经营性负债而非有息债务。 | C21: 资产负债率（合并）23.57%（2023）→16.19%（2024）→18.82%（2025）→25.11%（2026H1）（见表3-1、表3-3）；2025年末流动资产占总资产约69.18%；财务费用2023、2024年为负（利息收入大于支出），2025年仅98.61万元，表明几乎不存在有息负债（见表7-2、表7-5）。 | D21: S1 / S2 | E21: A / C | F21: 招股说明书未在本次提取范围内提供负债构成明细（应付账款、合同负债、应付职工薪酬、应交税费的分项），因此“负债上升源于经营性负债”属于基于财务费用极小这一间接证据的推断，需以财务报表附注核实（见表10）。
A22: 五、研发投入与科创属性
A23: C-15 | B23: 四项科创属性指标全部达标，但研发强度（研发费用率）随收入放大而快速稀释。 | C23: ①最近三年累计研发费用26,493.44万元 > 8,000万元门槛；②研发人员184人占员工总数516人的35.66% > 10%门槛；③截至2026年1月31日拥有境内发明专利20项（境内外注册专利合计262项）；④最近三年营业收入CAGR 226.78%（见表3-1、表7-6）。但研发费用率由31.39%（2023）→17.83%（2024）→8.53%（2025），研发费用÷扣非归母净利润由2024年约89.22%降至2025年约24.54%。 | D23: S1 | E23: A + E | F23: 研发费用率下降是分母（收入）高速扩张的结果，绝对额仍在增长（4,995.18万→7,001.70万→14,496.56万元）。但募投项目中研发类合计357,759.73万元（占85.15%），其中“智能机器人模型研发项目”单项202,245.93万元，相当于2025年全年研发费用的14倍、三年累计研发费用的7.6倍，公司能否有效消化这一投入强度并转化为技术领先性，是无法从历史数据判断的前瞻性问题。
A24: C-16 | B24: 人均研发投入水平较高，研发人员结构支撑“全栈自研”的商业模式主张。 | C24: 2025年人均研发费用约78.79万元/人（研发费用14,496.56万元 ÷ 研发人员184人，见表7-6）；研发人员占员工总数35.66%；招股说明书将其毛利率高于同业归因于“全栈自研自产降低硬件成本、规模效应及产品构成差异”。 | D24: S1 | E24: A + E | F24: “研发人员”的认定口径（是否包含生产端工艺人员）未在提取范围内核实；“全栈自研自产”与直接材料占成本81.73%（C-10）之间的关系需进一步理解——自研并不等于自制，核心零部件外购比例需核验。
A25: 六、发行定价、募集资金与估值
A26: C-17 | B26: 本次发行定价显著高于行业与可比公司参照水平，且存在大额超募。 | C26: 按公告书孰低口径，发行市盈率219.23倍，为所属行业（C34通用设备制造业）最近一个月平均静态市盈率38.56倍的约5.69倍；发行市销率35.89倍，较可比公司（优必选、越疆）2025年静态市销率算术平均19.74倍溢价约82%（见表7-7、表7-10）。募集资金净额591,714.92万元较募投项目计划投入420,171.12万元超募约171,543.80万元（40.83%），超募规模与2025年全年营业收入（169,926.93万元）相当（约1.01倍）。 | D26: S1 / S2 | E26: A + E | F26: 招股说明书以“可比上市公司均未盈利”为由选择市销率而非市盈率作为对比指标，这一方法论选择本身降低了对盈利质量的定价约束，需独立判断；公司自身在扣非口径下已实现盈利（2025年扣非归母净利59,075.28万元），因此“可比公司均未盈利”的表述并不能完全豁免市盈率对比。超募资金的具体使用安排在两份文件中均未项目化，属上市后治理跟踪事项。
A27: C-18 | B27: 发行估值倍数在四种口径下差异极大（92.92倍至219.23倍），引用时必须指明口径。 | C27: 四个披露口径分别为：①扣非后÷发行前总股本 92.92倍；②扣非前÷发行前总股本 197.31倍；③扣非后÷发行后总股本 103.25倍；④扣非前÷发行后总股本 219.23倍（见表7-7，四者均已复算一致）。口径①与④相差2.36倍，全部差异来自“扣非前后”与“发行前后股本”两个维度的组合。 | D27: S2 / S3 | E27: A + E | F27: 本底稿四个倍数均复算通过，但媒体与研究报告常混用口径，对外引用时应以公告书正式口径④（219.23倍）为准并注明。
A28: C-19 | B28: 战略配售结构显示长期资本与产业资本深度参与，员工持股比例较高。 | C28: 最终战略配售8,089,286股，占本次发行数量20.00%，获配金额合计1,219,864,328.80元（见表6-2）；其中员工1号资管计划1,356,100股（159名核心员工）+ 员工2号资管计划444,297股（12名高管及核心员工），合计1,800,397股，占本次发行约4.45%、获配金额约2.71亿元；杭州深度求索获配933,399股、限售期36个月（战配中最长）；全国社保基金理事会三个组合合计获配933,402股；保荐人跟投（中证投资）808,928股、限售24个月（见表7-11）。 | D28: S2 | E28: A + E | F28: 战略配售投资者的实际缴款、限售起止日与后续减持安排需以上市公告书原文及后续公告核验；限售期届满时点（2027年8月、2028年8月、2029年8月三批）构成可预期的流通盘扩容事件，应纳入跟踪日历。
A29: C-20 | B29: 特别表决权安排使实际控制人在发行后仍掌握绝对表决权，公众股东制衡能力有限。 | C29: 特别表决权安排设置于2025年5月16日；王兴兴发行前直接持股23.8216%但对应表决权63.5457%，合计控制表决权68.7816%；发行后直接持股降至21.4395%，合计控制表决权65.3090%（见表6-1、表7-11）；公司适用《科创板股票上市规则》第2.1.4条第（一）款“预计市值不低于人民币100亿元”标准上市。 | D29: S1 | E29: A | F29: 特别表决权的具体倍数、适用范围（是否及于重大事项）、以及日落条款需以公司章程原文核验；证券简称是否带“-W”标识需以交易所正式公布的简称为准。
A30: 七、二级市场表现（性质E，第三方行情）
A31: C-21 | B31: 上市后股价经历了“首日暴涨—快速回落—低位震荡”的完整过程，截至资料截止日仍较发行价上涨约2.88倍。 | C31: 上市首日（2026-08-19）开盘即最高1,100.00元、收盘845.00元（较发行价150.80元上涨460.34%），盘中最高对应市值约4,449.11亿元、收盘市值约3,417.72亿元；此后连续回落，至2026-08-28收盘585.00元，较首日收盘下跌30.77%、较盘中最高下跌46.82%，但仍较发行价上涨287.93%，对应市值约2,366.12亿元（见表2-2、表7-9）。8个交易日累计成交额约561亿元，日均换手率约31.84%。 | D31: S9 / S2 | E31: E | F31: 行情数据来自第三方接口，非公司或交易所的法定披露内容；样本仅8个交易日，任何关于“估值回归”“破发风险”的判断都不具备统计意义。
A32: C-22 | B32: 以资料截止日前最后收盘价计，公司二级市场估值已远超发行定价与同业参照水平。 | C32: 按2026-08-28收盘价585.00元计算：静态市销率约139.2倍（发行市销率35.89倍，可比公司均值19.74倍）；静态市盈率约850倍（按2025年归母净利）或约401倍（按2025年扣非归母净利），行业平均静态市盈率为38.56倍（见表7-7、表7-9、表7-10）。若以2026H1营收简单年化（230,449.12万元）测算，动态市销率约103倍。 | D32: S9 / S1 / S2 | E32: A + C + E | F32: 动态市销率依赖“上半年×2”的机械年化，未调整Q4占比偏高的季节性（C-06），敏感性极高，仅供内部参考；严禁将其表述为对公司2026年全年业绩的预测。市值与倍数测算必须标注行情时点（2026-08-28收盘）。
A33: 八、同业竞争地位
A34: C-23 | B34: 在四家可比公司中，公司2025年营收排名第二、毛利率与成长性均排名第一。 | C34: 2025年营业收入：优必选200,099.90万元 > 宇树169,926.93万元 > 越疆49,348.30万元 > 云深处33,749.06万元 > 乐聚智能25,818.79万元；宇树为可比公司平均值（77,254.01万元）的2.20倍。综合毛利率：宇树60.44% > 云深处52.83% > 越疆46.49% > 乐聚智能40.78% > 优必选37.67%（平均44.44%）。2023→2025营收CAGR：宇树约226.78% > 云深处约159.51% > 乐聚智能约118.68% > 优必选约37.67% > 越疆约31.13%（见表7-10）。 | D34: S1 | E34: A + E | F34: 可比公司业务结构差异大（越疆以协作机器人为主、云深处以四足及轮足为主、优必选含教育与物流消费类业务），直接对比毛利率的口径一致性有限；优必选、越疆为港股上市公司，其财务数据按招股说明书采用的汇率折算，折算口径需核验（招股书载明按2026-08-05中间价1港元=0.86562人民币）。
A35: C-24 | B35: 人形机器人收入占比51.78%，公司在该细分赛道的商业化进度领先于已披露的可比公司。 | C35: 2025年宇树人形机器人主营业务收入86,783.19万元，占主营业务收入51.78%、销量5,215台；优必选人形机器人收入占比由上年2.7%升至41.1%；越疆、云深处人形机器人收入占比均未超过5%；乐聚智能2025年全尺寸人形机器人成为主要收入来源（未披露具体比例）（见表4-1、表5-2）。 | D35: S1 | E35: A | F35: 招股说明书概览部分称2025年人形机器人“出货量已超5,500台（纯人形，不含轮式双臂机器人），出货量全球第一”，该“全球第一”为出货量口径且未见独立第三方数据支持，引用时必须同时注明口径与出处；财务口径销量为5,215台，两者相差约300台，不可混用（见表10）。
A36: 九、必须避免的表述错误（事实与预测的边界）
A37: C-25 | B37: 招股说明书披露的2026年1-6月“预计数”是管理层估计，不是已实现业绩，任何场合不得表述为事实。 | C37: 预计区间：营业收入105,200–112,800万元、归母净利润25,800–30,600万元、扣非归母净利润23,600–28,300万元（见表3-4，性质D）。上市公告书披露的实际数：营业总收入115,224.56万元、归母净利润27,399.99万元、扣非归母净利润24,393.03万元（见表3-3，性质C）。对比结果（见表7-8）：实际营收超出预计上限约2.15%（超出区间）；实际归母净利润与扣非归母净利润均落在预计区间内。 | D37: S1 / S2 | E37: D vs C | F37: 招股说明书原文：“上述2026年1-6月财务数据预计为管理层对经营状况的合理估计，不代表公司最终实现的营业收入及净利润，相关数据未经会计师审计或审阅，不构成公司的盈利预测或业绩承诺。”禁止表述：“公司完成了盈利预测”“业绩超预期兑现”“预计营收11.28亿元”（后者在已有实际数时属于误用旧口径）。
A38: C-26 | B38: 2026年上半年数据虽为实际发生数，但未经审计，且不会有后续的半年报可供验证。 | C38: 上市公告书载明2026年1-6月主要财务数据未经审计，并明示公司本次发行上市后不再另行披露2026年半年度报告（见表3-3）。同期2026年1-3月数据经容诚会计师事务所审阅（容诚阅字[2026]230Z0038号，性质B）。 | D38: S1 / S2 | E38: B / C | F38: 所有基于2026H1数据的比率、增速、年化测算，引用时必须标注“未经审计”；下一可验证的经审计数据节点为2026年年度报告（预计2027年披露），在此之前的任何2026年全年判断均属推测。
A39: C-27 | B39: 本底稿的资料截止日为2026-08-30，此后发生的事项一律未纳入，不构成遗漏。 | C39: 已排除的事项包括：2026-08-31及之后的全部行情数据；2026-09-03披露的公司章程、变更注册资本公告等文件（见表2-2附注、表7-9附注）。纳入的最后交易日为2026-08-28（08-29、08-30为周末）。 | D39: — | E39: — | F39: 如需更新，应以2026-08-30为界重新执行取数，并同步更新表7-9的行情测算与表9结论C-21、C-22。

Sheet 10_待人工核验
A1: 待人工核验事项清单（共18项，按优先级排序）
A2: 本清单列出所有因取数渠道限制、口径歧义、数据缺失或性质为测算/预测而必须经人工复核后方可对外使用的事项。“优先级”分为：高＝影响核心结论或涉及事实与预测的边界；中＝影响比率精度或可比性；低＝表述规范与格式类。“对应底稿位置”可直接定位到需要修订的表与行。
A3: 编号 | B3: 待核验事项 | C3: 类型 | D3: 当前底稿的处理方式 | E3: 为何需要人工核验 | F3: 建议核验动作（含具体文件与章节） | G3: 优先级
A4: V-01 | B4: 两份核心 PDF 并非直接取自上海证券交易所官网 | C4: 来源权威性 | D4: 招股说明书（382页，2026-08-14披露）与上市公告书（90页，2026-08-18披露）的 PDF 文件取自东方财富信息披露镜像（pdf.dfcfw.com，art_code 分别为 AN202608131827947910、AN202608171828062024）。全部财务与业务数据均逐字提取自这两份 PDF 原文表格，未使用任何二手财经媒体的转述数据。尝试通过上交所官方公告接口（query.sse.com.cn，productId=688836）获取时返回 total:0、result:[]，未能取得官方托管副本。 | E4: 虽然镜像文件与上交所披露内容通常一致，但镜像存在版本滞后、页面缺漏或被替换的理论风险；本底稿的一切结论都建立在这两份文件之上，属单点依赖。 | F4: 在 www.sse.com.cn「披露」→「上市公司信息」→「科创板的股票」中检索证券代码688836，下载《首次公开发行股票并在科创板上市招股说明书》与《首次公开发行股票科创板上市公告书》官方 PDF，与本底稿所用文件做逐页比对（重点核对表3-1、表3-2、表3-3、表3-4、发行结果与募投项目页），并核对文件 MD5。 | G4: 高
A5: V-02 | B5: 2026年上半年数据未经审计，且不会有后续半年报验证 | C5: 数据性质 | D5: 表3-3全部行标注性质C，表7-1、表7-2、表7-5、表7-8中涉及2026H1的列均标注“C”，并在附注中说明公司不再单独披露2026年半年报。 | E5: 上市公告书披露的2026年1-6月营业总收入115,224.56万元、归母净利润27,399.99万元、扣非归母净利润24,393.03万元、经营现金流净额23,154.53万元均为未经审计数。结论C-03、C-12（收入与利润/现金流背离）完全建立在这些数据之上。 | F5: ①核对上市公告书原文表格数字与本底稿表3-3是否逐字一致；②确认公告书中“不再另行披露2026年半年度报告”的表述原文；③将2026H1未审数据列入跟踪日历，以2026年年度报告（预计2027年披露）为唯一验证节点。 | G5: 高
A6: V-03 | B6: 招股说明书中的2026年1-6月“预计数”属性质D，存在被误引为事实的风险 | C6: 事实/预测边界 | D6: 表3-4整表以橙色底纹标示，标题直接写明“【预测数据·非事实】”，并逐字附上招股说明书“不构成公司的盈利预测或业绩承诺”的原文；表7-8将预计与实际分列对比；结论C-25单列禁止表述清单。 | E6: 预计营业收入105,200–112,800万元与实际115,224.56万元并不相同，实际已超出预计上限。若引用时未区分，将同时构成“把预测当事实”与“用过时的预计数覆盖已知实际数”两类错误。 | F6: ①核对招股说明书“重大事项提示”或“财务报告审计截止日后主要经营状况”章节中该预计表的原文与警示语；②对外材料中一律使用表3-3的实际数（性质C），并在脚注说明其未经审计；③检查是否有任何下游文档仍引用105,200–112,800万元区间。 | G6: 高
A7: V-04 | B7: 人形机器人“出货量超5,500台（全球第一）”与“销量5,215台”的口径差异 | C7: 口径歧义 | D7: 表4-3附注已用橙色标出两个口径，明确“引用全球第一表述时必须使用出货量口径并注明，进行收入测算时必须使用5,215台销量口径”；结论C-24、图表数据区5均使用5,215台；表7-4量价拆解亦基于5,215台。 | E7: 两者相差约300台（约5.5%）。招股说明书概览部分以出货量口径主张“出货量全球第一”，而主营业务收入口径的销量为5,215台。差额可能来自发出商品、样机、试用机或期后确认收入。值得注意的是2025年末发出商品账面价值恰为3,678.85万元，按2025年人形机器人平均单价16.64万元/台测算约相当于221台，与300台的差额方向一致但不足以完全解释。 | F7: ①核对招股说明书“第二节 概览”与“第六节 财务会计信息”中两处表述的原文；②查阅财务报表附注“营业收入—主营业务收入”明细与“存货—发出商品”明细，确认差额的具体构成；③核实“全球第一”是否有第三方研究机构（如IFR、CIER、行业白皮书）数据支持，若无则引用时必须标注为公司自述。 | G7: 高
A8: V-05 | B8: 2025年末应收账款账面余额为反推测算值，未经原文确认 | C8: 数据缺失/测算 | D8: 表5-4附注与表7-5均已用橙色标明：由前五大应收账款合计1,769.78万元占比28.59%反推余额约6,196万元，标注为性质E·测算；表7-5“应收账款周转率”一行留空并注明“数据缺失，暂不计算”。 | E8: 应收账款余额是计算周转率、以及评估“坏账计提比例低于同业”（结论C-13）影响程度的必要输入。若实际余额显著高于6,196万元，则按同业平均14.07%计提的利润影响将同步放大。 | F8: 在招股说明书“第六节 财务会计信息与管理层分析”中定位“应收账款”小节，取得2023、2024、2025年各期末应收账款账面余额、账龄结构表与坏账准备明细，回填表7-5并补算周转率与敏感性。 | G8: 高
A9: V-06 | B9: 坏账计提比例显著低于同业，缺乏可独立验证的解释 | C9: 会计估计判断 | D9: 表5-3完整录入公司与四家可比公司三年计提比例，表7-5计算了差额（2025年低8.94个百分点），结论C-13将其列为最重要的会计估计差异点，并指出其与经营现金流背离之间的张力。 | E9: 公司2025年计提比例5.13%，而优必选为29.29%、越疆11.09%、云深处9.70%、乐聚智能6.20%，平均14.07%。招股说明书的解释（账龄较短、周转较快、回款良好）为定性表述，未提供账龄分布数据支撑。同时2026H1经营现金流同比−32.53%与“回款良好”的表述需要调和。 | F9: ①取得招股说明书中应收账款账龄分布表与迁徙率/损失率测算表；②核对2026H1应收账款与合同资产的变动（若有）；③以确认后的余额测算“按同业平均计提”对2025年利润总额的敏感性影响，补入表7-5。 | G9: 高
A10: V-07 | B10: 2023、2024年存货数据及2024年末应收账款余额未提取 | C10: 数据缺失 | D10: 表3-1中2023、2024年“存货（账面价值）”行留空（仅2025年有值36,775.34万元）；表7-5存货周转率一行标注“数据缺失”，仅给出2025年以期末存货近似的非标准口径值。 | E10: 缺失期初数导致存货周转率、存货增速、以及存货占收入比例等营运能力指标无法进行时序分析；而存货恰恰是高速放量企业最需要跟踪的科目（结论C-11）。 | F10: 在招股说明书财务报表附注中取得2023-12-31、2024-12-31的存货明细表（原材料/在产品/库存商品/发出商品/跌价准备），回填表3-1并将表7-5存货周转率改为标准平均余额口径。 | G10: 中
A11: V-08 | B11: 负债构成明细缺失，“负债上升源于经营性负债”属间接推断 | C11: 数据缺失/推断 | D11: 结论C-14已在“局限”列明确标注该判断基于“财务费用极小（2025年仅98.61万元）”这一间接证据，并注明需以财务报表附注核实。 | E11: 2026H1负债总额较上年末+59.88%、流动负债+55.57%、资产负债率由18.82%升至25.11%，但披露摘要未提供应付账款、合同负债、应付职工薪酬、应交税费、短期借款的分项数据。若其中包含有息负债或大额关联方借款，结论需要修正。 | F11: 查阅招股说明书合并资产负债表全部科目、以及上市公告书2026年6月30日资产负债表（若有），取得负债分项；重点确认是否存在短期借款、长期借款、应付债券。 | G11: 中
A12: V-09 | B12: 网下配售10%限售6个月的推断未以上市公告书股本结构表原文验证 | C12: 口径推断 | D12: 表7-9以公式测算上市首日无限售条件流通股约30,092,133股，并用首日成交量反算换手率约85.26%，与披露的85.28%基本吻合（差0.02个百分点），以此作为推断的反向验证；该行同时标注“需以《上市公告书》股本结构表原文核验”。 | E12: 该推断影响首日换手率、流通市值、以及后续解禁节奏的判断。虽然换手率校验高度吻合，但仍属间接验证而非直接披露。 | F12: 在上市公告书中定位“本次发行前后的股本结构”或“无限售条件流通股数量”表，直接取得2026-08-19上市首日无限售条件流通股数量与网下限售股数量，回填表7-9并将性质由E改为A。 | G12: 中
A13: V-10 | B13: 行情数据来自第三方接口，非法定披露内容 | C13: 来源权威性 | D13: 表2-2与表7-9全部行情行标注性质E、来源S9，附注明确“不属于发行人或上海证券交易所的法定信息披露内容”；结论C-21、C-22亦标注来源为S9。 | E13: 首日收盘价845.00元、盘中最高1,100.00元、2026-08-28收盘价585.00元、成交量与成交额、换手率均来自第三方行情接口。基于这些价格测算的市值（3,417.72亿/4,449.11亿/2,366.12亿元）与静态市盈率、市销率全部为衍生结果。 | F13: 以上海证券交易所官网或 Wind/Choice 终端的688836日线数据逐日核对2026-08-19至2026-08-28的开高低收、成交量、成交额、换手率；核对是否涉及除权除息调整（上市初期通常无）。 | G13: 中
A14: V-11 | B14: 2026年1-3月与1-6月研发费用仅披露同比增额，未披露绝对值 | C14: 数据缺失 | D14: 表3-2、表3-3分别录入“研发费用同比增加额3,832.80万元”“8,203.74万元”，表7-1与表7-6在2026Q1/H1列注明“仅披露同比增额”，未反推绝对值，也未据此计算研发费用率。 | E14: 研发投入是判断结论C-03（收入增而利润减）成因的关键变量之一。若按增额反推，2026H1研发费用约在1.5亿元量级，但这属于推算而非披露，本底稿刻意不做。 | F14: 核对招股说明书“财务报告审计截止日后主要财务信息”与上市公告书相关段落原文，确认是否在其他位置（如管理层讨论、研发费用明细表）披露了2026年1-6月研发费用绝对值。 | G14: 中
... A21: V-18 | B21: 证券简称、特别表决权标识（“-W”）与上市初期涨跌幅限制等交易安排未逐项核对 | C21: 表述规范 | D21: 封面与表2-1均以“宇树科技股份有限公司（688836.SH）”表述，未使用证券简称；结论C-20的“局限”列注明证券简称是否带“-W”标识需以交易所正式公布为准。 | E21: 存在特别表决权安排的公司，其证券简称通常带有特殊标识；科创板新股上市初期（前5个交易日）无涨跌幅限制、之后为20%。这些交易安排虽不影响财务分析，但影响对外材料的表述准确性。 | F21: 以上海证券交易所官网688836的证券简称为准核对；同时核对上市公告书中关于上市初期交易安排的提示性条款。 | G21: 低
A23: 核验完成后的更新流程：①将修订后的原始数据填入 02–06 表对应单元格；②07_核心计算与08_趋势图表全部由公式驱动，会自动重算与重绘，无需手工修改；③回到本页将对应编号的“优先级”改为“已核验”，并在“当前底稿的处理方式”列追加核验日期与核验人；④若核验结果改变了某条结论，请同步修订 09_分析结论 对应编号，不要另建新行，以保持编号可追溯。
A25: 本底稿未包含（因资料截止日限制或披露文件未提供）的内容清单
A26: ①完整的合并资产负债表、利润表、现金流量表与所有者权益变动表（仅提取了招股说明书“主要财务数据”摘要表所列项目）
A27: ②财务报表附注全部明细（应收账款账龄、存货分项期初数、负债构成、股份支付公允价值假设、政府补助明细、税收优惠明细）
A28: ③2026年7月1日至2026年8月30日期间发生的经营事项（披露文件中无此期间的财务数据）
A29: ④2026年8月31日及之后的全部行情与公告（含2026-09-03的公司章程、变更注册资本公告），已按资料截止日主动排除
A30: ⑤宇树科技官方网站、产品发布会、媒体报道等非披露类信息（未纳入取数范围，见 V-12）
A31: ⑥任何前瞻性盈利预测、估值目标或投资建议——本底稿不提供，亦不应由本底稿数据推导后对外表述为公司业绩预期
A32: ⑦分产品型号的单价与毛利拆分（招股说明书仅披露四足/人形两大类的合并单价）
A33: ⑧在手订单、合同负债、产能利用率等前瞻性经营指标（披露摘要未提供）
A35: 最后声明：本底稿为基于公开披露文件的信息整理与财务分析工作底稿，不构成任何证券投资建议、评级或估值结论。所有测算值（性质E）与未经审计值（性质B/C）在使用前请按本清单完成人工核验。
