Workbook

Sheet 00_封面与口径
B1: 宇树科技股份有限公司(688836.SH) 经营与财务表现分析底稿
B2: 资料截止日 | C2: 2026-08-30（该日之后发生的二级市场数据不纳入本底稿）
B3: 生成日期 | C3: 2026-09-04
B4: 分析对象 | C4: 宇树科技股份有限公司，高性能通用人形/四足机器人、机器人组件及具身智能模型研发、生产、销售；2026-08-19 上交所科创板上市
B6: 一、工作簿结构
B7: 01_资料来源 | C7: 引用文件清单、披露主体、日期、链接与对应数据范围（来源编号 S1~S10）
B8: 02_原始数据_年度 | C8: 2023A/2024A/2025A 经审计年度原始数据（注册稿口径），逐行标注来源编号
B9: 03_原始数据_期间 | C9: 2025 分季度/2026Q1/2026H1 实际数；2026H1 业绩预告（预测，单独标识）
B10: 04_业务经营数据 | C10: 分产品收入/销量/单价、分地区收入、应用场景、人员、出货地位
B11: 05_核心计算 | C11: 同比、CAGR、利润率、费用率、现金流质量等，全部以 Excel 公式跨表引用，可联动重算
B12: 06_IPO与募投 | C12: 发行方案、估值历程、原拟募投项目、产能规划（规划≠已实现）
B13: 07_趋势图表 | C13: 6 张原生 Excel 图表（数据源以公式链接原始表，可编辑、随数据更新）
B14: 08_分析结论 | C14: 分主题结论及对应数据支撑位置
B15: 09_待人工核验 | C15: 需人工以招股书原文/年报进一步核验的事项清单
B16: 二、统一口径
B17: 货币与单位 | C17: 除特别注明外，金额单位均为人民币【万元】；股数为【万股】；单价为【万元/台】；人数为【人】
B18: 报告期口径 | C18: 年度=自然年(2023/2024/2025，经审计)；Q1=一季度、H1=上半年、1-9M=前三季度；2023→2025 的 CAGR 按 2 年计算
B19: 已实现 vs 预测 | C19: 列标题后缀 A=Actual 已实现(经审计/经审阅/上市公告书披露)；E=Estimate 预测。2026H1 业绩预告区间为公司 2026-05 披露的【预测数】，已在 03 表单独列示，不得当作已实现事实；实际数取自 2026-08-17 上市公告书
B20: 口径差异提示 | C20: 招股书申报稿(2026-03-20) 与注册稿(2026-06-02) 对 2025 年数据有修订，本底稿一律采用注册稿/上市保荐书最终数；差异在备注列说明
B21: 主营 vs 营业收入 | C21: 主营业务收入不含其他业务；占比分产品/分地区结构均以主营业务收入为分母，营业收入口径占比另注
B22: 颜色约定 | C22: 黑色=本表数据；绿色=跨工作表公式引用；浅黄底=待人工核验/约数或反推数；灰色斜体=注释与来源
B23: 三、重要声明 | C23: 本底稿为分析工作稿，不构成投资建议；数据以上交所披露文件原文为准，转引数据已标注；预测不代表实际结果。

Sheet 01_资料来源
B1: 资料来源清单（优先级：上交所披露 > 公司官方 > 券商/媒体转引）
B3: 编号 | C3: 文件/资料名称 | D3: 披露主体 | E3: 类型 | F3: 日期 | G3: 链接 / 出处 | H3: 用于数据
B4: S1 | C4: 招股说明书（注册稿），项目编号 auditId=2178（申报稿2026-03-20/上会稿2026-05-25/注册稿2026-06-02） | D4: 上海证券交易所/发行人 | E4: 一手·交易所 | F4: 2026-06-02 | G4: https://star.sse.com.cn/listing/renewal/ipo/index_listing_detail.shtml?auditId=2178 | H4: 年度三表、产品/地区/销量/费用/募投的最终口径
B5: S2 | C5: 《上市保荐书》（注册稿）002178_20260602_VI1W.pdf | D5: 中信证券/上交所 | E5: 一手·交易所 | F5: 2026-06-02 | G5: http://static.sse.com.cn/stock/disclosure/announcement/c/202606/002178_20260602_VI1W.pdf | H5: 主要财务数据及指标表、研发费用、科创属性、劳务外包、市值标准
B6: S3 | C6: 《审核中心意见落实函的回复》002178_20260525_V4H0.pdf | D6: 发行人/上交所 | E6: 一手·交易所 | F6: 2026-05-25 | G6: http://static.sse.com.cn/stock/disclosure/announcement/c/202605/002178_20260525_V4H0.pdf | H6: 综合毛利率、2026Q1 经审阅数据、同业对比
B7: S4 | C7: 《招股意向书》全文 | D7: 发行人（新浪财经公告库转引） | E7: 一手·转引 | F7: 2026-07-31 | G7: https://vip.stock.finance.sina.com.cn/corp/view/vCB_AllBulletinDetail.php?CompanyCode=82494861&gather=1&id=12470775 | H7: 境外主营收入及占比、汇兑、审计截止日后财务信息
B8: S5 | C8: 《首次公开发行股票科创板上市公告书》 | D8: 发行人/上海证券报 | E8: 一手·交易所 | F8: 2026-08-17 | G8: http://paper.cnstock.com/html/2026-08/18/content_2255912.htm（提示性公告）；全文数据见新浪/澎湃转引 | H8: 2026H1 实际业绩、资产负债、发行上市概况
B9: S6 | C9: 《发行公告》《投资风险特别公告》《发行结果公告》 | D9: 发行人/巨潮·上证报 | E9: 一手·转引 | F9: 2026-08-07 | G9: https://static.cninfo.com.cn/finalpage/2026-08-07/1225462415.PDF | H9: 发行价、发行数量、募资总额/净额、发行市盈率
B10: S7 | C10: 浦银国际《宇树招股书解读：六大维度看全球机器人龙头商业落地》 | D10: 浦银国际 | E10: 二手·研报转引 | F10: 2026-03-24 | G10: https://www.spdbi.com（研报PDF） | H10: 2022-2024 及 2025 1-9M 分产品/分地区/应用场景明细（申报稿口径）
B11: S8 | C11: 兴业证券《全球通用机器人领军企业》研报 | D11: 兴业证券 | E11: 二手·研报转引 | F11: 2026-08-11 | G11: 慧博投研资讯 hibor.com.cn | H11: 2025 四足销量 23,037 台、收入 69,762.56 万元、单价（注册稿口径）
B12: S9 | C12: 国信证券《人形机器人本体系列之宇树科技招股书梳理》 | D12: 国信证券 | E12: 二手·研报转引 | F12: 2026-08-22 | G12: 慧博投研资讯 hibor.com.cn | H12: 2025 产品结构（营业收入口径）交叉核对
B13: S10 | C13: 东方财富/证券时报·数据中心 688836 财务指标 | D13: 数据商 | E13: 二手·数据聚合 | F13: 2026-08-29起 | G13: https://data.eastmoney.com/stockdata/688836.html；https://stcn.com/quotes/index/sh688836.html | H13: 季度数据、2026H1 指标交叉核对
B14: S11 | C14: 公司官方网站与官方公开资料 | D14: 宇树科技 | E14: 公司官方 | F14: 持续 | G14: https://www.unitree.com；ir@unitree.com | H14: 产品线、技术与业务介绍（H1/G1/Go2/B2 等）
B16: 注：S7~S10 为二手转引/数据聚合，仅用于交叉核对与补充明细；如与 S1~S5 一手披露不一致，以一手披露为准。

Sheet 02_原始数据_年度
B1: 年度原始数据（单位：万元；比率除外；注册稿最终口径）
B2: （金额万元，比率为%；A=已实现并经审计）
B3: 项目 | C3: 2023A | D3: 2024A | E3: 2025A | F3: 来源 | G3: 备注
B4: 一、经营规模
B5: 营业收入 | C5: 15913.44 | D5: 39277.07 | E5: 169926.93 | F5: S2 | G5: 注册稿；申报稿曾为170,820.87，以注册稿为准
B6: 主营业务收入 | C6: 15753.65 | D6: 38727.28 | E6: 167611.09 | F6: S1/S7 | G6: 2025=境内94,445.56+境外73,165.53
B7: 其他业务收入 | C7: =C5-C6 -> 159.79 | D7: =D5-D6 -> 549.79 | E7: =E5-E6 -> 2315.84 | F7: 计算 | G7: =营业收入-主营业务收入 -> #NAME?
B8: 二、盈利能力
B9: 归母净利润 | C9: -1114.51 | D9: 9547.47 | E9: 27821.05 | F9: S2 | G9: 2023亏损，2024扭亏
B10: 扣非后归母净利润 | C10: -1801.91 | D10: 7847.65 | E10: 59075.28 | F10: S2 | G10: 2025扣非高于归母，因非经常性项目为净损失(主要为股份支付)
B11: 非经常性损益 | C11: =C9-C10 -> 687.4 | D11: =D9-D10 -> 1699.82 | E11: =E9-E10 -> -31254.23 | F11: 计算
B12: 主营业务毛利率 | C12: 0.4422 | D12: 0.5674 | E12: 0.6013 | F12: S2 | G12: 披露值
B13: 综合毛利率 | C13: 0.4475 | D13: 0.5722 | E13: 0.6044 | F13: S3 | G13: 披露值，与主营毛利率口径略异
B14: 扣非后加权平均ROE | C14: -0.0592 | D14: 0.086 | E14: 0.287 | F14: S2 | G14: 披露值
B15: 基本每股收益(元/股) | E15: 0.76 | F15: S2 | G15: 2023/2024股改前口径不可比，留空
B16: 三、期间费用与外包
B17: 研发费用 | C17: 4995.18 | D17: 7001.7 | E17: 14496.56 | F17: S2 | G17: 三年累计26,493.44万元
B18: 销售费用 | C18: 3771.83 | D18: 5915.85 | E18: 14120.93 | F18: S1/媒体 | G18: 2025约1.41亿、按披露销售费用率8.31%反推=14,120.93，精确值待核
B19: 劳务外包费用 | C19: 1161.69 | D19: 1922.26 | E19: 6802.65 | F19: S2 | G19: 装配环节外包
B20: 四、资产、权益与现金流（期末/当期）
B21: 资产总额 | C21: 39127.15 | D21: 152786.94 | E21: 320853.83 | F21: S2 | G21: 期末数
B22: 归母所有者权益 | C22: 29904.49 | D22: 128054.9 | E22: 260465.85 | F22: S2 | G22: 期末数
B23: 资产负债率(合并) | C23: 0.2357 | D23: 0.1619 | E23: 0.1882 | F23: S2 | G23: 披露值
B24: 经营活动现金流量净额 | C24: 494.25 | D24: 19239.13 | E24: 66998.18 | F24: S2 | G24: 当期数
B25: 五、人员（期末，人）
B26: 员工总数 | E26: 516 | F26: S2 | G26: 仅取得2025年末数
B27: 研发人员 | E27: 184 | F27: S2 | G27: 占员工35.66%
B28: 研发人员占比 | E28: =E27/E26 -> 0.35658915 | F28: 计算 | G28: =研发人员/员工总数 -> #NAME?

Sheet 03_原始数据_期间
B1: 期间数据：实际(A) 与 2026H1 业绩预告预测(E) 分列（万元）
B3: 一、已实现数据（A：2025 年分期间为账面/披露数；2026Q1 经审阅；2026H1 取自上市公告书）
B4: 项目 | C4: 2025Q1A | D4: 2025H1A | E4: 2025 1-9MA | F4: 2025FYA | G4: 2026Q1A | H4: 2026H1A | I4: 备注/来源
B5: 营业收入 | C5: 25095.9 | D5: 77571.4 | E5: 116749.01 | F5: 169926.93 | G5: 42284.05 | H5: 115224.56 | I5: S3/S5/S10；2025Q1、H1由同比与1-9M数反推(约)，1-9M及以后为披露精确值
B6: 归母净利润 | C6: 9560 | D6: -3202.45 | E6: 10530 | F6: 27821.05 | G6: 5001.38 | H6: 27399.99 | I6: S5/S10；2025Q1约0.956亿、1-9M约1.053亿
B7: 扣非归母净利润 | C7: 8483.65 | D7: 30243.35 | E7: 43061.23 | F7: 59075.28 | G7: 4025.36 | H7: 24393.03 | I7: S3/S5/S10
B8: 经营活动现金流量净额 | D8: 34300 | E8: 42800 | F8: 66998.18 | G8: 3439.96 | H8: 23154.53 | I8: S5/S10；2025H1约3.43亿、1-9M约4.28亿(约数)
B9: 营业收入同比 | F9: 3.3264 | G9: 0.6849 | H9: 0.4854 | I9: S2/S3/S5 披露值
B10: 扣非归母同比 | G10: -0.5255 | H10: -0.1934 | I10: S3/S5 披露值
B11: 审计/审阅状态 | I11: 2025年度经审计；2026Q1经审阅；2026H1为上市公告书披露(未经审计)；浅黄=约数/反推，精确值以定期报告为准
B13: 二、2026 年上半年业绩预告（E=预测，公司 2026-05 上会稿披露；【非已实现事实】，仅作对照）
B14: 预测指标 | C14: 下限 | D14: 上限 | E14: 同比下限 | F14: 同比上限 | G14: 说明
B15: 2026H1 营业收入(E) | C15: 105200 | D15: 112800 | E15: 0.3562 | F15: 0.4541 | G15: 预测区间10.52亿~11.28亿
B16: 2026H1 归母净利润(E) | C16: 25800 | D16: 30600 | G16: 预测2.58亿~3.06亿，上年同期-3,202.45万(扭亏)
B17: 2026H1 扣非归母(E) | C17: 23600 | D17: 28300 | E17: -0.2197 | F17: -0.0643 | G17: 预测2.36亿~2.83亿，同比-21.97%~-6.43%
B19: 三、预测 vs 实际对照（公式；实际取自上市公告书）
B20: 对照项 | C20: 实际值 | D20: 预测下限 | E20: 预测上限 | F20: 结论
B21: 2026H1 营业收入 | C21: =H5 -> 115224.56 | D21: =C15 -> 105200 | E21: =D15 -> 112800 | F21: =IF(C21>E21,"实际高于预测上限",IF(C21<D21,"实际低于预测下限","落在预测区间内")) -> 实际高于预测上限

Sheet 04_业务经营数据
B1: 业务经营数据（主营口径，金额万元；销量台；单价万元/台）
B3: 一、主营业务收入分产品（万元 / 占比）
B4: 产品 | C4: 2023A | D4: 2024A | E4: 2025A | F4: 来源 | G4: 备注
B5: 人形机器人收入 | C5: 296.71 | D5: 10689.76 | E5: 86783.19 | F5: S1/S8 | G5: 2025占主营51.78%，成第一大产品
B6: 四足机器人收入 | C6: 11938.09 | D6: 23054.37 | E6: 69762.56 | F6: S1/S8 | G6: 2025注册稿69,762.56
B7: 机器人组件收入 | C7: 2692.34 | D7: 4453.82 | F7: S7 | G7: 2025与其他合并轧差，见下
B8: 其他主营收入 | C8: 826.51 | D8: 529.33 | F8: S7
B9: 主营业务收入合计 | C9: =SUM(C5:C8) -> 15753.65 | D9: =SUM(D5:D8) -> 38727.28 | E9: =SUM(E5:E8) -> 156545.75 | F9: 计算 | G9: 分产品合计，应与02表主营一致
B10: 人形占比 | C10: =C5/C9 -> 0.018834365 | D10: =D5/D9 -> 0.27602661 | E10: =E5/E9 -> 0.55436312 | F10: 计算
B11: 四足占比 | C11: =C6/C9 -> 0.75779835 | D11: =D6/D9 -> 0.59530052 | E11: =E6/E9 -> 0.44563688 | F11: 计算
B12: 组件+其他占比 | C12: =(C7+C8)/C9 -> 0.22336728 | D12: =(D7+D8)/D9 -> 0.12867286 | E12: =(E9-E5-E6)/E9 -> 0 | F12: 计算 | G12: 2025=轧差数11,065.34(约6.6%)，其中组件约1.04亿待核
B14: 二、销量（台）与平均单价（万元/台，=收入/销量）
B15: 指标 | C15: 2023A | D15: 2024A | E15: 2025A | F15: 来源 | G15: 备注
B16: 人形机器人销量(台) | C16: 5 | D16: 412 | E16: 5215 | F16: S1/上证报 | G16: 2024最终412台(申报稿曾为410)
B17: 四足机器人销量(台) | C17: 3121 | D17: 7136 | E17: 23037 | F17: S7/S8 | G17: 三年合计33,294台(超3.3万台)
B18: 人形平均单价 | C18: =C5/C16 -> 59.342 | D18: =D5/D16 -> 25.946019 | E18: =E5/E16 -> 16.641072 | F18: 计算 | G18: 披露59.34→26.04→16.64；2024按注册稿销量412台机械相除得25.95，与披露26.04差于版本修订，以披露为准
B19: 四足平均单价 | C19: =C6/C17 -> 3.8250849 | D19: =D6/D17 -> 3.2307133 | E19: =E6/E17 -> 3.0282832 | F19: 计算 | G19: 3.83→3.23→3.03
B21: 三、主营业务收入分地区（万元 / 占比）
B22: 地区 | C22: 2023A | D22: 2024A | E22: 2025A | F22: 来源 | G22: 备注
B23: 境内收入 | C23: 6989.41 | D23: 17116.54 | E23: 94445.56 | F23: S4/S1 | G23: 2024=主营-境外轧差(申报稿17,156.55略有修订)
B24: 境外收入 | C24: 8764.24 | D24: 21610.74 | E24: 73165.53 | F24: S4 | G24: 占比55.63%→55.74%→43.65%
B25: 主营合计 | C25: =SUM(C23:C24) -> 15753.65 | D25: =SUM(D23:D24) -> 38727.28 | E25: =SUM(E23:E24) -> 167611.09 | F25: 计算
B26: 境外占比 | C26: =C24/C25 -> 0.55633076 | D26: =D24/D25 -> 0.5580237 | E26: =E24/E25 -> 0.43651962 | F26: 计算
B28: 四、下游应用场景结构（2025年1-9月，占该产品收入比，申报稿口径）
B29: 产品/场景 | C29: 科研教育 | D29: 商业消费 | E29: 行业应用 | F29: 来源 | G29: 备注
B30: 人形机器人 | C30: 0.736 | D30: 0.1739 | E30: 0.0901 | F30: S7 | G30: 人形仍高度依赖科研教育(73.6%)
B31: 四足机器人 | C31: 0.3158 | D31: 0.423 | E31: 0.2612 | F31: S7 | G31: 场景相对均衡
B33: 五、出货地位与人员
B34: 2025年人形机器人出货 | C34: 超5,500台（纯人形，不含轮式双臂），公司称出货量全球第一；确认收入口径销量5,215台（S1/S2）
B35: 四足机器人 | C35: 报告期(2023-2025)销量合计超3.3万台，全球份额领先（S2）
B36: 员工 | C36: 2025年末516人，其中研发184人、占35.66%（S2）
B37: 产能现状 | C37: 2025年前三季度人形产销率超95%，基本满产满销（S7）

Sheet 05_核心计算
B1: 核心计算（全部为 Excel 公式，绿色=跨表引用；修改原始数据后自动重算）
B3: 指标 | C3: 2023A | D3: 2024A | E3: 2025A | F3: 2026H1A | G3: 口径/公式说明
B4: 营业收入同比增速 | D4: ='02_原始数据_年度'!D5/'02_原始数据_年度'!C5-1 -> 1.4681697 | E4: ='02_原始数据_年度'!E5/'02_原始数据_年度'!D5-1 -> 3.3263647 | F4: ='03_原始数据_期间'!H5/'03_原始数据_期间'!D5-1 -> 0.48540003 | G4: 本期/上年同期-1；2026H1对比2025H1
B5: 营业收入2年CAGR(23→25) | E5: =('02_原始数据_年度'!E5/'02_原始数据_年度'!C5)^(1/2)-1 -> 2.2677519 | G5: (末值/起值)^(1/年数)-1，披露值226.78%
B6: 归母净利润同比 | D6: ='02_原始数据_年度'!D9/ABS('02_原始数据_年度'!C9)*SIGN('02_原始数据_年度'!D9) -> 8.566518 | E6: ='02_原始数据_年度'!E9/'02_原始数据_年度'!D9-1 -> 1.9139709 | F6: ='03_原始数据_期间'!H6/'03_原始数据_期间'!D6-1 -> -9.5559462 | G6: 2023为负，2024同比按扭亏口径展示
B7: 扣非归母同比 | E7: ='02_原始数据_年度'!E10/'02_原始数据_年度'!D10-1 -> 6.5277669 | F7: ='03_原始数据_期间'!H7/'03_原始数据_期间'!D7-1 -> -0.19344153 | G7: 2026H1扣非同比-19.34%
B8: 销售净利率(归母/营收) | C8: ='02_原始数据_年度'!C9/'02_原始数据_年度'!C5 -> -0.070035769 | D8: ='02_原始数据_年度'!D9/'02_原始数据_年度'!D5 -> 0.24308 | E8: ='02_原始数据_年度'!E9/'02_原始数据_年度'!E5 -> 0.16372361 | F8: ='03_原始数据_期间'!H6/'03_原始数据_期间'!H5 -> 0.23779644 | G8: 归母净利润/营业收入
B9: 扣非净利率(扣非/营收) | C9: ='02_原始数据_年度'!C10/'02_原始数据_年度'!C5 -> -0.11323196 | D9: ='02_原始数据_年度'!D10/'02_原始数据_年度'!D5 -> 0.19980233 | E9: ='02_原始数据_年度'!E10/'02_原始数据_年度'!E5 -> 0.34765108 | F9: ='03_原始数据_期间'!H7/'03_原始数据_期间'!H5 -> 0.21169992 | G9: 扣非归母/营业收入，2025达34.8%
B10: 研发费用率 | C10: ='02_原始数据_年度'!C17/'02_原始数据_年度'!C5 -> 0.31389693 | D10: ='02_原始数据_年度'!D17/'02_原始数据_年度'!D5 -> 0.17826432 | E10: ='02_原始数据_年度'!E17/'02_原始数据_年度'!E5 -> 0.085310551 | G10: 研发费用/营业收入，核对披露31.39/17.83/8.53%
B11: 销售费用率 | C11: ='02_原始数据_年度'!C18/'02_原始数据_年度'!C5 -> 0.23702166 | D11: ='02_原始数据_年度'!D18/'02_原始数据_年度'!D5 -> 0.15061841 | E11: ='02_原始数据_年度'!E18/'02_原始数据_年度'!E5 -> 0.083100012 | G11: 销售费用/营业收入；2025销售费用为约数(浅黄)
B12: 研发+销售费用合计 | C12: ='02_原始数据_年度'!C17+'02_原始数据_年度'!C18 -> 8767.01 | D12: ='02_原始数据_年度'!D17+'02_原始数据_年度'!D18 -> 12917.55 | E12: ='02_原始数据_年度'!E17+'02_原始数据_年度'!E18 -> 28617.49 | G12: 万元
B13: 非经常性损益(归母-扣非) | C13: ='02_原始数据_年度'!C11 -> 687.4 | D13: ='02_原始数据_年度'!D11 -> 1699.82 | E13: ='02_原始数据_年度'!E11 -> -31254.23 | G13: 2025为-3.13亿，主要系股份支付费用
B14: 经营现金流/营收(CFO含金量) | C14: ='02_原始数据_年度'!C24/'02_原始数据_年度'!C5 -> 0.031058652 | D14: ='02_原始数据_年度'!D24/'02_原始数据_年度'!D5 -> 0.48983109 | E14: ='02_原始数据_年度'!E24/'02_原始数据_年度'!E5 -> 0.39427641 | F14: ='03_原始数据_期间'!H8/'03_原始数据_期间'!H5 -> 0.20095134 | G14: CFO/营业收入
B15: 经营现金流/归母净利润 | C15: =IF('02_原始数据_年度'!C9=0,"",'02_原始数据_年度'!C24/'02_原始数据_年度'!C9) -> -0.44346843 | D15: ='02_原始数据_年度'!D24/'02_原始数据_年度'!D9 -> 2.0151024 | E15: ='02_原始数据_年度'!E24/'02_原始数据_年度'!E9 -> 2.408183 | F15: ='03_原始数据_期间'!H8/'03_原始数据_期间'!H6 -> 0.84505615 | G15: 盈利现金保障倍数
B16: 资产总额同比 | D16: ='02_原始数据_年度'!D21/'02_原始数据_年度'!C21-1 -> 2.9048829 | E16: ='02_原始数据_年度'!E21/'02_原始数据_年度'!D21-1 -> 1.1000082 | G16: 期末口径
B17: 2025人均营业收入(万元/人) | E17: ='02_原始数据_年度'!E5/'02_原始数据_年度'!E26 -> 329.31576 | G17: 仅2025有年末员工数
B18: 2026H1营收/2025全年 | F18: ='03_原始数据_期间'!H5/'02_原始数据_年度'!E5 -> 0.67808299 | G18: 半年完成去年全年比重
B20: 单季度拆分（由期间累计数相减得到，万元）
B21: 单季 | C21: 2025Q2 | D21: 2025Q3 | E21: 2025Q4 | F21: 2026Q2 | G21: 说明
B22: 单季营业收入 | C22: ='03_原始数据_期间'!D5-'03_原始数据_期间'!C5 -> 52475.5 | D22: ='03_原始数据_期间'!E5-'03_原始数据_期间'!D5 -> 39177.61 | E22: ='03_原始数据_期间'!F5-'03_原始数据_期间'!E5 -> 53177.92 | F22: ='03_原始数据_期间'!H5-'03_原始数据_期间'!G5 -> 72940.51 | G22: 累计值相减
B23: 单季归母净利润 | C23: ='03_原始数据_期间'!D6-'03_原始数据_期间'!C6 -> -12762.45 | D23: ='03_原始数据_期间'!E6-'03_原始数据_期间'!D6 -> 13732.45 | E23: ='03_原始数据_期间'!F6-'03_原始数据_期间'!E6 -> 17291.05 | F23: ='03_原始数据_期间'!H6-'03_原始数据_期间'!G6 -> 22398.61 | G23: 2025Q2亏损主因股份支付
B24: 单季扣非归母 | C24: ='03_原始数据_期间'!D7-'03_原始数据_期间'!C7 -> 21759.7 | D24: ='03_原始数据_期间'!E7-'03_原始数据_期间'!D7 -> 12817.88 | E24: ='03_原始数据_期间'!F7-'03_原始数据_期间'!E7 -> 16014.05 | F24: ='03_原始数据_期间'!H7-'03_原始数据_期间'!G7 -> 20367.67

Sheet 06_IPO与募投
B1: IPO 发行方案、估值历程与募投项目
B3: 一、发行上市方案
B4: 股票简称/代码 | C4: 宇树科技 / 688836.SH | D4: S5/S6 | E4: 科创板，扩位简称同
B5: 上市日期 | C5: 2026-08-19 | D5: S5
B6: 发行价格(元/股) | C6: 150.8 | D6: S6
B7: 本次公开发行数量(万股) | C7: 4044.6434 | D7: S6 | E7: 占发行后总股本10.00%
B8: 发行后总股本(万股) | C8: 40446.434 | D8: S5
B9: 发行募资总额(亿元) | C9: 60.99 | D9: S6 | E9: 按150.80元×4,044.6434万股
B10: 发行募资净额(亿元) | C10: 59.17 | D10: S6 | E10: 扣除发行费用
B11: 发行时市值(亿元) | C11: 609.93 | D11: S5/S6 | E11: 发行价×发行后总股本
B12: 发行市盈率(倍) | C12: 219.23 | D12: 媒体(待核) | E12: 按2025归母口径，数据见媒体，需以发行公告原文核验
B13: 上市标准 | C13: 预计市值≥100亿元(科创板规则2.1.4条第一款) | D13: S2 | E13: 具有表决权差异安排
B14: 实际控制人 | C14: 王兴兴，发行后持股21.44%；上市前直接持股23.82%、合计控制68.78%表决权 | D14: S5/S7 | E14: 同股不同权
B16: 二、估值历程（亿元）
B17: 时点 | C17: 投前估值 | D17: 投后/发行市值 | E17: 说明
B18: 2025-06 Pre-IPO轮 | C18: 120 | D18: 127 | E18: 最近一次市场化股权融资(S2)
B19: 2026-08 IPO发行 | D19: 609.93 | E19: 发行价对应市值(S6)
B21: 三、原拟募投项目（招股书披露，万元；实际募资60.99亿元为超募）
B22: 项目 | C22: 拟投入(万元) | D22: 占比 | E22: 性质
B23: 智能机器人模型研发项目 | C23: 202200 | D23: =C23/C27 -> 0.48131397 | E23: 具身大模型(大脑/小脑)
B24: 机器人本体研发项目 | C24: 111000 | D24: =C24/C27 -> 0.2642228 | E24: 本体与结构
B25: 新型智能机器人产品开发项目 | C25: 44500 | D25: =C25/C27 -> 0.10592716 | E25: 新产品开发
B26: 智能机器人制造基地建设项目 | C26: 62400 | D26: =C26/C27 -> 0.14853606 | E26: 达产规划年产能：人形7.5万台、四足11.5万台（规划，非已实现）
B27: 合计 | C27: =SUM(C23:C26) -> 420100 | D27: =C27/C27 -> 1 | E27: 原拟募资420,171.12万元(约42.02亿)；表内为约数，精确分项目金额以招股书为准(待核)

Sheet 07_趋势图表
B1: 趋势图表（原生 Excel 图表，数据源为下方公式链接区，可编辑、随原始数据更新）
B3: 图1数据源：年度营收与扣非归母（万元）
B4: 年份 | C4: 营业收入 | D4: 扣非归母净利润
B5: 2023A | C5: ='02_原始数据_年度'!C5 -> 15913.44 | D5: ='02_原始数据_年度'!C10 -> -1801.91
B6: 2024A | C6: ='02_原始数据_年度'!D5 -> 39277.07 | D6: ='02_原始数据_年度'!D10 -> 7847.65
B7: 2025A | C7: ='02_原始数据_年度'!E5 -> 169926.93 | D7: ='02_原始数据_年度'!E10 -> 59075.28
B9: 图2数据源：年度盈利能力与费用率（%）
B10: 年份 | C10: 主营毛利率 | D10: 销售净利率 | E10: 扣非净利率 | F10: 研发费用率
B11: 2023A | C11: ='02_原始数据_年度'!C12 -> 0.4422 | D11: ='05_核心计算'!C8 -> -0.070035769 | E11: ='05_核心计算'!C9 -> -0.11323196 | F11: ='05_核心计算'!C10 -> 0.31389693
B12: 2024A | C12: ='02_原始数据_年度'!D12 -> 0.5674 | D12: ='05_核心计算'!D8 -> 0.24308 | E12: ='05_核心计算'!D9 -> 0.19980233 | F12: ='05_核心计算'!D10 -> 0.17826432
B13: 2025A | C13: ='02_原始数据_年度'!E12 -> 0.6013 | D13: ='05_核心计算'!E8 -> 0.16372361 | E13: ='05_核心计算'!E9 -> 0.34765108 | F13: ='05_核心计算'!E10 -> 0.085310551
B15: 图3数据源：分产品收入（万元）
B16: 年份 | C16: 人形机器人 | D16: 四足机器人 | E16: 组件及其他
B17: 2023A | C17: ='04_业务经营数据'!C5 -> 296.71 | D17: ='04_业务经营数据'!C6 -> 11938.09 | E17: ='04_业务经营数据'!C5*0+'04_业务经营数据'!C7+'04_业务经营数据'!C8 -> 3518.85
B18: 2024A | C18: ='04_业务经营数据'!D5 -> 10689.76 | D18: ='04_业务经营数据'!D6 -> 23054.37 | E18: ='04_业务经营数据'!D7+'04_业务经营数据'!D8 -> 4983.15
B19: 2025A | C19: ='04_业务经营数据'!E5 -> 86783.19 | D19: ='04_业务经营数据'!E6 -> 69762.56 | E19: ='04_业务经营数据'!E12*'04_业务经营数据'!E9 -> 0
B21: 图4数据源：分地区收入（万元）
B22: 年份 | C22: 境内 | D22: 境外
B23: 2023A | C23: ='04_业务经营数据'!C23 -> 6989.41 | D23: ='04_业务经营数据'!C24 -> 8764.24
B24: 2024A | C24: ='04_业务经营数据'!D23 -> 17116.54 | D24: ='04_业务经营数据'!D24 -> 21610.74
B25: 2025A | C25: ='04_业务经营数据'!E23 -> 94445.56 | D25: ='04_业务经营数据'!E24 -> 73165.53
B27: 图5数据源：单季营业收入（万元，累计相减）
B28: 季度 | C28: 营业收入
B29: 2025Q1 | C29: ='03_原始数据_期间'!C5 -> 25095.9
B30: 2025Q2 | C30: ='03_原始数据_期间'!D5-'03_原始数据_期间'!C5 -> 52475.5
B31: 2025Q3 | C31: ='03_原始数据_期间'!E5-'03_原始数据_期间'!D5 -> 39177.61
B32: 2025Q4 | C32: ='03_原始数据_期间'!F5-'03_原始数据_期间'!E5 -> 53177.92
B33: 2026Q1 | C33: ='03_原始数据_期间'!G5 -> 42284.05
B34: 2026Q2 | C34: ='03_原始数据_期间'!H5-'03_原始数据_期间'!G5 -> 72940.51
B36: 图6数据源：人形机器人销量(台)与单价(万元/台)
B37: 年份 | C37: 销量(台) | D37: 平均单价
B38: 2023A | C38: ='04_业务经营数据'!C16 -> 5 | D38: ='04_业务经营数据'!C18 -> 59.342
B39: 2024A | C39: ='04_业务经营数据'!D16 -> 412 | D39: ='04_业务经营数据'!D18 -> 25.946019
B40: 2025A | C40: ='04_业务经营数据'!E16 -> 5215 | D40: ='04_业务经营数据'!E18 -> 16.641072

Sheet 08_分析结论
B1: 经营与财务分析结论（结论后附数据支撑位置；截至2026-08-30）
B3: 主题 | C3: 分析结论 | D3: 数据支撑
B4: 1 高增长但增速换挡 | C4: 2023-2025营收1.59→3.93→16.99亿元，2年CAGR约226.8%；但增速逐期回落：2025全年+332.6%→2026Q1+68.5%→2026H1+48.5%，公司明确归因于基数抬高、行业热度缓和与竞争加剧，高增速阶段正在过去。 | D4: 02表营业收入；05表CAGR/同比；03表期间同比
B5: 2 盈利：扣非强、归母受股份支付扰动 | C5: 2024扭亏，2025扣非归母5.91亿、扣非净利率约34.8%、主营毛利率60.1%（全栈自研、核心零部件自产支撑高毛利）；但2025归母仅2.78亿，差额-3.13亿为非经常性损失（主要是股权激励股份支付）。分析盈利质量应以扣非口径为主。 | D5: 02表归母/扣非/非经常性损益/毛利率；05表扣非净利率
B6: 3 2026利润端承压 | C6: 2026H1营收11.52亿(+48.5%)、归母2.74亿(同比扭亏，因上年同期含3.49亿股份支付低基数)，但扣非2.44亿、同比-19.3%；2026Q1扣非-52.6%。主因研发费用(上半年同比+0.82亿)与销售费用(春晚品牌推广、销售扩编，H1销售费用1.64亿)快速扩张。 | D6: 03表实际数；05表单季拆分；04表费用
B7: 4 产品结构切换、量增价减 | C7: 人形机器人收入由2023年296.71万(占1.88%)升至2025年8.68亿(占主营51.78%)，超过四足成为第一大产品；销量5→412→5,215台，单价59.34→26.04→16.64万元/台(G1下探至10万级)。四足仍是基本盘(6.98亿、23,037台、单价降至3.03万)。 | D7: 04表分产品/销量/单价；07图3、图6
B8: 5 地区：境内放量、境外占比回落 | C8: 境外收入0.88→2.16→7.32亿元，占主营55.63%→55.74%→43.65%；2025境内9.44亿(56.35%)反超，主要系国内人形需求与春晚效应；海外仍为重要市场，需关注汇率与外销结算风险。 | D8: 04表分地区；07图4
B9: 6 现金流与资产负债表 | C9: 经营现金流净额0.05→1.92→6.70亿元，2025 CFO/营收约39.4%、现金对利润覆盖充分；合并资产负债率仅18.82%、低杠杆。2026H1末总资产38.45亿(较年初+19.85%)、负债率回升至25.11%(合同负债、应付及租赁负债增加)，CFO 2.32亿同比-32.5%需跟踪。 | D9: 02表资产/权益/负债/CFO；05表现金含量；03表2026H1
B10: 7 研发：强度下降、绝对额上升 | C10: 研发费用0.50→0.70→1.45亿元，费用率31.39%→17.83%→8.53%（规模摊薄而非缩减）；研发人员184人、占35.66%；IPO原拟募资42.02亿中约85%(35.77亿)投向模型/本体/新产品研发，战略向具身大模型倾斜。 | D10: 02表研发；06表募投；05表研发费率
B11: 8 主要风险 | C11: ①人形机器人2025 1-9M约73.6%收入来自科研教育、行业应用仅约9%，规模化工业商业化尚早；②价格战与降价趋势压制单价/毛利；③股份支付等非经常项持续扰动表观利润；④2026费用扩张可能继续压制扣非利润；⑤发行市盈率高、估值波动大；⑥装配依赖劳务外包。 | D11: 04表应用场景；06表发行方案；02表外包费用
B12: 9 预测与实际严格区分 | C12: 公司2026-05曾预测2026H1营收10.52-11.28亿、扣非2.36-2.83亿(预测E)；上市公告书披露实际营收11.52亿、扣非2.44亿——营收略超预测上限，扣非落在区间内。预测仅作参照，不应当作既成事实。 | D12: 03表第二、三区块

Sheet 09_待人工核验
B1: 仍需人工核验事项（底稿中以浅黄底标注者同属此类）
B3: 序号 | C3: 待核验事项 | D3: 原因 / 建议核对位置 | E3: 当前底稿处理
B4: 1 | C4: 以S1招股说明书注册稿PDF原文复核全部年度数字 | D4: 本底稿年度数主要取自S2上市保荐书摘要表，应与招股书『财务会计信息』章节逐字核对 | E4: 已采用注册稿口径，差异处已备注
B5: 2 | C5: 2025年销售费用精确值 | D5: 媒体称约1.41亿、按披露费率8.31%反推为14,120.93万 | E5: 浅黄标注为约数
B6: 3 | C6: 2025年管理费用、财务费用及期间费用明细 | D6: 仅取得管理费用约3.64亿(含股份支付)的媒体口径，未取得三年完整序列 | E6: 未填列，避免编造
B7: 4 | C7: 2025年分产品中'机器人组件'与'其他主营'精确拆分 | D7: 仅取得组件约1.04亿，精确值需查招股书收入附注 | E7: 以轧差合并列示并备注
B8: 5 | C8: 2025Q1、2025H1部分数据为反推/约数 | D8: 由后续累计数与同比反推(浅黄格)，需以2025半年报/三季报原文替换 | E8: 已浅黄标注
B9: 6 | C9: 2026H1数据的审计状态与精确金额 | D9: 取自上市公告书转引(营收115,224.56、归母27,399.99、扣非24,393.03、CFO23,154.53)，正式半年报披露后应替换核对 | E9: 已标注未经审计
B10: 7 | C10: 发行市盈率219.23倍、初始流通比例7.44% | D10: 来自媒体，需以S6发行公告/发行结果公告原文核验 | E10: 浅黄标注待核
B11: 8 | C11: 原拟募投四项目精确到万元的金额 | D11: 本表按20.22/11.10/4.45/6.24亿元约数填列(合计约42.02亿) | E11: 已标注为约数
B12: 9 | C12: 应用场景结构为2025年1-9月(申报稿)口径 | D12: 非全年口径，且后续注册稿可能修订 | E12: 已明确标注期间与口径
B13: 10 | C13: 境外收入分国别/币种、汇兑损益、客户与供应商集中度 | D13: 本次未取得完整明细 | E13: 未纳入，建议补充
B14: 11 | C14: 二级市场股价/市值 | D14: 属资料截止日(8-30)后波动数据，本底稿仅保留发行时市值609.93亿，不纳入后续行情 | E14: 按截止日剔除
B15: 12 | C15: 研报转引数据(S7-S10) | D15: 均为二手，需回溯招股书对应表格原文 | E15: 已标注来源级别
